Workbook
Name CU?: 'Waterfall (10-yr-S1)'!$A$6
Name Equity_Share_GP: 'Waterfall (10-yr-S1)'!$C$9
Name Equity_Share_LP: 'Waterfall (10-yr-S1)'!$C$10
Name Preferred_Return: 'Waterfall (10-yr-S1)'!$E$15
Name Total_Equity: 'Waterfall (10-yr-S1)'!$D$11
Name CU?: 'Waterfall (5-yr-S1)'!$A$6
Name Equity_Share_GP: 'Waterfall (5-yr-S1)'!$C$9
Name Equity_Share_LP: 'Waterfall (5-yr-S1)'!$C$10
Name Preferred_Return: 'Waterfall (5-yr-S1)'!$E$15
Name Total_Equity: 'Waterfall (5-yr-S1)'!$D$11

Sheet Extraction Check
B2: EXTRACTION CHECK — SOURCE RECONCILIATION
B3: What the model pulled from the documents, and whether it ties to the source. Review before trusting the underwriting.
B5: REPORTING PERIOD USED
B6: Period used | C6: Monthly recap 11/01/24 - 10/31/25
B7: Date range | C7: Nov 2024 - Oct 2025
B8: Months covered | C8: 12
B9: Other periods seen in doc | C9: Monthly recap 11/01/24 - 10/31/25 (accrual basis), PRO FORMA
B10: Notes | C10: The document contains one T12 period (Nov 2024 - Oct 2025) with 12 monthly columns (NOV 24 through OCT 25) plus a PRO FORMA column. The T12 TOTAL column (O) is the operative annual figure. PRO FORMA is a forward-looking projection and was not used.
B12: RECONCILIATION CHECKS
B13: ⚠ 3 FAILED, 2 warnings, 63 passed — review the failures before using these numbers.
B14: Item | C14: Check | D14: Status | E14: Detail
B15: Rent roll rows vs unit count | C15: Rent roll long | D15: ✗ FAIL | E15: 127 rows but only 109 units stated — verify unit count or check for non-unit rows.
B16: POH count vs rent roll | C16: User stated 0 POH | D16: ✗ FAIL | E16: User stated 0 park-owned homes but the rent roll has home rent entries. Use the rent-roll count as authoritative — the user input was wrong.
B17: Rent-roll vs income parity: Retail/Commercial | C17: Expect non-zero 'Retail Income' income | D17: ✗ FAIL | E17: Rent roll has 2 occupied Retail/Commercial unit(s) but 'Retail Income' income totals $0. The LLM likely collapsed this revenue into another category (most often Gross Potential Rent).
B18: Multiple periods in doc | C18: Picked most recent T12 | D18: ⚠ WARN | E18: Document had 2 period columns: Monthly recap 11/01/24 - 10/31/25 (accrual basis), PRO FORMA. Confirm the right one was used.
B19: Methodology schema validation | C19: Per-line Pydantic check | D19: ⚠ WARN | E19: expenses[6]: Value error, Repair and Maintenance (5107 Septic + 5108 Plumbing + 5109 Misc + 5110 Equipment + 5111 Electrical + 5200 Park Supplies): monthly sum $9,733.42 != t12Total $10,414.78 (diff $681.36, 6.5%)
B20: Reporting period | C20: T12 (12 months) | D20: ✓ OK | E20: Monthly recap 11/01/24 - 10/31/25 (Nov 2024 - Oct 2025)
B21: Income: 4101 Lot Rent | C21: Monthlies sum to annual | D21: ✓ OK | E21: Σmonthly=1,144,604 vs annual=1,144,604
B22: Income: 4103 Long Term RV Lot Rent | C22: Monthlies sum to annual | D22: ✓ OK | E22: Σmonthly=172,705 vs annual=172,705
B23: Income: 4108 Storage Unit Rent | C23: Monthlies sum to annual | D23: ✓ OK | E23: Σmonthly=900 vs annual=900
B24: Income: 4110 Retail Unit Rent | C24: Monthlies sum to annual | D24: ✓ OK | E24: Σmonthly=12,426 vs annual=12,426
B25: Income: 4131 Move in Specials | C25: Monthlies sum to annual | D25: ✓ OK | E25: Σmonthly=-168 vs annual=-168
... B82: Expense ratio | C82: 25–55% typical for MHC, 35–50% for hybrid | D82: ✓ OK | E82: Underwritten expense ratio = 37.4%

Sheet Miscellaneous
B2: PROPERTY OVERVIEW
B3: Location context, visuals, demographics, and qualitative assessment
B5: PROPERTY LINKS
B6: Property Name | C6: Whaleshead Beach Resort
B7: Address | C7: 19921 Whaleshead Road, Brookings, OR
B8: Property Type | C8: Hybrid
B9: Total Units | C9: 109
B10: County | C10: Curry
B11: Asking Price | C11: 10000000
B12: CoStar Link
B13: Property Website
B14: Broker / OM
B15: County Assessor
B16: FEMA Flood Map
B18: DEMOGRAPHICS
B19: County Population | C19: 21776
B20: 5-Year Population Growth | C20: -4.0%
B21: Median Household Income | C21: $62,244
B22: Unemployment Rate | C22: 5.4%
B23: Top Employers | C23: Curry Health Network / Curry Medical Center (Brookings) & Curry General Hospital (Gold Beach), Brookings-Harbor School District 17C, Curry County government, City of Brookings, Port of Brookings Harbor commercial fishing fleet (crab/salmon/tuna), Fred Meyer and local retail, Sutter Coast Hospital (Crescent City, CA - regional), OSU Extension / Southwestern Oregon Community College
B25: ALTERNATIVE HOUSING (affordability)
B26: Avg Single-Family Home Price | C26: $580,000
B27: Avg 1BR Apartment Rent | C27: $900/mo
B28: Avg 2BR Apartment Rent | C28: $1,477/mo
B29: Avg 3BR Apartment Rent | C29: $1,650/mo
B30: MHP All-In Monthly Cost | C30: $1,068/mo
B31: MHP Savings vs 2BR Apt | C31: 28.0%
B33: AERIAL & LOCATION MAP
B34: Satellite / Aerial | D34: Roadmap (with landmarks)
B51: STREET VIEW
B52: Main Entrance | D52: Interior Road
B69: Example Home #1 | D69: Example Home #2
B86: CLICKABLE URLs
B87: Aerial / Satellite | C87: https://www.google.com/maps/place/19921+Whaleshead+Rd,+Brookings,+OR+97415/@42.1547,-124.3556,1000m/data=!3m1!1e3
B88: Roadmap | C88: https://www.google.com/maps/search/?api=1&query=19921+Whaleshead+Road%2C+Brookings%2C+OR
B89: Street View — Main Entrance | C89: https://www.google.com/maps?q=19921+Whaleshead+Road,+Brookings,+OR+97415&layer=c
B90: Street View — Interior Road | C90: https://www.google.com/maps/@42.1547,-124.3556,3a,75y/data=!3m6!1e1
B91: Street View — Example Home #1 | C91: https://www.google.com/maps/search/Whaleshead+Beach+Resort+Brookings+OR
B92: Street View — Example Home #2 | C92: https://www.google.com/maps/search/19921+Whaleshead+Rd+Brookings+OR+homes
B93: Driving Directions | C93: https://www.google.com/maps/dir/Brookings,+OR/19921+Whaleshead+Rd,+Brookings,+OR+97415
B95: PROXIMITY TO KEY LANDMARKS
B96: Landmark Type | C96: Name / Address | E96: Distance (mi)
B97: Nearest Major Employer #1 | C97: Curry Medical Center (Curry Health Network), 500 5th St, Brookings | E97: 7
B98: Nearest Major Employer #2 | C98: Brookings-Harbor School District 17C | E98: 7.5
B99: Nearest Major Employer #3 | C99: Port of Brookings Harbor (commercial fishing fleet) | E99: 8
B100: Nearest Walmart / Big Box | C100: Fred Meyer, Brookings (nearest Walmart is Crescent City, CA ~30 mi) | E100: 7
B101: Nearest Grocery Store | C101: Grocery Outlet / Fred Meyer, Brookings | E101: 7
B102: Nearest Hospital / Urgent Care | C102: Curry Medical Center Urgent Care/ED, Brookings (Curry General Hospital, Gold Beach ~21 mi) | E102: 7
B103: Nearest Elementary School | C103: Kalmiopsis Elementary School, Brookings | E103: 7
B104: Nearest High School | C104: Brookings-Harbor High School, 625 Pioneer Rd | E104: 8
B105: Nearest Community College / University | C105: Southwestern Oregon Community College, Brookings campus (College of the Redwoods, Crescent City ~16 mi) | E105: 7
B106: Nearest Major Highway / Interstate | C106: US-101 (adjacent to Whaleshead Rd) | E106: 0.5
B107: Downtown (nearest city) | C107: Downtown Brookings | E107: 7
B108: Nearest Airport | C108: Del Norte County Regional Airport, Crescent City, CA (Medford Intl ~100 mi) | E108: 17
B110: DILIGENCE FLAGS
B111: HIGH | C111: Investment Criteria — Spread: DOES NOT MEET INVESTMENT CRITERIA: Stabilized Yield on Cost (9.66%) minus Ingoing Cap Rate (9.10%) = +56 bps, below GGC's 200 bps minimum spread. — Recommendation: Asset is already ~98% occupied with limited lot-rent upside, so value-add spread is thin. NOTE the absolute ingoing cap of 9.10% on the $10M ask is strong — recommend evaluating as a yield/cash-flow acquisition rather than a value-add deal. Deal fails the spread hurdle as currently structured.
B112: HIGH | C112: Unit Count Reconciliation: Rent roll shows 127 rows but property is stated at 109 units — rent_roll_long. Note: 107 WHA Lots + 1 Commercial + 1 Storage = 109 (matches stated count), but the 18 WHA RV sites appear to be excluded from the user's 109. True operating pad count is ~125 (107 MH lots + 18 RV). — Recommendation: Confirm with broker: does the 109 exclude the 18 long-term RV sites? Also reconcile the 'Caldeira, Ken' row (no unit #, RC=984) and the 124-tenant/126-unit summary discrepancy. Underwriting used 107 TOH lots + 18 RV + 2 retail/storage = 127 rent-roll rows.
B113: HIGH | C113: RV Income Decline: 4103 RV lot rent declined ~24% across the T12 ($17,051/mo -> ~$12,900/mo). — Recommendation: Underwrote at T3 annualized ($153,917) per declining-trend rule. Confirm cause — occupancy attrition, seasonal, or rate reductions. RV income is a riskier stream; consider capping it at a higher rate than MH lot rent.
B114: HIGH | C114: Bad Debt Underwriting: Underwritten bad debt ($52,331, ~4.2% of GPR) is ~2x seller historical T12 bad debt ($26,062). Driven by timing mismatch (rent roll dated 03/01/26 vs T12 ending 10/31/25). — Recommendation: Reconcile current rent-roll rents against actual T12 collections. Elevated late fees, legal fees, and a $10,327 single-month bad-debt charge corroborate real collection pressure — but verify the plug isn't overstating due to period mismatch.
B115: MEDIUM | C115: Payroll / Casual Labour Spike: 5703 Casual Labour = $10,400 in each of the final two months vs ~$200 average, while regular wages (5701) drop to ~$422/$0 in the same months. — Recommendation: Possible staffing transition (W-2 to contract) or one-time project. Confirm scope with seller. If one-time, exclude from payroll T12 x 1.03 basis.
B116: MEDIUM | C116: Ground Maintenance Spike: Months 11-12 spike to $5,729.84 and $6,000 (tree + grounds) vs ~$200 average. — Recommendation: Likely seasonal tree work/cleanup. Confirm if one-time; if so, exclude from T12 x 1.03 underwriting basis.
B117: MEDIUM | C117: Advertising Spike: Month 2 = $1,448 vs ~$93 average (~15.6x). — Recommendation: Likely one-time listing/campaign. Reviewer to decide exclusion.
B118: MEDIUM | C118: Insurance / Flood Zone: Coastal Oregon beach resort; flood zone status UNKNOWN. Per-unit insurance ~$301/pad at top of MHC benchmark. — Recommendation: Pull FEMA flood map — if not Zone X, apply 20.75% insurance trend override (currently only 5% applied). Also test GGC portfolio umbrella for potential premium reduction.
B119: MEDIUM | C119: Property Tax / Oregon Measure 50: Standard reassessment formula ($6.5M x ~0.85% = ~$55,250) far exceeds historical $15,391, but Oregon Measure 50 caps assessed-value growth at 3%/yr and does NOT reassess to market on sale. — Recommendation: Used fallback T12 x 1.15 = $17,699. Verify Curry County parcel and maximum assessed value; confirm no compression/exception triggers reassessment.
B120: MEDIUM | C120: Water System / Testing Burden: Recurring 5403 Water Testing ($12,049/yr) plus heavy 5402 W&S suggests a private well/water system. — Recommendation: Diligence on water treatment infrastructure, compliance, and potential capital needs — factor into CapEx plan.
B122: QUESTIONS FOR SELLER / BROKER
B123: #1 | C123: Does the user's 109-unit count exclude the 18 long-term RV sites? True operating pad count appears to be ~125 (107 MH lots + 18 RV).
B124: #2 | C124: What is driving the ~24% decline in long-term RV lot rent across the T12?
B125: #3 | C125: Confirm current rent-roll rents (dated 03/01/26) versus actual T12 collections — the period mismatch inflates the underwritten bad-debt plug.
B126: #4 | C126: Is the casual-labour spike in the final two months ($10,400 x2) a staffing transition or a one-time project? Is there an on-site manager receiving a comped lot (Employee Allowance)?
B127: #5 | C127: Provide FEMA flood zone determination for this coastal parcel.
B128: #6 | C128: Provide Curry County parcel number / current assessed value to confirm Measure 50 tax treatment.
B129: #7 | C129: Confirm the water system is a private well and provide compliance/testing history and any capital requirements.
B130: #8 | C130: Clarify the 'Caldeira, Ken' rent-roll row (no unit number, RC=984) and reconcile the 124-tenant / 126-unit / 127-row discrepancy.
B131: #9 | C131: Is the Rental Pool Revenue Sharing ($22,774) a sustainable recurring stream, and why is the final month $0?

Sheet Comps Analysis
B2: COMPS ANALYSIS — DETAILED COMPETITIVE SET
B3: Rent comps, sale comps, statistics, and subject-vs-market positioning
B5: INVESTMENT CRITERIA CHECK — 200 bps spread rule
B6: Ingoing Cap Rate | C6: Stabilized Yield on Cost | D6: Spread (bps) | E6: Hurdle | F6: Verdict
B7: 0.091 | C7: 0.0966 | D7: +56 bps | E7: ≥ 200 bps | F7: ✗ DOES NOT MEET INVESTMENT CRITERIA
B8: Spread is 56 bps — 144 bps short of the 200 bps hurdle. GGC does not pay for value it's creating; this deal would require either a lower purchase price or a more aggressive stabilized plan to clear.
B11: SUBJECT vs MARKET — KEY METRICS
B12: Metric | C12: Subject | D12: Comp Min | E12: Comp Max | F12: Comp Avg | G12: Comp Median | H12: Subject Position
B13: Lot Rent ($/mo) | C13: 966.38 | D13: 575 | E13: 740 | F13: 618 | G13: 600 | H13: 56.4% above avg
B14: # Sites | C14: 109 | D14: 20 | E14: 63 | F14: 44.6 | G14: 50
B15: Occupancy | C15: 0.984 | D15: 1 | E15: 1 | F15: 1 | G15: 1
B18: RENT COMPS (16 found)
B19: Property | C19: Location | D19: Distance | E19: # Sites | F19: Lot Rent | G19: Occupancy | H19: Year Built | I19: POH % | J19: Amenities | K19: Quality | L19: Source
B20: Sunset View Mobile Home Park | C20: Brookings, OR | D20: 7.0 mi | E20: 50 | F20: 740 | G20: 1 | H20: 1974 | J20: Off-street parking, paved streets, WiFi, pet-friendly (under 20 lbs), 55+ age-re | K20: ★★★ | L20: https://www.mhvillage.com/parks/22374
B21: Tamaroo Mobile Home Park | C21: Brookings, OR | D21: 7.2 mi | F21: 600 | J21: Paved average-width streets, well water, septic, off-street parking, 55+ age-res | K21: ★★★ | L21: https://www.mhbo.com/mobile-home-park/90764-tamaroo-mobile-home-park-16329-grootendorst-street-brookings-or-97415
B22: Brookings Mobile Home Park | C22: Brookings, OR | D22: 6.5 mi | F22: 600 | J22: All-ages, pet-friendly, city water/sewer, paved streets, near Hwy 101 and Chetco | K22: ★★★ | L22: https://www.mhbo.com/mobile-home-park/88472-brookings-mobile-home-park-16391-us-101-brookings-or-97415
B23: Driftwood Estates | C23: Harbor (Brookings), OR | D23: 8.0 mi | E23: 62 | F23: 575 | J23: 55+ community, minutes from beach, near Port of Brookings Harbor | K23: ★★★ | L23: https://www.mobilehome.net/mobile-home-parks/59111-harbor-hills-mh-park-in-brookings-or
B24: Harbor Hills MH Park | C24: Brookings, OR | D24: 8.0 mi | E24: 28 | J24: Highway-frontage manufactured home community | K24: ★★ | L24: https://www.mhbo.com/mobile-home-park/76579-harbor-hills-mh-park-15765-highway-101-s-brookings-or-97415
B25: Driftwood RV Park (long-term sites) | C25: Harbor, OR | D25: 8.0 mi | F25: 575 | J25: Full hookups (water/sewer/trash/cable/electric), clubhouse/banquet room, on-site | K25: ★★★ | L25: https://www.driftwoodrvpark.com/
B26: Ocean View Mobile Estates | C26: Brookings, OR | D26: 7.0 mi | J26: Manufactured home community | L26: https://www.mobilehome.net/mobile-home-park-directory/oregon/brookings
B27: Pleasant Hill Mobile Estates | C27: Brookings, OR | D27: 7.0 mi | J27: Manufactured home community | L27: https://www.mobilehome.net/mobile-home-park-directory/oregon/brookings
B28: Vista Hills Mobile Home Park | C28: Brookings, OR | D28: 7.0 mi | J28: Manufactured home community | L28: https://www.mobilehomeparkstore.com/mobile-home-park-directory/oregon/brookings
B29: Emerald Coast Estates | C29: Brookings, OR | D29: 7.0 mi | J29: Gated premier 55+ community, newer Energy Star homes | K29: ★★★★ | L29: https://www.redfin.com/city/23199/OR/Harbor
B30: Rainbow Rock Village | C30: Brookings, OR | D30: 9.0 mi | J30: Oceanfront/north-county manufactured community | L30: https://www.mobilehomeparkstore.com/mobile-home-park-directory/oregon/brookings
B31: Tonopah Mobile Home Village | C31: Brookings, OR | D31: 7.0 mi | J31: Manufactured home community | L31: https://www.mhbay.com/mobile-home-park-directory/oregon/brookings
B32: Mountain View MH Park | C32: Brookings, OR | D32: 7.0 mi | J32: Manufactured home community | L32: https://www.mobilehomeparkstore.com/mobile-home-park-directory/oregon/brookings
B33: River Hills Estates | C33: Gold Beach, OR | D33: 21.0 mi | J33: All-age community along the Rogue River corridor | L33: https://www.mobilehome.net/mobile-home-parks/59111-harbor-hills-mh-park-in-brookings-or
B34: Rogue Pacific MHP | C34: Gold Beach, OR | D34: 21.0 mi | E34: 63 | J34: Manufactured home community near coast | L34: https://www.mobilehome.net/mobile-home-parks/59111-harbor-hills-mh-park-in-brookings-or
B35: Riverview Village MHP | C35: Gold Beach, OR | D35: 23.0 mi | E35: 20 | J35: Riverside manufactured home community | L35: https://www.mobilehome.net/mobile-home-parks/59111-harbor-hills-mh-park-in-brookings-or
B36: STATISTICS | D36: Range: | E36: 20-63 | F36: $575-$740
D37: Average: | E37: 45 | F37: $618 | G37: 100.0%
B38: MARKET RENT CONCLUSION
B39: Brookings-area lot/space rents cluster in a 450-750 monthly band, with Brookings Mobile Home Park at 450-750, Tamaroo at 475-725, and Sunset View posting an average of 740 with zero vacant sites. The subject's 109 sites sit at the larger end of a market dominated by sub-65-site parks, giving it scarcity value. Assuming the subject is currently positioned mid-band (~650), there is realistic upside of 50-100 per site toward the 740-750 ceiling already proven by occupied competitors, implying roughly 65,000-130,000 of annual revenue lift at full occupancy. Coastal demand and minimal new MHP supply support pushing rents to the top of the prevailing range over time.
B41: SALE COMPS (10 found)
B42: Property | C42: Location | D42: Sale Date | E42: # Sites | F42: Sale Price | G42: $ / Unit | H42: Cap Rate | I42: NOI | J42: Buyer | K42: Seller | L42: Source
B43: Coos Bay Mobile Home Park (12-unit) | C43: Coos Bay, OR | D43: 05/26 | E43: 12 | F43: 1600000 | G43: 133333 | L43: https://www.loopnet.com/search/mobile-home-parks/or/for-sale/
B44: Lebanon Mobile Home Park (36-unit) | C44: Lebanon, OR | D44: 05/26 | E44: 36 | F44: 2045000 | G44: 56806 | H44: 0.05 | I44: 102250 | L44: https://www.loopnet.com/search/mobile-home-parks/or/for-sale/
B45: Keizer Mobile Home Park (14-unit) | C45: Keizer, OR | D45: 05/26 | E45: 14 | F45: 1237000 | G45: 88357 | H45: 0.05 | I45: 61850 | L45: https://www.loopnet.com/search/mobile-home-parks/or/for-sale/
B46: Tillamook Mobile Home Park (27-unit) | C46: Tillamook, OR | D46: 05/26 | E46: 27 | F46: 2700000 | G46: 100000 | L46: https://www.loopnet.com/search/mobile-home-parks/or/for-sale/
B47: Central Point Mobile Home Park (25-unit) | C47: Central Point, OR | D47: 05/26 | E47: 25 | F47: 1995000 | G47: 79800 | L47: https://www.loopnet.com/search/mobile-home-parks/or/for-sale/
B48: Willamina Mobile Home Park (3-unit) | C48: Willamina, OR | D48: 05/26 | E48: 3 | F48: 365000 | G48: 121667 | H48: 0.083 | I48: 30295 | L48: https://www.loopnet.com/search/mobile-home-parks/or/for-sale/
B49: Vale Mobile Home Park | C49: Vale, OR | D49: 05/26 | F49: 4175000 | H49: 0.05 | I49: 208750 | L49: https://www.loopnet.com/search/mobile-home-parks/or/for-sale/
B50: Rogue River Mobile Estates | C50: Rogue River / Grants Pass, OR | D50: 02/25 | E50: 10 | H50: 0.06 | L50: https://nwparks.com/listingsind.php?id_listing=92
B51: 7059 Rogue River Hwy (5-Acre MHP) | C51: Grants Pass, OR | D51: 02/25 | E51: 10 | H51: 0.06 | L51: https://www.loopnet.com/Listing/7059-Rogue-River-Hwy-Grants-Pass-OR/32384003/
B52: Coos Bay Mobile Home Park (11-unit) | C52: Coos Bay, OR | D52: 05/26 | E52: 11 | H52: 0.0815 | L52: https://www.loopnet.com/search/mobile-home-parks/coos-bay-or/for-sale/
B53: STATISTICS | F53: Avg $/Unit: | G53: $96,660 | H53: Avg Cap: | I53: 6.21%
B55: IMPLIED VALUATION USING COMP SET
B56: Asking Price | C56: 10000000
B57: Asking $ / Unit | C57: 91743.119
B58: Comp Avg $ / Unit | C58: 96660.5
B59: Comp Cap (trimmed mean, N=7) | C59: 0.0603
B60: MARKET CAP RATE CONCLUSION
B61: Regional Oregon MHP pricing is bifurcated: stabilized Willamette Valley and coastal listings trade tight at ~5.0% (Lebanon 36-unit and Keizer 14-unit both at 5.0%, Vale at 5.0%), while smaller inland/value-add deals price wider at 6.0%-8.6% (Rogue River parks near 6.0%, a Coos Bay 11-unit at 8.15%, Willamina at 8.3%). Price-per-unit ranges broadly from ~57,000 (Lebanon) to ~133,000 (Coos Bay 12-unit). Given the subject's coastal location, larger scale, and partial RV/resort component, a market cap rate in the 6.0%-7.0% range is the most defensible underwriting target, with the lower end achievable only on fully stabilized lot-rent income.
B63: DEMOGRAPHICS — DEEP DIVE
B64: County | C64: Curry County, OR (Brookings, OR Micropolitan Statistical Area)
B65: Total Population | C65: 21776
B66: 1-Year Pop Growth | C66: -2.2%
B67: 5-Year Pop Growth | C67: -4.0%
B68: 10-Year Pop Growth | C68: -2.7%
B69: 5-Yr Population Projection
B70: Median HH Income | C70: $62,244
B71: 5-Year Income Growth | C71: 7.5%
B72: Unemployment (Current) | C72: 5.4%
B73: Unemployment (1yr Ago) | C73: 5.0%
B74: Poverty Rate | C74: 15.2%
B75: % HHs Earning < $50K | C75: 40.0%
B76: Major Industries | C76: Commercial fishing & seafood processing (crab, salmon, tuna), Healthcare, Timber / wood products & logging, Retail, Tourism, Public sector / government
B77: Planned Developments | C77: No large factory or base projects identified. Growth driver is in-migration of retirees and remote workers from California and the PNW drawn by the mild 'Banana Belt' climate and low cost of living; new housing construction is limited given the city's geographic isolation. Healthcare (Curry Health Network) remains the principal institutional anchor.
B79: TOP EMPLOYERS
B80: #1 | C80: Curry Health Network / Curry Medical Center (Brookings) & Curry General Hospital (Gold Beach)
B81: #2 | C81: Brookings-Harbor School District 17C
B82: #3 | C82: Curry County government
B83: #4 | C83: City of Brookings
B84: #5 | C84: Port of Brookings Harbor commercial fishing fleet (crab/salmon/tuna)
B85: #6 | C85: Fred Meyer and local retail
B86: #7 | C86: Sutter Coast Hospital (Crescent City, CA - regional)
B87: #8 | C87: OSU Extension / Southwestern Oregon Community College

Sheet Data Consolidation
A1: Choose Income Category | B1: Input Source Data | D1: Input Source Data | G1: Choose Ann. # | H1: 3
A2: GGC Catorgy | B2: Source Name | D2: 2023 | E2: 2024 | F2: Broker's Proforma Y1 | G2: T12 | H2: Annualization | J2: 45444 | K2: 45474 | L2: 45505 | M2: 45536 | N2: 45566 | O2: 45597 | P2: 45627 | Q2: 45658 | R2: 45689 | S2: 45717 | T2: 45748 | U2: 45992 | V2: T12
A3: Gross Potential Rent | B3: 4101 Lot Rent | E3: 1144604.5 | F3: 1144604.5 | G3: 1144604.5 | H3: =((SUM(S3:U3)/$H$1)*12) | J3: 88056 | K3: 88063.94 | L3: 95245 | M3: 96356 | N3: 97084 | O3: 97396 | P3: 97648 | Q3: 97396.53 | R3: 96074 | S3: 97095 | T3: 97095 | U3: 97095 | V3: =SUM(J3:U3)
A4: Less: Vacancy | B4: Physical vacancy (rent roll) | E4: 0 | F4: 0 | G4: 0 | H4: =((SUM(S4:U4)/$H$1)*12) | J4: -1932.75 | K4: -1932.75 | L4: -1932.75 | M4: -1932.75 | N4: -1932.75 | O4: -1932.75 | P4: -1932.75 | Q4: -1932.75 | R4: -1932.75 | S4: -1932.75 | T4: -1932.75 | U4: -1932.75 | V4: =(((SUM(J4:U4))))
A5: Less: Concessions | B5: 4131 Move in Specials | E5: -168 | F5: -168 | G5: -168 | H5: =((SUM(S5:U5)/$H$1)*12) | J5: -84 | K5: -84 | L5: 0 | M5: 0 | N5: 0 | O5: 0 | P5: 0 | Q5: 0 | R5: 0 | S5: 0 | T5: 0 | U5: 0 | V5: =SUM(J5:U5)
A6: Less: Bad Debt | B6: 6120 Bad Debt (re-routed from expense block to income contra) | E6: -26061.7 | F6: -26061.7 | G6: -26061.7 | H6: =((SUM(S6:U6)/$H$1)*12) | J6: -35.6 | K6: -6151.01 | L6: 0 | M6: -1886.84 | N6: 0 | O6: -3846.97 | P6: -10326.98 | Q6: -3814.3 | R6: 0 | S6: 0 | T6: 0 | U6: 0 | V6: =SUM(J6:U6)
A7: RV Site Rental Income | B7: 4103 Long Term RV Lot Rent | E7: 172705.2 | F7: 172705.2 | G7: 172705.2 | H7: =((SUM(S7:U7)/$H$1)*12) | J7: 17051 | K7: 14962 | L7: 15578 | M7: 15645 | N7: 14563 | O7: 14831 | P7: 14090 | Q7: 14090 | R7: 13416 | S7: 12742 | T7: 12742 | U7: 12995.2 | V7: =SUM(J7:U7)
A8: Parking Income | B8: 4108 Storage Unit Rent | E8: 900 | F8: 900 | G8: 900 | H8: =((SUM(S8:U8)/$H$1)*12) | J8: 75 | K8: 75 | L8: 75 | M8: 75 | N8: 75 | O8: 75 | P8: 75 | Q8: 75 | R8: 75 | S8: 75 | T8: 75 | U8: 75 | V8: =SUM(J8:U8)
A9: Retail | B9: 4110 Retail Unit Rent | E9: 12425.81 | F9: 12425.81 | G9: 12425.81 | H9: =((SUM(S9:U9)/$H$1)*12) | J9: 1200 | K9: 1200 | L9: 425.81 | M9: 0 | N9: 1200 | O9: 1200 | P9: 1200 | Q9: 1200 | R9: 1200 | S9: 1200 | T9: 1200 | U9: 1200 | V9: =SUM(J9:U9)
A10: Utility Reimbursement | B10: 4403 Electric | E10: 79147.02 | F10: 79147.02 | G10: 79147.02 | H10: =((SUM(S10:U10)/$H$1)*12) | J10: 5895.17 | K10: 7136.87 | L10: 8138.93 | M10: 7443.4 | N10: 9404.69 | O10: 7438.49 | P10: 6708.47 | Q10: 6135.98 | R10: 6004.45 | S10: 5116.73 | T10: 4779.05 | U10: 4944.79 | V10: =SUM(J10:U10)
A11: Utility Reimbursement | B11: 4404 Garbage | E11: 30 | F11: 30 | G11: 30 | H11: =((SUM(S11:U11)/$H$1)*12) | J11: 0 | K11: 0 | L11: 0 | M11: 0 | N11: 0 | O11: 0 | P11: 0 | Q11: 0 | R11: 0 | S11: 0 | T11: 0 | U11: 30 | V11: =SUM(J11:U11)
A12: Other Income | B12: 4402 Water & Sewer (contra) | E12: -1709 | F12: -1709 | G12: -1709 | H12: =((SUM(S12:U12)/$H$1)*12) | J12: 0 | K12: 0 | L12: 0 | M12: -1709 | N12: 0 | O12: 0 | P12: 0 | Q12: 0 | R12: 0 | S12: 0 | T12: 0 | U12: 0 | V12: =SUM(J12:U12)
A13: Other Income | B13: 4304 Damages | E13: 1250.65 | F13: 1250.65 | G13: 1250.65 | H13: =((SUM(S13:U13)/$H$1)*12) | J13: 0 | K13: 0 | L13: 0 | M13: 0 | N13: 1250.65 | O13: 0 | P13: 0 | Q13: 0 | R13: 0 | S13: 0 | T13: 0 | U13: 0 | V13: =SUM(J13:U13)
A14: Other Income | B14: 4905 Recovered Legal/Court Fees | E14: 3183.75 | F14: 3183.75 | G14: 3183.75 | H14: =((SUM(S14:U14)/$H$1)*12) | J14: 0 | K14: 0 | L14: 0 | M14: 0 | N14: 0 | O14: 0 | P14: 1305.25 | Q14: 1878.5 | R14: 0 | S14: 0 | T14: 0 | U14: 0 | V14: =SUM(J14:U14)
A15: Other Income | B15: 4907 Violation Fines | E15: 50 | F15: 50 | G15: 50 | H15: =((SUM(S15:U15)/$H$1)*12) | J15: 0 | K15: 0 | L15: 0 | M15: 0 | N15: 0 | O15: 0 | P15: 0 | Q15: 50 | R15: 0 | S15: 25 | T15: -25 | U15: 0 | V15: =SUM(J15:U15)
A16: Other Income | B16: 4908 Payment Processing Fee | E16: 7159.9 | F16: 7159.9 | G16: 7159.9 | H16: =((SUM(S16:U16)/$H$1)*12) | J16: 630.54 | K16: 692.09 | L16: 635.06 | M16: 627.78 | N16: 666.63 | O16: 646.82 | P16: 562.24 | Q16: 572.18 | R16: 514.04 | S16: 539.64 | T16: 548.87 | U16: 524.01 | V16: =SUM(J16:U16)
... A21: Other Income | B21: 4915 NSF Fees | E21: 375 | F21: 375 | G21: 375 | H21: =((SUM(S21:U21)/$H$1)*12) | J21: 50 | K21: 0 | L21: 25 | M21: 25 | N21: 25 | O21: 75 | P21: 50 | Q21: 0 | R21: 25 | S21: 100 | T21: 0 | U21: 0 | V21: =SUM(J21:U21)
H22: =F22*4
D23: =SUM(D3:D21) | E23: =SUM(E3:E21) | F23: =SUM(F3:F21) | G23: =SUM(G3:G21) | H23: =SUM(H3:H21) | I23: =SUM(I3:I21) | J23: =SUM(J3:J21) | K23: =SUM(K3:K21) | ... V23: =SUM(V3:V21)
B24: Input Source Data
B25: Check | D25: =IF(D23=D24,"OK") | E25: =IF(E23=E24,"OK") | F25: =IF(F23=F24,"OK") | G25: =IF(G23=G24,"OK") | H25: N/A | J25: =IF(J23=J24,"OK") | K25: =IF(K23=K24,"OK") | L25: =IF(L23=L24,"OK") | M25: =IF(M23=M24,"OK") | N25: =IF(N23=N24,"OK") | O25: =IF(O23=O24,"OK") | P25: =IF(P23=P24,"OK") | Q25: =IF(Q23=Q24,"OK") | ... V25: =IF(V23=V24,"OK")
A27: Choose Expense Category | B27: Input Source Data | D27: Input Source Epense Data | H27: =H1 | J27: =J2 | K27: =K2 | L27: =L2 | M27: =M2 | N27: =N2 | O27: =O2 | P27: =P2 | Q27: =Q2 | ... U27: =U2 | V27: Total
H28: =((SUM(S28:U28)/$H$1)*12) | V28: =SUM(J28:U28)
H29: =((SUM(S29:U29)/$H$1)*12) | V29: =SUM(J29:U29)
H30: =((SUM(S30:U30)/$H$1)*12) | V30: =SUM(J30:U30)
H31: =((SUM(S31:U31)/$H$1)*12) | V31: =SUM(J31:U31)
H32: =((SUM(S32:U32)/$H$1)*12) | V32: =SUM(J32:U32)
H33: =((SUM(S33:U33)/$H$1)*12) | V33: =SUM(J33:U33)
H34: =((SUM(S34:U34)/$H$1)*12) | V34: =SUM(J34:U34)
H35: =((SUM(S35:U35)/$H$1)*12) | V35: =SUM(J35:U35)
H36: =((SUM(S36:U36)/$H$1)*12) | V36: =SUM(J36:U36)
H37: =((SUM(S37:U37)/$H$1)*12) | V37: =SUM(J37:U37)
H38: =((SUM(S38:U38)/$H$1)*12) | V38: =SUM(J38:U38)
H39: =((SUM(S39:U39)/$H$1)*12) | V39: =SUM(J39:U39)
... H42: =((SUM(S42:U42)/$H$1)*12) | V42: =SUM(J42:U42)
A43: RE Taxes | B43: 5301 Property Taxes | E43: 15390.51 | F43: 15390.51 | G43: 15390.51 | H43: =((SUM(S43:U43)/$H$1)*12) | J43: 1243.41 | K43: 1243.41 | L43: 1492.92 | M43: 1243.41 | N43: 1243.41 | O43: 1463.39 | P43: 1243.41 | Q43: 1243.43 | R43: 1243.43 | S43: 1243.43 | T43: 1243.43 | U43: 1243.43 | V43: =SUM(J43:U43)
A44: Insurance | B44: 5051 Car Insurance + 5053 Liability Insurance | E44: 37680.97 | F44: 37680.97 | G44: 37680.97 | H44: =((SUM(S44:U44)/$H$1)*12) | J44: 3230.91 | K44: 3234.24 | L44: 3224.27 | M44: 3230.91 | N44: 3368.16 | O44: 3340.71 | P44: 3340.71 | Q44: 3340.71 | R44: 2784.99 | S44: 2784.99 | T44: 2794.69 | U44: 3005.68 | V44: =SUM(J44:U44)
A45: Gas/Fuel | B45: 5401 Fuel for Vehicles + 5406 Gas & Propane | E45: 2806.94 | F45: 2806.94 | G45: 2806.94 | H45: =((SUM(S45:U45)/$H$1)*12) | J45: 0 | K45: 75.48 | L45: 185.18 | M45: 75.21 | N45: 1929.44 | O45: 108.36 | P45: 109.17 | Q45: 146.92 | R45: 139.94 | S45: 37.24 | T45: 0 | U45: 0 | V45: =SUM(J45:U45)
A46: Electrcitiy | B46: 5404 Electric | E46: 93309.56 | F46: 93309.56 | G46: 93309.56 | H46: =((SUM(S46:U46)/$H$1)*12) | J46: 6947.07 | K46: 8871.79 | L46: 8845.15 | M46: 9808.06 | N46: 9372.18 | O46: 9800.4 | P46: 7480.45 | Q46: 7135.25 | R46: 6309.76 | S46: 6385.77 | T46: 6149.59 | U46: 6204.09 | V46: =SUM(J46:U46)
A47: Water and Sewer | B47: 5402 Water & Sewer + 5403 Water Testing | E47: 57277.28 | F47: 57277.28 | G47: 57277.28 | H47: =((SUM(S47:U47)/$H$1)*12) | J47: 2605.17 | K47: 5411.91 | L47: 6936.49 | M47: 6639.17 | N47: 3819.28 | O47: 4149.08 | P47: 3844.62 | Q47: 3427.94 | R47: 5729.44 | S47: 3850.64 | T47: 4833.27 | U47: 6030.27 | V47: =SUM(J47:U47)
A48: Trash Removal | B48: 5405 Garbage | E48: 22439.25 | F48: 22439.25 | G48: 22439.25 | H48: =((SUM(S48:U48)/$H$1)*12) | J48: 1676.5 | K48: 2209.9 | L48: 2020.55 | M48: 1804.37 | N48: 2280.27 | O48: 1771.04 | P48: 1893.85 | Q48: 1957.44 | R48: 1964.24 | S48: 1848.32 | T48: 1928.85 | U48: 1083.92 | V48: =SUM(J48:U48)
A49: Repair and Maintenance | B49: 5107 Septic + 5108 Plumbing + 5109 Misc + 5110 Equipment + 5111 Electrical + 5200 Park Supplies | E49: 10414.78 | F49: 10414.78 | G49: 10414.78 | H49: =((SUM(S49:U49)/$H$1)*12) | J49: 1761.97 | K49: 447.91 | L49: 847.94 | M49: 459.97 | N49: 893.71 | O49: 1117.36 | P49: 317.61 | Q49: 376.93 | R49: 1372.58 | S49: 1782.51 | T49: 354.93 | U49: 0 | V49: =SUM(J49:U49)
A50: Ground Maintenance | B50: 5102 Tree + 5103 Pest + 5104 Grounds Maintenance | E50: 13943.64 | F50: 13943.64 | G50: 13943.64 | H50: =((SUM(S50:U50)/$H$1)*12) | J50: 0 | K50: 0 | L50: 50.99 | M50: 0 | N50: 52 | O50: 22.98 | P50: 956.19 | Q50: 423.6 | R50: 147.38 | S50: 560.66 | T50: 5729.84 | U50: 6000 | V50: =SUM(J50:U50)
A51: Management Fee | B51: 5000 Management Fees Expense (OVERRIDDEN) | E51: 43799.97 | F51: 43799.97 | G51: 43799.97 | H51: =((SUM(S51:U51)/$H$1)*12) | J51: 3420.21 | K51: 4344.21 | L51: 3638.85 | M51: 3638.84 | N51: 3723.95 | O51: 3673.68 | P51: 3638.72 | Q51: 3620.6 | R51: 3544.15 | S51: 3520.16 | T51: 3506.55 | U51: 3530.05 | V51: =SUM(J51:U51)
A52: Payroll | B52: 5700 Total Personnel (wages, taxes, benefits, casual labour, WC) | E52: 103292.34 | F52: 103292.34 | G52: 103292.34 | H52: =((SUM(S52:U52)/$H$1)*12) | J52: 5423.04 | K52: 5790.08 | L52: 9007.66 | M52: 8342.9 | N52: 8129.43 | O52: 7828.83 | P52: 7058.22 | Q52: 9548.72 | R52: 9080.27 | S52: 8744.73 | T52: 13938.46 | U52: 10400 | V52: =SUM(J52:U52)
A53: General and Administrative | B53: 5070 Licenses + 5072 Dues + 5407 Tenant Cable TV + 5601-5650 Office/Bank | E53: 84160.86 | F53: 84160.86 | G53: 84160.86 | H53: =((SUM(S53:U53)/$H$1)*12) | J53: 7398.55 | K53: 6595.16 | L53: 6927.5 | M53: 6987.85 | N53: 6982.16 | O53: 6957.32 | P53: 6892.59 | Q53: 6936.46 | R53: 6800.81 | S53: 6792.78 | T53: 6905.58 | U53: 6256 | V53: =SUM(J53:U53)
A54: Professional Fees | B54: 5062 Legal Fees | E54: 4201.25 | F54: 4201.25 | G54: 4201.25 | H54: =((SUM(S54:U54)/$H$1)*12) | J54: 385 | K54: 0 | L54: 0 | M54: 0 | N54: 330 | O54: 0 | P54: 1305.25 | Q54: 1878.5 | R54: 247.5 | S54: 55 | T54: 0 | U54: 0 | V54: =SUM(J54:U54)
... A57: Cap-Ex Reserve | B57: GGC synthetic reserve (not in seller financials) | E57: 0 | F57: 0 | G57: 0 | H57: =((SUM(S57:U57)/$H$1)*12) | J57: 0 | K57: 0 | L57: 0 | M57: 0 | N57: 0 | O57: 0 | P57: 0 | Q57: 0 | R57: 0 | S57: 0 | T57: 0 | U57: 0 | V57: =SUM(J57:U57)
H58: =((SUM(S58:U58)/$H$1)*12) | V58: =SUM(J58:U58)
D60: =SUM(D28:D58) | E60: =SUM(E28:E58) | F60: =SUM(F28:F58) | G60: =SUM(G28:G58) | H60: =SUM(H28:H58) | I60: =SUM(I28:I58) | J60: =SUM(J28:J58) | K60: =SUM(K28:K58) | ... V60: =SUM(V28:V58)
B61: Input Source Data
B62: Check | D62: =IF(D60=D61,"OK") | E62: =IF(E60=E61,"OK") | F62: =IF(F60=F61,"OK") | G62: =IF(G60=G61,"OK") | H62: N/A | J62: =IF(J60=J61,"OK") | K62: =IF(K60=K61,"OK") | L62: =IF(L60=L61,"OK") | M62: =IF(M60=M61,"OK") | N62: =IF(N60=N61,"OK") | O62: =IF(O60=O61,"OK") | P62: =IF(P60=P61,"OK") | Q62: =IF(Q60=Q61,"OK") | ... V62: =IF(V60=V61,"OK")
B64: Net Operating Income | D64: =D23-D60 | E64: =E23-E60 | F64: =F23-F60 | G64: =G23-G60 | H64: =H23-H60 | J64: =J23-J60 | K64: =K23-K60 | L64: =L23-L60 | M64: =M23-M60 | N64: =N23-N60 | O64: =O23-O60 | P64: =P23-P60 | Q64: =Q23-Q60 | ... V64: =V23-V60

Sheet Collections
A1: GARY GROUP CAPITAL
B4: Month | C4: GPR | D4: Vacant | E4: Concessions | F4: Bad Debt | G4: Net Rental Income | H4: RUBS | I4: HR Income | J4: RV Income | K4: Parking | L4: Laundry | M4: Other Income | N4: EGI
B5: ='Data Consolidation'!J2 | C5: =SUMIFS('Data Consolidation'!J3:J21,'Data Consolidation'!$A$3:$A$21,"Gross Potential Rent") | D5: =SUMIFS('Data Consolidation'!$J$3:$J$21,'Data Consolidation'!$A$3:$A$21,"Vacancy") | E5: =SUMIFS('Data Consolidation'!$J$3:$J$21,'Data Consolidation'!$A$3:$A$21,"Concessions") | F5: =SUMIFS('Data Consolidation'!$J$3:$J$21,'Data Consolidation'!$A$3:$A$21,"bad debt") | G5: =SUM(C5:F5) | H5: =SUMIFS('Data Consolidation'!$J$3:$J$21,'Data Consolidation'!$A$3:$A$21,"Utility Reimbursement") | I5: =SUMIFS('Data Consolidation'!$J$3:$J$21,'Data Consolidation'!$A$3:$A$21,"Home Rent Income") | J5: =SUMIFS('Data Consolidation'!$J$3:$J$21,'Data Consolidation'!$A$3:$A$21,"RV site rental income") | K5: =SUMIFS('Data Consolidation'!$J$3:$J$21,'Data Consolidation'!$A$3:$A$21,"Parking Income") | L5: =SUMIFS('Data Consolidation'!$J$3:$J$21,'Data Consolidation'!$A$3:$A$21,"Laundry Income") | M5: =SUMIFS('Data Consolidation'!$J$3:$J$21,'Data Consolidation'!$A$3:$A$21,"Other Income") | N5: =G5+H5+I5+J5+K5+L5+M5
B6: ='Data Consolidation'!K2 | C6: =SUMIFS('Data Consolidation'!K$3:K$21,'Data Consolidation'!$A$3:$A$21,"Gross Potential Rent") | D6: =SUMIFS('Data Consolidation'!$K$3:$K$21,'Data Consolidation'!$A$3:$A$21,"Vacant") | E6: =SUMIFS('Data Consolidation'!$K$3:$K$21,'Data Consolidation'!$A$3:$A$21,"Concessions") | F6: =SUMIFS('Data Consolidation'!$K$3:$K$21,'Data Consolidation'!$A$3:$A$21,"bad debt") | G6: =SUM(C6:F6) | H6: =SUMIFS('Data Consolidation'!$K$3:$K$21,'Data Consolidation'!$A$3:$A$21,"Utility Reimbursement") | I6: =SUMIFS('Data Consolidation'!$K$3:$K$21,'Data Consolidation'!$A$3:$A$21,"Home Rent Income") | J6: =SUMIFS('Data Consolidation'!$K$3:$K$21,'Data Consolidation'!$A$3:$A$21,"RV site rental income") | K6: =SUMIFS('Data Consolidation'!$K$3:$K$21,'Data Consolidation'!$A$3:$A$21,"Parking Income") | L6: =SUMIFS('Data Consolidation'!$K$3:$K$21,'Data Consolidation'!$A$3:$A$21,"Laundry Income") | M6: =SUMIFS('Data Consolidation'!$K$3:$K$21,'Data Consolidation'!$A$3:$A$21,"Other Income") | N6: =G6+H6+I6+J6+K6+L6+M6
B7: ='Data Consolidation'!L2 | C7: =SUMIFS('Data Consolidation'!L$3:L$21,'Data Consolidation'!$A$3:$A$21,"Gross Potential Rent") | D7: =SUMIFS('Data Consolidation'!$L$3:$L$21,'Data Consolidation'!$A$3:$A$21,"Vacancy") | E7: =SUMIFS('Data Consolidation'!$L$3:$L$21,'Data Consolidation'!$A$3:$A$21,"Concessions") | F7: =SUMIFS('Data Consolidation'!$L$3:$L$21,'Data Consolidation'!$A$3:$A$21,"bad debt") | G7: =SUM(C7:F7) | H7: =SUMIFS('Data Consolidation'!$L$3:$L$21,'Data Consolidation'!$A$3:$A$21,"Utility Reimbursement") | I7: =SUMIFS('Data Consolidation'!$L$3:$L$21,'Data Consolidation'!$A$3:$A$21,"Home Rent Income") | J7: =SUMIFS('Data Consolidation'!$L$3:$L$21,'Data Consolidation'!$A$3:$A$21,"RV site rental income") | K7: =SUMIFS('Data Consolidation'!$L$3:$L$21,'Data Consolidation'!$A$3:$A$21,"Parking Income") | L7: =SUMIFS('Data Consolidation'!$L$3:$L$21,'Data Consolidation'!$A$3:$A$21,"Laundry Income") | M7: =SUMIFS('Data Consolidation'!$L$3:$L$21,'Data Consolidation'!$A$3:$A$21,"Other Income") | N7: =G7+H7+I7+J7+K7+L7+M7
B8: ='Data Consolidation'!M2 | C8: =SUMIFS('Data Consolidation'!M$3:M$21,'Data Consolidation'!$A$3:$A$21,"Gross Potential Rent") | D8: =SUMIFS('Data Consolidation'!$M$3:$M$21,'Data Consolidation'!$A$3:$A$21,"Vacancy") | E8: =SUMIFS('Data Consolidation'!$M$3:$M$21,'Data Consolidation'!$A$3:$A$21,"Concessions") | F8: =SUMIFS('Data Consolidation'!$M$3:$M$21,'Data Consolidation'!$A$3:$A$21,"bad debt") | G8: =SUM(C8:F8) | H8: =SUMIFS('Data Consolidation'!$M$3:$M$21,'Data Consolidation'!$A$3:$A$21,"Utility Reimbursement") | I8: =SUMIFS('Data Consolidation'!$M$3:$M$21,'Data Consolidation'!$A$3:$A$21,"Home Rent Income") | J8: =SUMIFS('Data Consolidation'!$M$3:$M$21,'Data Consolidation'!$A$3:$A$21,"RV site rental income") | K8: =SUMIFS('Data Consolidation'!$M$3:$M$21,'Data Consolidation'!$A$3:$A$21,"Parking Income") | L8: =SUMIFS('Data Consolidation'!$M$3:$M$21,'Data Consolidation'!$A$3:$A$21,"Laundry Income") | M8: =SUMIFS('Data Consolidation'!$M$3:$M$21,'Data Consolidation'!$A$3:$A$21,"Other Income") | N8: =G8+H8+I8+J8+K8+L8+M8
B9: ='Data Consolidation'!N2 | C9: =SUMIFS('Data Consolidation'!N$3:N$21,'Data Consolidation'!$A$3:$A$21,"Gross Potential Rent") | D9: =SUMIFS('Data Consolidation'!$N$3:$N$21,'Data Consolidation'!$A$3:$A$21,"Vacancy") | E9: =SUMIFS('Data Consolidation'!$N$3:$N$21,'Data Consolidation'!$A$3:$A$21,"Concessions") | F9: =SUMIFS('Data Consolidation'!$N$3:$N$21,'Data Consolidation'!$A$3:$A$21,"bad debt") | G9: =SUM(C9:F9) | H9: =SUMIFS('Data Consolidation'!$N$3:$N$21,'Data Consolidation'!$A$3:$A$21,"Utility Reimbursement") | I9: =SUMIFS('Data Consolidation'!$N$3:$N$21,'Data Consolidation'!$A$3:$A$21,"Home Rent Income") | J9: =SUMIFS('Data Consolidation'!$N$3:$N$21,'Data Consolidation'!$A$3:$A$21,"RV site rental income") | K9: =SUMIFS('Data Consolidation'!$N$3:$N$21,'Data Consolidation'!$A$3:$A$21,"Parking Income") | L9: =SUMIFS('Data Consolidation'!$N$3:$N$21,'Data Consolidation'!$A$3:$A$21,"Laundry Income") | M9: =SUMIFS('Data Consolidation'!$N$3:$N$21,'Data Consolidation'!$A$3:$A$21,"Other Income") | N9: =G9+H9+I9+J9+K9+L9+M9
B10: ='Data Consolidation'!O2 | C10: =SUMIFS('Data Consolidation'!O$3:O$21,'Data Consolidation'!$A$3:$A$21,"Gross Potential Rent") | D10: =SUMIFS('Data Consolidation'!$O$3:$O$21,'Data Consolidation'!$A$3:$A$21,"Vacancy") | E10: =SUMIFS('Data Consolidation'!$O$3:$O$21,'Data Consolidation'!$A$3:$A$21,"Concessions") | F10: =SUMIFS('Data Consolidation'!$O$3:$O$21,'Data Consolidation'!$A$3:$A$21,"bad debt") | G10: =SUM(C10:F10) | H10: =SUMIFS('Data Consolidation'!$O$3:$O$21,'Data Consolidation'!$A$3:$A$21,"Utility Reimbursement") | I10: =SUMIFS('Data Consolidation'!$O$3:$O$21,'Data Consolidation'!$A$3:$A$21,"Home Rent Income") | J10: =SUMIFS('Data Consolidation'!$O$3:$O$21,'Data Consolidation'!$A$3:$A$21,"RV site rental income") | K10: =SUMIFS('Data Consolidation'!$O$3:$O$21,'Data Consolidation'!$A$3:$A$21,"Parking Income") | L10: =SUMIFS('Data Consolidation'!$O$3:$O$21,'Data Consolidation'!$A$3:$A$21,"Laundry Income") | M10: =SUMIFS('Data Consolidation'!$O$3:$O$21,'Data Consolidation'!$A$3:$A$21,"Other Income") | N10: =G10+H10+I10+J10+K10+L10+M10
B11: ='Data Consolidation'!P2 | C11: =SUMIFS('Data Consolidation'!P$3:P$21,'Data Consolidation'!$A$3:$A$21,"Gross Potential Rent") | D11: =SUMIFS('Data Consolidation'!$P$3:$P$21,'Data Consolidation'!$A$3:$A$21,"Vacancy") | E11: =SUMIFS('Data Consolidation'!$P$3:$P$21,'Data Consolidation'!$A$3:$A$21,"Concessions") | F11: =SUMIFS('Data Consolidation'!$P$3:$P$21,'Data Consolidation'!$A$3:$A$21,"bad debt") | G11: =SUM(C11:F11) | H11: =SUMIFS('Data Consolidation'!$P$3:$P$21,'Data Consolidation'!$A$3:$A$21,"Utility Reimbursement") | I11: =SUMIFS('Data Consolidation'!$P$3:$P$21,'Data Consolidation'!$A$3:$A$21,"Home Rent Income") | J11: =SUMIFS('Data Consolidation'!$P$3:$P$21,'Data Consolidation'!$A$3:$A$21,"RV site rental income") | K11: =SUMIFS('Data Consolidation'!$P$3:$P$21,'Data Consolidation'!$A$3:$A$21,"Parking Income") | L11: =SUMIFS('Data Consolidation'!$P$3:$P$21,'Data Consolidation'!$A$3:$A$21,"Laundry Income") | M11: =SUMIFS('Data Consolidation'!$P$3:$P$21,'Data Consolidation'!$A$3:$A$21,"Other Income") | N11: =G11+H11+I11+J11+K11+L11+M11
B12: ='Data Consolidation'!Q2 | C12: =SUMIFS('Data Consolidation'!Q$3:Q$21,'Data Consolidation'!$A$3:$A$21,"Gross Potential Rent") | D12: =SUMIFS('Data Consolidation'!$Q$3:$Q$21,'Data Consolidation'!$A$3:$A$21,"Vacancy") | E12: =SUMIFS('Data Consolidation'!$Q$3:$Q$21,'Data Consolidation'!$A$3:$A$21,"Concessions") | F12: =SUMIFS('Data Consolidation'!$Q$3:$Q$21,'Data Consolidation'!$A$3:$A$21,"bad debt") | G12: =SUM(C12:F12) | H12: =SUMIFS('Data Consolidation'!$Q$3:$Q$21,'Data Consolidation'!$A$3:$A$21,"Utility Reimbursement") | I12: =SUMIFS('Data Consolidation'!$Q$3:$Q$21,'Data Consolidation'!$A$3:$A$21,"Home Rent Income") | J12: =SUMIFS('Data Consolidation'!$Q$3:$Q$21,'Data Consolidation'!$A$3:$A$21,"RV site rental income") | K12: =SUMIFS('Data Consolidation'!$Q$3:$Q$21,'Data Consolidation'!$A$3:$A$21,"Parking Income") | L12: =SUMIFS('Data Consolidation'!$Q$3:$Q$21,'Data Consolidation'!$A$3:$A$21,"Laundry Income") | M12: =SUMIFS('Data Consolidation'!$Q$3:$Q$21,'Data Consolidation'!$A$3:$A$21,"Other Income") | N12: =G12+H12+I12+J12+K12+L12+M12
B13: ='Data Consolidation'!R2 | C13: =SUMIFS('Data Consolidation'!R$3:R$21,'Data Consolidation'!$A$3:$A$21,"Gross Potential Rent") | D13: =SUMIFS('Data Consolidation'!$R$3:$R$21,'Data Consolidation'!$A$3:$A$21,"Vacancy") | E13: =SUMIFS('Data Consolidation'!$R$3:$R$21,'Data Consolidation'!$A$3:$A$21,"Concessions") | F13: =SUMIFS('Data Consolidation'!$R$3:$R$21,'Data Consolidation'!$A$3:$A$21,"bad debt") | G13: =SUM(C13:F13) | H13: =SUMIFS('Data Consolidation'!$R$3:$R$21,'Data Consolidation'!$A$3:$A$21,"Utility Reimbursement") | I13: =SUMIFS('Data Consolidation'!$R$3:$R$21,'Data Consolidation'!$A$3:$A$21,"Home Rent Income") | J13: =SUMIFS('Data Consolidation'!$R$3:$R$21,'Data Consolidation'!$A$3:$A$21,"RV site rental income") | K13: =SUMIFS('Data Consolidation'!$R$3:$R$21,'Data Consolidation'!$A$3:$A$21,"Parking Income") | L13: =SUMIFS('Data Consolidation'!$R$3:$R$21,'Data Consolidation'!$A$3:$A$21,"Laundry Income") | M13: =SUMIFS('Data Consolidation'!$R$3:$R$21,'Data Consolidation'!$A$3:$A$21,"Other Income") | N13: =G13+H13+I13+J13+K13+L13+M13
B14: ='Data Consolidation'!S2 | C14: =SUMIFS('Data Consolidation'!S$3:S$21,'Data Consolidation'!$A$3:$A$21,"Gross Potential Rent") | D14: =SUMIFS('Data Consolidation'!$S$3:$S$21,'Data Consolidation'!$A$3:$A$21,"Vacancy") | E14: =SUMIFS('Data Consolidation'!$S$3:$S$21,'Data Consolidation'!$A$3:$A$21,"Concessions") | F14: =SUMIFS('Data Consolidation'!$S$3:$S$21,'Data Consolidation'!$A$3:$A$21,"bad debt") | G14: =SUM(C14:F14) | H14: =SUMIFS('Data Consolidation'!$S$3:$S$21,'Data Consolidation'!$A$3:$A$21,"Utility Reimbursement") | I14: =SUMIFS('Data Consolidation'!$S$3:$S$21,'Data Consolidation'!$A$3:$A$21,"Home Rent Income") | J14: =SUMIFS('Data Consolidation'!$S$3:$S$21,'Data Consolidation'!$A$3:$A$21,"RV site rental income") | K14: =SUMIFS('Data Consolidation'!$S$3:$S$21,'Data Consolidation'!$A$3:$A$21,"Parking Income") | L14: =SUMIFS('Data Consolidation'!$S$3:$S$21,'Data Consolidation'!$A$3:$A$21,"Laundry Income") | M14: =SUMIFS('Data Consolidation'!$S$3:$S$21,'Data Consolidation'!$A$3:$A$21,"Other Income") | N14: =G14+H14+I14+J14+K14+L14+M14
B15: ='Data Consolidation'!T2 | C15: =SUMIFS('Data Consolidation'!T$3:T$21,'Data Consolidation'!$A$3:$A$21,"Gross Potential Rent") | D15: =SUMIFS('Data Consolidation'!$T$3:$T$21,'Data Consolidation'!$A$3:$A$21,"Vacancy") | E15: =SUMIFS('Data Consolidation'!$T$3:$T$21,'Data Consolidation'!$A$3:$A$21,"Concessions") | F15: =SUMIFS('Data Consolidation'!$T$3:$T$21,'Data Consolidation'!$A$3:$A$21,"bad debt") | G15: =SUM(C15:F15) | H15: =SUMIFS('Data Consolidation'!$T$3:$T$21,'Data Consolidation'!$A$3:$A$21,"Utility Reimbursement") | I15: =SUMIFS('Data Consolidation'!$T$3:$T$21,'Data Consolidation'!$A$3:$A$21,"Home Rent Income") | J15: =SUMIFS('Data Consolidation'!$T$3:$T$21,'Data Consolidation'!$A$3:$A$21,"RV site rental income") | K15: =SUMIFS('Data Consolidation'!$T$3:$T$21,'Data Consolidation'!$A$3:$A$21,"Parking Income") | L15: =SUMIFS('Data Consolidation'!$T$3:$T$21,'Data Consolidation'!$A$3:$A$21,"Laundry Income") | M15: =SUMIFS('Data Consolidation'!$T$3:$T$21,'Data Consolidation'!$A$3:$A$21,"Other Income") | N15: =G15+H15+I15+J15+K15+L15+M15
B16: ='Data Consolidation'!U2 | C16: =SUMIFS('Data Consolidation'!U$3:U$21,'Data Consolidation'!$A$3:$A$21,"Gross Potential Rent") | D16: =SUMIFS('Data Consolidation'!$U$3:$U$21,'Data Consolidation'!$A$3:$A$21,"Vacancy") | E16: =SUMIFS('Data Consolidation'!$U$3:$U$21,'Data Consolidation'!$A$3:$A$21,"Concessions") | F16: =SUMIFS('Data Consolidation'!$U$3:$U$21,'Data Consolidation'!$A$3:$A$21,"bad debt") | G16: =SUM(C16:F16) | H16: =SUMIFS('Data Consolidation'!$U$3:$U$21,'Data Consolidation'!$A$3:$A$21,"Utility Reimbursement") | I16: =SUMIFS('Data Consolidation'!$U$3:$U$21,'Data Consolidation'!$A$3:$A$21,"Home Rent Income") | J16: =SUMIFS('Data Consolidation'!$U$3:$U$21,'Data Consolidation'!$A$3:$A$21,"RV site rental income") | K16: =SUMIFS('Data Consolidation'!$U$3:$U$21,'Data Consolidation'!$A$3:$A$21,"Parking Income") | L16: =SUMIFS('Data Consolidation'!$U$3:$U$21,'Data Consolidation'!$A$3:$A$21,"Laundry Income") | M16: =SUMIFS('Data Consolidation'!$U$3:$U$21,'Data Consolidation'!$A$3:$A$21,"Other Income") | N16: =G16+H16+I16+J16+K16+L16+M16
B20: Avg NRI Analysis | D20: % Difference | F20: Net Rental Income
B21: T1 | C21: =G16 | D21: =(C21-C22)/C22 | E21: T1vsT3
B22: T3 | C22: =AVERAGE(G14:G16) | D22: =(C22-C23)/C23 | E22: T3vsT6
B23: T6 | C23: =AVERAGE(G11:G16) | D23: =(C23-C24)/C24 | E23: T6vsT12
B24: T12 | C24: =AVERAGE(G5:G16)
F40: EGI

Sheet Rent Roll Input
A1: RENT ROLL April 2026 | E1: MHC Only | I1: Apartments | N1: Other Income | Q1: Commercial Leases
A2: Count | B2: Unit | C2: Unit Type | D2: Occupied or Vacant | F2: Name | G2: Type detail | H2: Type code | I2: Lot Rent | J2: Home Rent | K2: Combined | M2: Combined | N2: Storage | O2: Utility RUBS | P2: Pet Income | Q2: Lease Amount | R2: Maturity | S2: Lease Type | T2: CAM Amount
A3: =IF(C3="","",ROW()-2) | C3: TOH MH Site | D3: Occupied | F3: Individual tenants (names not provided in extraction) 1 | I3: 966.38 | J3: 0 | K3: =IFERROR(I3+J3,0) | M3: =K3+L3+I3
A4: =IF(C4="","",ROW()-2) | C4: TOH MH Site | D4: Occupied | F4: Individual tenants (names not provided in extraction) 2 | I4: 966.38 | J4: 0 | K4: =IFERROR(I4+J4,0) | M4: =K4+L4+I4
A5: =IF(C5="","",ROW()-2) | C5: TOH MH Site | D5: Occupied | F5: Individual tenants (names not provided in extraction) 3 | I5: 966.38 | J5: 0 | K5: =IFERROR(I5+J5,0) | M5: =K5+L5+I5
A6: =IF(C6="","",ROW()-2) | C6: TOH MH Site | D6: Occupied | F6: Individual tenants (names not provided in extraction) 4 | I6: 966.38 | J6: 0 | K6: =IFERROR(I6+J6,0) | M6: =K6+L6+I6
A7: =IF(C7="","",ROW()-2) | C7: TOH MH Site | D7: Occupied | F7: Individual tenants (names not provided in extraction) 5 | I7: 966.38 | J7: 0 | K7: =IFERROR(I7+J7,0) | M7: =K7+L7+I7
A8: =IF(C8="","",ROW()-2) | C8: TOH MH Site | D8: Occupied | F8: Individual tenants (names not provided in extraction) 6 | I8: 966.38 | J8: 0 | K8: =IFERROR(I8+J8,0) | M8: =K8+L8+I8
A9: =IF(C9="","",ROW()-2) | C9: TOH MH Site | D9: Occupied | F9: Individual tenants (names not provided in extraction) 7 | I9: 966.38 | J9: 0 | K9: =IFERROR(I9+J9,0) | M9: =K9+L9+I9
A10: =IF(C10="","",ROW()-2) | C10: TOH MH Site | D10: Occupied | F10: Individual tenants (names not provided in extraction) 8 | I10: 966.38 | J10: 0 | K10: =IFERROR(I10+J10,0) | M10: =K10+L10+I10
A11: =IF(C11="","",ROW()-2) | C11: TOH MH Site | D11: Occupied | F11: Individual tenants (names not provided in extraction) 9 | I11: 966.38 | J11: 0 | K11: =IFERROR(I11+J11,0) | M11: =K11+L11+I11
A12: =IF(C12="","",ROW()-2) | C12: TOH MH Site | D12: Occupied | F12: Individual tenants (names not provided in extraction) 10 | I12: 966.38 | J12: 0 | K12: =IFERROR(I12+J12,0) | M12: =K12+L12+I12
A13: =IF(C13="","",ROW()-2) | C13: TOH MH Site | D13: Occupied | F13: Individual tenants (names not provided in extraction) 11 | I13: 966.38 | J13: 0 | K13: =IFERROR(I13+J13,0) | M13: =K13+L13+I13
A14: =IF(C14="","",ROW()-2) | C14: TOH MH Site | D14: Occupied | F14: Individual tenants (names not provided in extraction) 12 | I14: 966.38 | J14: 0 | K14: =IFERROR(I14+J14,0) | M14: =K14+L14+I14
... A72: =IF(C72="","",ROW()-2) | C72: TOH MH Site | D72: Occupied | F72: Individual tenants (names not provided in extraction) 70 | I72: 966.38 | J72: 0 | K72: =IFERROR(I72+J72,0) | M72: =K72+L72+I72
A73: =IF(C73="","",ROW()-2) | C73: TOH MH Site | D73: Occupied | F73: Individual tenants (names not provided in extraction) 71 | I73: 966.38 | J73: 0 | K73: =IFERROR(I73+J73,0) | O73: =SUM(O3:O72) | P73: =SUM(P3:P72) | Q73: =SUM(Q3:Q72) | R73: N/A | S73: N/A | T73: =SUM(T3:T72)
A74: =IF(C74="","",ROW()-2) | C74: TOH MH Site | D74: Occupied | F74: Individual tenants (names not provided in extraction) 72 | I74: 966.38 | J74: 0 | K74: =IFERROR(I74+J74,0)
A75: =IF(C75="","",ROW()-2) | C75: TOH MH Site | D75: Occupied | F75: Individual tenants (names not provided in extraction) 73 | I75: 966.38 | J75: 0 | K75: =IFERROR(I75+J75,0) | O75: =O73*12
A76: =IF(C76="","",ROW()-2) | C76: TOH MH Site | D76: Occupied | F76: Individual tenants (names not provided in extraction) 74 | I76: 966.38 | J76: 0 | K76: =IFERROR(I76+J76,0)
A77: =IF(C77="","",ROW()-2) | C77: TOH MH Site | D77: Occupied | F77: Individual tenants (names not provided in extraction) 75 | I77: 966.38 | J77: 0 | K77: =IFERROR(I77+J77,0)
A78: =IF(C78="","",ROW()-2) | C78: TOH MH Site | D78: Occupied | F78: Individual tenants (names not provided in extraction) 76 | I78: 966.38 | J78: 0 | K78: =IFERROR(I78+J78,0)
A79: =IF(C79="","",ROW()-2) | C79: TOH MH Site | D79: Occupied | F79: Individual tenants (names not provided in extraction) 77 | I79: 966.38 | J79: 0 | K79: =IFERROR(I79+J79,0)
A80: =IF(C80="","",ROW()-2) | C80: TOH MH Site | D80: Occupied | F80: Individual tenants (names not provided in extraction) 78 | I80: 966.38 | J80: 0 | K80: =IFERROR(I80+J80,0)
A81: =IF(C81="","",ROW()-2) | C81: TOH MH Site | D81: Occupied | F81: Individual tenants (names not provided in extraction) 79 | I81: 966.38 | J81: 0 | K81: =IFERROR(I81+J81,0)
A82: =IF(C82="","",ROW()-2) | C82: TOH MH Site | D82: Occupied | F82: Individual tenants (names not provided in extraction) 80 | I82: 966.38 | J82: 0 | K82: =IFERROR(I82+J82,0)
A83: =IF(C83="","",ROW()-2) | C83: TOH MH Site | D83: Occupied | F83: Individual tenants (names not provided in extraction) 81 | I83: 966.38 | J83: 0 | K83: =IFERROR(I83+J83,0)
A84: =IF(C84="","",ROW()-2) | C84: TOH MH Site | D84: Occupied | F84: Individual tenants (names not provided in extraction) 82 | I84: 966.38 | J84: 0 | K84: =IFERROR(I84+J84,0)
A85: =IF(C85="","",ROW()-2) | C85: TOH MH Site | D85: Occupied | F85: Individual tenants (names not provided in extraction) 83 | I85: 966.38 | J85: 0 | K85: =IFERROR(I85+J85,0)
A86: =IF(C86="","",ROW()-2) | C86: TOH MH Site | D86: Occupied | F86: Individual tenants (names not provided in extraction) 84 | I86: 966.38 | J86: 0 | K86: =IFERROR(I86+J86,0)
A87: =IF(C87="","",ROW()-2) | C87: TOH MH Site | D87: Occupied | F87: Individual tenants (names not provided in extraction) 85 | I87: 966.38 | J87: 0 | K87: =IFERROR(I87+J87,0)
... A107: =IF(C107="","",ROW()-2) | C107: TOH MH Site | D107: Occupied | F107: Individual tenants (names not provided in extraction) 105 | I107: 966.38 | J107: 0 | K107: =IFERROR(I107+J107,0)
A108: =IF(C108="","",ROW()-2) | C108: TOH MH Site | D108: Vacant | I108: 0 | J108: 0 | K108: =IFERROR(I108+J108,0)
A109: =IF(C109="","",ROW()-2) | C109: TOH MH Site | D109: Vacant | I109: 0 | J109: 0 | K109: =IFERROR(I109+J109,0)
A110: =IF(C110="","",ROW()-2) | C110: Long term RV Site | D110: Occupied | F110: Long-term RV tenants 108 | I110: 738.83 | J110: 0 | K110: =IFERROR(I110+J110,0)
A111: =IF(C111="","",ROW()-2) | C111: Long term RV Site | D111: Occupied | F111: Long-term RV tenants 109 | I111: 738.83 | J111: 0 | K111: =IFERROR(I111+J111,0)
A112: =IF(C112="","",ROW()-2) | C112: Long term RV Site | D112: Occupied | F112: Long-term RV tenants 110 | I112: 738.83 | J112: 0 | K112: =IFERROR(I112+J112,0)
A113: =IF(C113="","",ROW()-2) | C113: Long term RV Site | D113: Occupied | F113: Long-term RV tenants 111 | I113: 738.83 | J113: 0 | K113: =IFERROR(I113+J113,0)
A114: =IF(C114="","",ROW()-2) | C114: Long term RV Site | D114: Occupied | F114: Long-term RV tenants 112 | I114: 738.83 | J114: 0 | K114: =IFERROR(I114+J114,0)
A115: =IF(C115="","",ROW()-2) | C115: Long term RV Site | D115: Occupied | F115: Long-term RV tenants 113 | I115: 738.83 | J115: 0 | K115: =IFERROR(I115+J115,0)
A116: =IF(C116="","",ROW()-2) | C116: Long term RV Site | D116: Occupied | F116: Long-term RV tenants 114 | I116: 738.83 | J116: 0 | K116: =IFERROR(I116+J116,0)
A117: =IF(C117="","",ROW()-2) | C117: Long term RV Site | D117: Occupied | F117: Long-term RV tenants 115 | I117: 738.83 | J117: 0 | K117: =IFERROR(I117+J117,0)
A118: =IF(C118="","",ROW()-2) | C118: Long term RV Site | D118: Occupied | F118: Long-term RV tenants 116 | I118: 738.83 | J118: 0 | K118: =IFERROR(I118+J118,0)
A119: =IF(C119="","",ROW()-2) | C119: Long term RV Site | D119: Occupied | F119: Long-term RV tenants 117 | I119: 738.83 | J119: 0 | K119: =IFERROR(I119+J119,0)
A120: =IF(C120="","",ROW()-2) | C120: Long term RV Site | D120: Occupied | F120: Long-term RV tenants 118 | I120: 738.83 | J120: 0 | K120: =IFERROR(I120+J120,0)
A121: =IF(C121="","",ROW()-2) | C121: Long term RV Site | D121: Occupied | F121: Long-term RV tenants 119 | I121: 738.83 | J121: 0 | K121: =IFERROR(I121+J121,0)
... A129: =IF(C129="","",ROW()-2) | C129: Retail/Commercial | D129: Occupied | F129: 1 Commercial Space ($1,200) + 1 Storage ($75) 127 | I129: 637.5 | J129: 0 | K129: =IFERROR(I129+J129,0)
A130: =IF(C130="","",ROW()-2) | K130: =IFERROR(I130+J130,0)
A131: =IF(C131="","",ROW()-2) | K131: =IFERROR(I131+J131,0)
A132: =IF(C132="","",ROW()-2) | K132: =IFERROR(I132+J132,0)
A133: =IF(C133="","",ROW()-2) | K133: =IFERROR(I133+J133,0)
A134: =IF(C134="","",ROW()-2) | K134: =IFERROR(I134+J134,0)
A135: =IF(C135="","",ROW()-2) | K135: =IFERROR(I135+J135,0)
A136: =IF(C136="","",ROW()-2) | K136: =IFERROR(I136+J136,0)
A137: =IF(C137="","",ROW()-2) | K137: =IFERROR(I137+J137,0)
A138: =IF(C138="","",ROW()-2) | K138: =IFERROR(I138+J138,0)
A139: =IF(C139="","",ROW()-2) | K139: =IFERROR(I139+J139,0)
A140: =IF(C140="","",ROW()-2) | K140: =IFERROR(I140+J140,0)
A141: =IF(C141="","",ROW()-2) | K141: =IFERROR(I141+J141,0)
... A150: =IF(C150="","",ROW()-2) | K150: =IFERROR(I150+J150,0)
A151: =IF(C151="","",ROW()-2) | B151: Totals | I151: =SUM(I3:I150) | J151: =SUM(J3:J150) | K151: =SUM(K3:K150)
A152: =IF(C152="","",ROW()-2) | K152: =IFERROR(I152+J152,0)
A153: =IF(C153="","",ROW()-2) | K153: =IFERROR(I153+J153,0)
A154: =IF(C154="","",ROW()-2) | K154: =IFERROR(I154+J154,0)
A155: =IF(C155="","",ROW()-2) | K155: =IFERROR(I155+J155,0)
A156: =IF(C156="","",ROW()-2) | K156: =IFERROR(I156+J156,0)
A157: =IF(C157="","",ROW()-2) | K157: =IFERROR(I157+J157,0)
A158: =IF(C158="","",ROW()-2) | K158: =IFERROR(I158+J158,0)
A159: =IF(C159="","",ROW()-2) | K159: =IFERROR(I159+J159,0)
A160: =IF(C160="","",ROW()-2) | K160: =IFERROR(I160+J160,0)
A161: =IF(C161="","",ROW()-2) | K161: =IFERROR(I161+J161,0)
A162: =IF(C162="","",ROW()-2) | K162: =IFERROR(I162+J162,0)
A163: =IF(C163="","",ROW()-2) | K163: =IFERROR(I163+J163,0)
... A1002: =IF(C1002="","",ROW()-2) | K1002: =IFERROR(I1002+J1002,0)
E1003: =SUM(E3:E1002) | F1003: =SUM(F3:F1002) | G1003: =SUM(G3:G1002) | H1003: =SUM(H3:H1002) | I1003: =SUM(I3:I1002) | J1003: =SUM(J3:J1002) | K1003: =SUM(K3:K1002) | L1003: =SUM(L3:L1002) | ... N1003: =SUM(N3:N1002)
F1004: =AVERAGE(F3:F1002) | G1004: =AVERAGE(G3:G1002)
E1005: =E1003*12 | F1005: =F1003*12 | G1005: =G1003*12 | H1005: =H1003*12 | N1005: =N1003*12

Sheet Unit Mix Rent Growth
A1: GARY GROUP CAPITAL - UNIT MIX GROWTH
B2: for y1 realized only increases starting May
A3: Lots only | B3: next increase in May 2026
A4: Key Assumptions | B4: Year 1 | C4: Year 2 | D4: Year 3 | E4: Year 4 | F4: Year 5 | G4: Year 6 | H4: Year 7 | I4: Year 8 | J4: Year 9 | K4: Year 10
A5: MH Lot Rent (TOH) | B5: 0.035 | C5: 0.075 | D5: 0.07 | E5: 0.05 | F5: 0.04 | G5: 0.04 | H5: 0.04 | I5: 0.04 | J5: 0.04 | K5: 0.04
A6: Long Term RV Rent | B6: 0.063 | C6: 0.075 | D6: 0.07 | E6: 0.05 | F6: 0.04 | G6: 0.04 | H6: 0.04 | I6: 0.04 | J6: 0.04 | K6: 0.04
B7: 0.042 | C7: 0.075 | D7: 0.07 | E7: 0.05 | F7: 0.04 | G7: 0.04 | H7: 0.04 | I7: 0.04 | J7: 0.04 | K7: 0.04
B8: 0.035 | C8: 0.075 | D8: 0.07 | E8: 0.05 | F8: 0.04 | G8: 0.04 | H8: 0.04 | I8: 0.04 | J8: 0.04 | K8: 0.04
B10: =IFERROR(D10/$D$12,0) | C10: ='Unit Mix Summary'!B4 | D10: ='Unit Mix Summary'!E4 | E10: =IFERROR('Unit Mix Summary'!H4/'Unit Mix Summary'!E4,0) | F10: =E10*(100%+B$5) | G10: =F10*(100%+C$5) | H10: =G10*(100%+D$5) | I10: =H10*(100%+E$5) | J10: =I10*(100%+F$5) | K10: =J10*(100%+G$5)
B11: =IFERROR(D11/$D$12,0) | C11: ='Unit Mix Summary'!B5 | D11: ='Unit Mix Summary'!E5 | E11: =IFERROR('Unit Mix Summary'!H5/'Unit Mix Summary'!E5,0) | F11: =E11*(100%+B$6) | G11: =F11*(100%+C$6) | H11: =G11*(100%+D$6) | I11: =H11*(100%+E$6) | J11: =I11*(100%+F$6) | K11: =J11*(100%+G$6)
B12: =SUM(B10:B11) | C12: Total Weighted Average | D12: =SUM(D10:D11) | E12: =SUMPRODUCT($B$10:$B$11,E10:E11) | F12: =SUMPRODUCT($B$10:$B$11,F10:F11) | G12: =SUMPRODUCT($B$10:$B$11,G10:G11) | H12: =SUMPRODUCT($B$10:$B$11,H10:H11) | I12: =SUMPRODUCT($B$10:$B$11,I10:I11) | J12: =SUMPRODUCT($B$10:$B$11,J10:J11) | K12: =SUMPRODUCT($B$10:$B$11,K10:K11)
D13: $change | F13: =F12-E12 | G13: =G12-F12 | H13: =H12-G12 | I13: =I12-H12 | J13: =J12-I12 | K13: =K12-J12 | M13: Year 8 | N13: Year 9 | O13: Year 10
D14: GPR | E14: =E12*$D$12*12 | F14: =F12*$D$12*12 | G14: =G12*$D$12*12 | H14: =H12*$D$12*12 | I14: =I12*$D$12*12 | J14: =J12*$D$12*12 | K14: =K12*$D$12*12 | M14: =L14*(100%+I$5) | N14: =M14*(100%+J$5) | O14: =N14*(100%+K$5)
C15: 0 | D15: Vacant Lots | E15: ='Unit Mix Summary'!D4 | F15: =E15-C15 | M15: =L15*(100%+I$6) | N15: =M15*(100%+J$6) | O15: =N15*(100%+K$6)
C16: 0 | D16: Vacant Homes | E16: ='Unit Mix Summary'!D5 | F16: =E16-$C$16 | M16: =L16*(100%+I$7) | N16: =M16*(100%+J$7) | O16: =N16*(100%+K$7)
D17: Vacancy | E17: =SUM(E15:E16)/$D$12 | F17: =SUM(F15:F16)/$D$12 | G17: =SUM(G15:G16)/$D$12 | H17: =SUM(H15:H16)/$D$12 | I17: =SUM(I15:I16)/$D$12 | J17: =SUM(J15:J16)/$D$12 | K17: =SUM(K15:K16)/$D$12 | M17: =L17*(100%+I$8) | N17: =M17*(100%+J$8) | O17: =N17*(100%+K$8)
M18: =L18*(100%+I$9) | N18: =M18*(100%+J$9) | O18: =N18*(100%+K$9)
M19: =L19*(100%+I$10) | N19: =M19*(100%+J$10) | O19: =N19*(100%+K$10)
M20: 0 | N20: 0 | O20: 0
M21: =M16-L16 | N21: =N16-M16 | O21: =O16-N16
M22: =(J14*(1+G$5)*(1+H$5)*C14+J15*(1+G$6)*(1+H$6)*C15)*12 | N22: =(J14*(1+G$5)*(1+H$5)*(1+I$5)*C14+J15*(1+G$6)*(1+H$6)*(1+I$6)*C15)*12 | O22: =(J14*(1+G$5)*(1+H$5)*(1+I$5)*(1+J$5)*C14+J15*(1+G$6)*(1+H$6)*(1+I$6)*(1+J$6)*C15)*12
D23: Vacant Lots | E23: ='Unit Mix Summary'!D4+'Unit Mix Summary'!D5 | F23: =E23 | G23: =$F$23 | H23: =$F$23 | I23: =$F$23 | J23: =$F$23 | K23: =$F$23 | L23: =$F$23 | M23: =$F$23 | N23: =$F$23 | O23: =$F$23
D24: Vacant Homes | E24: ='Unit Mix Summary'!D6 | F24: =E24-1 | G24: =$F$24 | H24: =$F$24 | I24: =$F$24 | J24: =$F$24 | K24: =$F$24 | L24: =$F$24 | M24: =$F$24 | N24: =$F$24 | O24: =$F$24
D25: Vacancy | E25: =SUM(E23:E24)/$D$20 | F25: =SUM(F23:F24)/$D$20 | G25: =SUM(G23:G24)/$D$20 | H25: =SUM(H23:H24)/$D$20 | I25: =SUM(I23:I24)/$D$20 | J25: =SUM(J23:J24)/$D$20 | K25: =SUM(K23:K24)/$D$20 | L25: =SUM(L23:L24)/$D$20 | ... O25: =SUM(O23:O24)/$D$20
F26: min vacancy estimated
E27: 1 SW LTO 43 being evicted so categorized as a vacant POH
E28: lot 69 is a vacant site--home to be delivered in few weeks
E29: LOT 8 IS A HOME CURRENTLY BEING REHABBED
A34: Key Assumptions | B34: Year 1 | C34: Year 2 | D34: Year 3 | E34: Year 4 | F34: Year 5 | G34: Year 6 | H34: Year 7 | I34: Year 8 | J34: Year 9 | K34: Year 10
A35: POH Home Rents | B35: =4%*(8/12) | C35: 0.04 | D35: 0.04 | E35: 0.04 | F35: 0.04 | G35: 0.04 | H35: 0.04 | I35: 0.04 | J35: 0.04 | K35: 0.04
D37: Home Rents
C38: Unit Mix | D38: # of Units | E38: Avg Monthly Rent | F38: Year 1 | G38: Year 2 | H38: Year 3 | I38: Year 4 | J38: Year 5 | K38: Year 6 | L38: Year 7 | M38: Year 8 | N38: Year 9 | O38: Year 10
B39: assumes 2 vacant POH to be sold | C39: Occupied POH Rentals | D39: ='Unit Mix Summary'!C6+'Unit Mix Summary'!C7 | E39: ='Rent Roll Input'!F1004 | F39: =E39*(100%+B$35) | G39: =F39*(100%+C$35) | H39: =G39*(100%+D$35) | I39: =H39*(100%+E$35) | J39: =I39*(100%+F$35) | K39: =J39*(100%+G$35) | L39: =K39*(100%+H$35) | M39: =L39*(100%+I$35) | ... O39: =N39*(100%+K$35)
D40: Gross Home Rent Income | E40: =E39*$D$39*12 | F40: =F39*$D$39*12 | G40: =G39*$D$39*12 | H40: =H39*$D$39*12 | I40: =I39*$D$39*12 | J40: =J39*$D$39*12 | K40: =K39*$D$39*12 | L40: =L39*$D$39*12 | ... O40: =O39*$D$39*12
D41: Net HRI(less 5%) | E41: =E40*95% | F41: =F40*95% | G41: =G40*95% | H41: =H40*95% | I41: =I40*95% | J41: =J40*95% | K41: =K40*95% | L41: =L40*95% | ... O41: =O40*95%
C44: Conversion Model
H45: until POH% comes down to 22%
A47: Conversion | C47: These are currently 100% occupied | E47: POH Rentals%
A48: sell existing POH | E48: ='Unit Mix Summary'!C20 | F48: =F50/'Unit Mix Summary'!$E$12 | G48: =G50/'Unit Mix Summary'!$E$12 | H48: =H50/'Unit Mix Summary'!$E$12 | I48: =I50/'Unit Mix Summary'!$E$12 | J48: =J50/'Unit Mix Summary'!$E$12 | K48: =K50/'Unit Mix Summary'!$E$12 | L48: =L50/'Unit Mix Summary'!$E$12 | M48: =M50/'Unit Mix Summary'!$E$12 | ... O48: =O50/'Unit Mix Summary'!$E$12
E49: Current POH Rentals | F49: Year 1 | G49: Year 2 | H49: Year 3 | I49: Year 4 | J49: Year 5 | K49: Year 6 | L49: Year 7 | M49: Year 8 | N49: Year 9 | O49: Year 10
C50: 3 | D50: #units | E50: =D39 | F50: =E50-$C$50 | G50: =F50-$C$50 | H50: =G50-$C$50 | I50: =H50-$C$50 | J50: =$I$50 | K50: =$I$50 | L50: =$I$50 | M50: =$I$50 | N50: =$I$50 | O50: =$I$50
D51: Gross HRI | E51: =E50*E39*12 | F51: =F50*F39*12 | G51: =G50*G39*12 | H51: =H50*H39*12 | I51: =I50*I39*12 | J51: =J50*J39*12 | K51: =K50*K39*12 | L51: =L50*L39*12 | ... O51: =O50*O39*12
D52: Less stabilized estimated vacancy% | E52: 0.05 | F52: 0.02 | G52: 0.02 | H52: 0.02 | I52: 0.02 | J52: 0.02 | K52: 0.02 | L52: 0.02 | M52: 0.02 | N52: 0.02 | O52: 0.02
D53: New Net HRI after conversion | E53: =E51*(100%-E52) | F53: =F51*(100%-F52) | G53: =G51*(100%-G52) | H53: =H51*(100%-H52) | I53: =I51*(100%-I52) | J53: =J51*(100%-J52) | K53: =K51*(100%-K52) | L53: =L51*(100%-L52) | ... O53: =O51*(100%-O52)
D56: New Pro forma Vacancy as we sell down the POH
D57: Vacant Lots | F57: =F23 | G57: =G23 | H57: =H23 | I57: =I23 | J57: =J23 | K57: =K23 | L57: =L23 | M57: =M23 | ... O57: =O23
D58: Vacant Homes | F58: =F24 | G58: =G24 | H58: =H24 | I58: =I24 | J58: =J24 | K58: =K24 | L58: =L24 | M58: =M24 | ... O58: =O24
D59: Estimated Stabilized Vacancy for existing homes(available homes*stabilized vacancy%) | F59: =F52*F50 | G59: =G52*G50 | H59: =H52*H50 | I59: =I52*I50 | J59: =J52*J50 | K59: =K52*K50 | L59: =L52*L50 | M59: =M52*M50 | ... O59: =O52*O50
D60: New Vacancy in Proforma after conversion | F60: =SUM(F57:F59)/'Unit Mix Summary'!$E$12 | G60: =SUM(G57:G59)/'Unit Mix Summary'!$E$12 | H60: =SUM(H57:H59)/'Unit Mix Summary'!$E$12 | I60: =SUM(I57:I59)/'Unit Mix Summary'!$E$12 | J60: =SUM(J57:J59)/'Unit Mix Summary'!$E$12 | K60: =SUM(K57:K59)/'Unit Mix Summary'!$E$12 | L60: =SUM(L57:L59)/'Unit Mix Summary'!$E$12 | M60: =SUM(M57:M59)/'Unit Mix Summary'!$E$12 | ... O60: =SUM(O57:O59)/'Unit Mix Summary'!$E$12
E64: Y1 | F64: Y2 | G64: Y3 | H64: Y4
C65: Sales Proceeds from selling existing homes | E65: =E50-F50 | F65: =F50-G50 | G65: =G50-H50 | H65: =H50-I50
B66: Price/Home | C66: 35000 | D66: Sales Proceeds | E66: =E65*$C$66 | F66: =F65*$C$66 | G66: =G65*$C$66 | H66: =H65*$C$66
C67: 0.1 | D67: Cost of Sales | E67: =-$C$67*E66 | F67: =-$C$67*F66 | G67: =-$C$67*G66 | H67: =-$C$67*H66
D68: Net Existing Home Sales Proceeds | E68: =SUM(E66:E67) | F68: =SUM(F66:F67) | G68: =SUM(G66:G67) | H68: =SUM(H66:H67)
A73: Key Assumptions | B73: Year 1 | C73: Year 2 | D73: Year 3 | E73: Year 4 | F73: Year 5 | G73: Year 6 | H73: Year 7 | I73: Year 8 | J73: Year 9 | K73: Year 10
A74: LTO | B74: =C109 | C74: =D109 | D74: =E109 | E74: =F109 | F74: =G109 | G74: =H109 | H74: =I109 | I74: =J109 | ... K74: =L109
C77: Lot | D77: Balance | E77: Interest Rate | F77: Amortization | G77: Last Payment on Contract | H77: Maturity Year
C78: 1 | D78: 6000 | E78: 11 | F78: 15yrs | G78: 46600 | H78: 2027
C79: 3 | D79: 14079 | E79: 10 | F79: 10yyrs | G79: 49400 | H79: 2035
C80: 12 | D80: 28400 | E80: 11 | F80: 20yrs | G80: 47849 | H80: 2031
C81: 19 | D81: 24768 | E81: 11 | F81: 10yrs | G81: 49706 | H81: 2036
C82: 21 | D82: 25000 | E82: 9 | F82: 8yrs | G82: 47880 | H82: 2031
C83: 24 | D83: 20700 | E83: 11 | F83: 25yrs | G83: 51592 | H83: 2041
C84: 26 | D84: 63900 | E84: 10 | F84: 20yrs | G84: 53053 | H84: 2045
C85: 32 | D85: 32400 | E85: 10 | F85: 20yrs | G85: 53053 | H85: 2045
C86: 33 | D86: 30000 | E86: 9 | F86: 8yrs | G86: 47969 | H86: 2031
C87: 39 | D87: 12500 | E87: 11 | F87: 22yrs | G87: 50375 | H87: 2037
C88: 43 | D88: 18700 | E88: 11 | F88: 10yrs | G88: 49522 | H88: 2035
C89: 45 | D89: being evicted | H89: 1900 | J89: Highlighted have baloon payment at the end of date
C90: 46 | D90: 29000 | E90: 10 | F90: 10yrs | G90: 47604 | H90: 2030 | I90: =4/16
C91: 50 | D91: 38000 | E91: 10 | F91: 12yrs | G91: 50100 | H91: 2037
C92: 56 | D92: 23175 | E92: 9 | F92: 30yrs | G92: 52597 | H92: 2044
C93: 57 | D93: 48480 | E93: 10 | F93: 15yrs | G93: 51227 | H93: 2040
C94: 58 | D94: 26750 | E94: 11 | F94: 30yrs | G94: 54544 | H94: 2049
C96: Maturity | D96: Count | E96: LTO | F96: ='Unit Mix Summary'!E14*'Rent Roll Input'!G1004*12
B97: Y1 | C97: 2026 | D97: =COUNTIF($H$78:$H$94,C97) | F97: =-D97/$F$96
B98: Y2 | C98: 2027 | D98: =COUNTIF($H$78:$H$94,C98) | F98: =-D98/$F$96
B99: Y3 | C99: =C98+1 | D99: =COUNTIF($H$78:$H$94,C99) | F99: =-D99/$F$96
B100: Y4 | C100: =C99+1 | D100: =COUNTIF($H$78:$H$94,C100) | F100: =-D100/$F$96
B101: Y5 | C101: =C100+1 | D101: =COUNTIF($H$78:$H$94,C101) | F101: =-D101/$F$96
B102: Y6 | C102: =C101+1 | D102: =COUNTIF($H$78:$H$94,C102) | F102: =-D102/$F$96
B103: Y7 | C103: =C102+1 | D103: =COUNTIF($H$78:$H$94,C103) | F103: =-D103/$F$96
B104: Y8 | C104: =C103+1 | D104: =COUNTIF($H$78:$H$94,C104) | F104: =-D104/$F$96
B105: Y9 | C105: =C104+1 | D105: =COUNTIF($H$78:$H$94,C105) | F105: =-D105/$F$96
B106: Y10 | C106: =C105+1 | D106: =COUNTIF($H$78:$H$94,C106) | F106: =-D106/$F$96
D107: =SUM(D97:D106) | F107: =-D107/$F$96
B109: LTO | C109: {=TRANSPOSE(F97:F106)} | D109: #DIV/0! | E109: #DIV/0! | F109: #DIV/0! | G109: #DIV/0! | H109: #DIV/0! | I109: #DIV/0! | J109: #DIV/0! | K109: #DIV/0! | L109: #DIV/0!
K117: add new homes
B118: Expansion Sites | D118: # of Units | E118: Avg Monthly Rent | F118: Year 1 | G118: Year 2 | H118: Year 3 | I118: Year 4 | J118: Year 5 | K118: Year 6 | L118: Year 7 | M118: Year 8 | N118: Year 9 | O118: Year 10
D119: New Expansion Sites | K119: 7 | L119: =$K$119 | M119: =$K$119 | N119: 0 | O119: 0
D120: Cumulative New Sites | F120: 0 | G120: 0 | H120: 0 | I120: 0 | J120: 0 | K120: =SUM(F119:K119) | L120: =SUM(K119:L119) | M120: =SUM(K119:M119) | N120: =M120 | O120: =N120
D121: Existing Sites | F121: 69 | G121: 69 | H121: 69 | I121: 69 | J121: 69 | K121: 69 | L121: 69 | M121: 69 | N121: 69 | O121: 69
D122: New Total Sites | F122: =SUM(F120:F121) | G122: =SUM(G120:G121) | H122: =SUM(H120:H121) | I122: =SUM(I120:I121) | J122: =SUM(J120:J121) | K122: =SUM(K120:K121) | L122: =SUM(L120:L121) | M122: =SUM(M120:M121) | ... O122: =SUM(O120:O121)
B123: 80000 | D123: Rents | F123: =F20 | G123: =G20 | H123: =H20 | I123: =I20 | J123: =J20 | K123: =K20 | L123: =L20 | M123: =M20 | ... O123: =O20
B124: =B123*7 | C124: for 7 homes | D124: GPR (with expansion sites) | F124: =F123*F122*12 | G124: =G123*G122*12 | H124: =H123*H122*12 | I124: =I123*I122*12 | J124: =J123*J122*12 | K124: =K123*K122*12 | L124: =L123*L122*12 | M124: =M123*M122*12 | ... O124: =O123*O122*12
D125: Lease up vacancy for new homes %-(Assume takes 3 months to sell) | K125: =3/12 | L125: =$K$125 | M125: =$L$125
D126: Stabilized Vacancy Estimated | F126: 0.03 | G126: 0.03 | H126: 0.03 | I126: 0.03 | J126: 0.03 | K126: 0.03 | L126: 0.03 | M126: 0.03 | N126: 0.03 | O126: 0.03 | S126: blended | T126: 3% stabilized + (estimated time to lease *new sites/total)
D127: Blended Vacancy % | F127: =F126 | G127: =G126 | H127: =H126 | I127: =I126 | J127: =J126 | K127: =K126+(K119/K122*K125) | L127: =L126+(L119/L122*L125) | M127: =M126+(M119/M122*M125) | N127: =N126+(N119/N122*N125) | O127: =O126+(O119/O122*O125)
K128: we sell new homes | L128: we sell new homes | M128: we sell new homes
D130: 85000 | K130: =K119 | L130: =L119 | M130: =M119
...

Sheet Unit Mix Summary
B2: MH/RV Rent Roll | C2: Next Increase in MAY 1 2026--Separate increases -see RR
C3: # of Occupied Units | D3: # of Vacant Units | E3: Total Units | F3: Occupied Monthly Rent | G3: Vacant Monthly Rent | H3: Monthly Gross Potential Rent
B4: TOH MH Site | C4: =COUNTIFS('Rent Roll Input'!$D$3:$D$1002,"Occupied",'Rent Roll Input'!$C$3:$C$1002,"TOH MH Site") | D4: =COUNTIFS('Rent Roll Input'!$D$3:$D$1002,"Vacant",'Rent Roll Input'!$C$3:$C$1002,"TOH MH Site") | E4: =SUM(C4:D4) | F4: =SUMIFS('Rent Roll Input'!$I$3:$I$1002,'Rent Roll Input'!$D$3:$D$1002,"Occupied",'Rent Roll Input'!$C$3:$C$1002,"TOH MH Site") | G4: =SUMIFS('Rent Roll Input'!$I$3:$I$1002,'Rent Roll Input'!$D$3:$D$1002,"Vacant",'Rent Roll Input'!$C$3:$C$1002,"TOH MH Site") | H4: =F4+G4
B5: POH-Infilled units | C5: =COUNTIFS('Rent Roll Input'!$D$3:$D$1002,"Occupied",'Rent Roll Input'!$C$3:$C$1002,"POH-Infilled units") | D5: =COUNTIFS('Rent Roll Input'!$D$3:$D$1002,"Vacant",'Rent Roll Input'!$C$3:$C$1002,"POH-Infilled units") | E5: =SUM(C5:D5) | F5: =SUMIFS('Rent Roll Input'!$I$3:$I$1002,'Rent Roll Input'!$D$3:$D$1002,"Occupied",'Rent Roll Input'!$C$3:$C$1002,"POH-Infilled units") | G5: =SUMIFS('Rent Roll Input'!$I$3:$I$1002,'Rent Roll Input'!$D$3:$D$1002,"Vacant",'Rent Roll Input'!$C$3:$C$1002,"POH-Infilled units") | H5: =F5+G5
B6: Long term RV Site | C6: =COUNTIFS('Rent Roll Input'!$D$3:$D$1002,"Occupied",'Rent Roll Input'!$C$3:$C$1002,"Long term RV Site") | D6: =COUNTIFS('Rent Roll Input'!$D$3:$D$1002,"Vacant",'Rent Roll Input'!$C$3:$C$1002,"Long term RV Site") | E6: =SUM(C6:D6) | F6: =SUMIFS('Rent Roll Input'!$I$3:$I$1002,'Rent Roll Input'!$D$3:$D$1002,"Occupied",'Rent Roll Input'!$C$3:$C$1002,"Long term RV Site") | G6: =SUMIFS('Rent Roll Input'!$I$3:$I$1002,'Rent Roll Input'!$D$3:$D$1002,"Vacant",'Rent Roll Input'!$C$3:$C$1002,"Long term RV Site") | H6: =F6+G6
B7: Retail/Commercial | C7: =COUNTIFS('Rent Roll Input'!$D$3:$D$1002,"Occupied",'Rent Roll Input'!$C$3:$C$1002,"Retail/Commercial") | D7: =COUNTIFS('Rent Roll Input'!$D$3:$D$1002,"Vacant",'Rent Roll Input'!$C$3:$C$1002,"Retail/Commercial") | E7: =SUM(C7:D7) | F7: =SUMIFS('Rent Roll Input'!$I$3:$I$1002,'Rent Roll Input'!$D$3:$D$1002,"Occupied",'Rent Roll Input'!$C$3:$C$1002,"Retail/Commercial") | G7: =SUMIFS('Rent Roll Input'!$I$3:$I$1002,'Rent Roll Input'!$D$3:$D$1002,"Vacant",'Rent Roll Input'!$C$3:$C$1002,"Retail/Commercial") | H7: =F7+G7
B8: Total Units | C8: =SUM(C4:C7) | D8: =SUM(D4:D7) | E8: =SUM(E4:E7)
B9: Total MH Sites (TOH + POH) | C9: =SUM(C4:C5) | D9: =SUM(D4:D5) | E9: =SUM(E4:E5) | F9: =SUM(F4:F5) | G9: =SUM(G4:G5) | H9: =SUM(H4:H5)
B10: Total POH | C10: =C5 | D10: =D5 | E10: =E5
B11: Annual GPR (MH Lot Rent) | C11: =H9*12
B12: Avg MH Lot Rent | C12: =IFERROR(H4/E4,0)
B13: Occupancy % | C13: =IFERROR(C8/E8,0)
B14: POH % | C14: =IFERROR(E10/E9,0)
B15: Annual Long term RV | C15: =H6*12
B16: Long term RV avg rent | C16: =IFERROR(H6/E6,0)
B23: Annual LTO Premium | C23: =H14*12
B24: Avg Lot Rent | C24: ='Rent Roll Input'!G1004

Sheet GGC Underwriting
A1: GARY GROUP CAPITAL
D2: Months: | E2: ='Data Consolidation'!H1 | G2: ALT NOI | H2: Lot Rent only NOI | K2: Comps | L2: Comps | P2: 46108
A3: Income | B3: ='Data Consolidation'!D2 | C3: ='Data Consolidation'!E2 | D3: ='Data Consolidation'!G2 | E3: ='Data Consolidation'!H2 | F3: ='Data Consolidation'!F2 | G3: GGC ProForma | H3: GGC ProForma | I3: GGC ProForma | J3: % of GPR | K3: Expense Comp 1 | L3: Expense Comp 2 | M3: Notes
A4: Gross Potential Rent | B4: =SUMIFS('Data Consolidation'!$D$3:$D$36,'Data Consolidation'!$A$3:$A$36,"Gross Potential Rent") | C4: =SUMIFS('Data Consolidation'!$E$3:$E$36,'Data Consolidation'!$A$3:$A$36,"Gross Potential Rent") | D4: =SUMIFS('Data Consolidation'!$G$3:$G$36,'Data Consolidation'!$A$3:$A$36,"Gross Potential Rent") | E4: =SUMIFS('Data Consolidation'!$H$3:$H$36,'Data Consolidation'!$A$3:$A$36,"Gross Potential Rent") | F4: =SUMIFS('Data Consolidation'!$F$3:$F$36,'Data Consolidation'!$A$3:$A$36,"Gross Potential Rent") | G4: ='Unit Mix Rent Growth'!H14 | H4: =I4 | I4: ='Unit Mix Summary'!C11 | M4: Property Name | N4: Whaleshead Beach Resort | O4: Purchase/Offer Price | P4: 10000000 | Q4: Purchase/Offer Price | S4: Homes
A5: Less: Vacancy | B5: =SUMIFS('Data Consolidation'!$D$3:$D$36,'Data Consolidation'!$A$3:$A$36,"Vacancy") | C5: =SUMIFS('Data Consolidation'!$E$3:$E$36,'Data Consolidation'!$A$3:$A$36,"Vacancy") | D5: =SUMIFS('Data Consolidation'!$G$3:$G$36,'Data Consolidation'!$A$3:$A$36,"Vacancy") | E5: =SUMIFS('Data Consolidation'!$H$3:$H$36,'Data Consolidation'!$A$3:$A$36,"Vacancy") | F5: =SUMIFS('Data Consolidation'!$F$3:$F$36,'Data Consolidation'!$A$3:$A$36,"Vacancy") | G5: =-5%*G4 | H5: =I5 | I5: =-J5*I4 | J5: =100%-N8 | M5: Property Address | N5: 19921 Whaleshead Road | O5: Purchase Price Per Site | P5: =P4/N7 | Q5: Purchase Price Per Site | R5: =R4/P7 | S5: Utilities
A6: Less: Concessions | B6: =SUMIFS('Data Consolidation'!$D$3:$D$36,'Data Consolidation'!$A$3:$A$36,"Concessions") | C6: =SUMIFS('Data Consolidation'!$E$3:$E$36,'Data Consolidation'!$A$3:$A$36,"Concessions") | D6: =SUMIFS('Data Consolidation'!$G$3:$G$36,'Data Consolidation'!$A$3:$A$36,"Concessions") | E6: =SUMIFS('Data Consolidation'!$H$3:$H$36,'Data Consolidation'!$A$3:$A$36,"Concessions") | F6: =SUMIFS('Data Consolidation'!$F$3:$F$36,'Data Consolidation'!$A$3:$A$36,"Concessions") | G6: =-J6*$G$4 | H6: =I6 | I6: 0 | J6: =-I6/I4 | M6: Property Type | N6: Hybrid | O6: Underwritten CAP rate | P6: =I47/P4 | Q6: Underwritten CAP rate | R6: =I47/R4 | S6: Flood Zone
A7: Less: Bad Debt | B7: =SUMIFS('Data Consolidation'!$D$3:$D$36,'Data Consolidation'!$A$3:$A$36,"Bad Debt") | C7: =SUMIFS('Data Consolidation'!$E$3:$E$36,'Data Consolidation'!$A$3:$A$36,"Bad Debt") | D7: =SUMIFS('Data Consolidation'!$G$3:$G$36,'Data Consolidation'!$A$3:$A$36,"Bad Debt") | E7: =SUMIFS('Data Consolidation'!$H$3:$H$36,'Data Consolidation'!$A$3:$A$36,"Bad Debt") | F7: =SUMIFS('Data Consolidation'!$F$3:$F$36,'Data Consolidation'!$A$3:$A$36,"Bad Debt") | G7: =-J7*$G$4 | H7: =I7 | I7: =D7 | J7: 0.03 | M7: # of Units | N7: ='Unit Mix Summary'!E8 | O7: Stabilized YOC | P7: =G47/'Sources and Uses'!C18 | Q7: Stabilized YOC | R7: =G47/'Sources and Uses'!C18
M8: Rent Roll Occupancy | N8: ='Unit Mix Summary'!C13 | P8: ='Unit Mix Summary'!C18
A9: Net Rental Income | B9: =B4-B5-B6-B7 | C9: =SUM(C4:C7) | D9: =SUM(D4:D7) | E9: =SUM(E4:E7) | F9: =SUM(F4:F7) | G9: =SUM(G4:G7) | H9: =SUM(H4:H7) | I9: =SUM(I4:I7) | J9: =I9/12 | M9: Acreage | O9: Asking Price by Seller | P9: 10000000 | Q9: Asking Price by Seller
A10: YoY % Growth | C10: =(C9-B9)/B9 | D10: =(D9-C9)/C9 | E10: =(E9-D9)/D9 | J10: =I9/$N$7 | M10: County | N10: Curry | O10: Asking Price Per Site | P10: =P9/N7 | Q10: Asking Price Per Site | R10: =R9/P7
A12: Utility Reimbursement | B12: =SUMIFS('Data Consolidation'!$D$3:$D$36,'Data Consolidation'!$A$3:$A$36,"Utility Reimbursement") | C12: =SUMIFS('Data Consolidation'!$E$3:$E$36,'Data Consolidation'!$A$3:$A$36,"Utility Reimbursement") | D12: =SUMIFS('Data Consolidation'!$G$3:$G$36,'Data Consolidation'!$A$3:$A$36,"Utility Reimbursement") | E12: =SUMIFS('Data Consolidation'!$H$3:$H$36,'Data Consolidation'!$A$3:$A$36,"Utility Reimbursement") | F12: =SUMIFS('Data Consolidation'!$F$3:$F$36,'Data Consolidation'!$A$3:$A$36,"Utility Reimbursement") | G12: =I12 | H12: =I12 | I12: =D12 | J12: =I12/$N$7 | O12: Brookings Multifamily cap rate at 6%-7.5% | Q12: Cap Rate | R12: Value | S12: Value/Unit | T12: #Units
A13: Home Rent Income | B13: =SUMIFS('Data Consolidation'!$D$3:$D$36,'Data Consolidation'!$A$3:$A$36,"Home Rent Income") | C13: =SUMIFS('Data Consolidation'!$E$3:$E$36,'Data Consolidation'!$A$3:$A$36,"Home Rent Income") | D13: =SUMIFS('Data Consolidation'!$G$3:$G$36,'Data Consolidation'!$A$3:$A$36,"Home Rent Income") | E13: =SUMIFS('Data Consolidation'!$H$3:$H$36,'Data Consolidation'!$A$3:$A$36,"Home Rent Income") | F13: =SUMIFS('Data Consolidation'!$F$3:$F$36,'Data Consolidation'!$A$3:$A$36,"Home Rent Income") | G13: ='Rent Roll Input'!J151*12*95% | H13: 0 | I13: 0 | J13: =I13/$N$7 | M13: Asset | N13: NOI | O13: CAP RATE | P13: VALUE | Q13: 0 | R13: =P13/Q13 | S13: =R13/T13 | T13: 0
A14: RV Site Rental Income | B14: =SUMIFS('Data Consolidation'!$D$3:$D$36,'Data Consolidation'!$A$3:$A$36,"RV Site Rental Income") | C14: =SUMIFS('Data Consolidation'!$E$3:$E$36,'Data Consolidation'!$A$3:$A$36,"RV Site Rental Income") | D14: =SUMIFS('Data Consolidation'!$G$3:$G$36,'Data Consolidation'!$A$3:$A$36,"RV Site Rental Income") | E14: =SUMIFS('Data Consolidation'!$H$3:$H$36,'Data Consolidation'!$A$3:$A$36,"RV Site Rental Income") | F14: =SUMIFS('Data Consolidation'!$F$3:$F$36,'Data Consolidation'!$A$3:$A$36,"RV Site Rental Income") | G14: =I14 | H14: =I14 | I14: ='Unit Mix Summary'!C15*90% | J14: =I14/$N$7 | M14: Lot Rent only NOI | N14: =I47 | O14: 0.055 | P14: =N14/O14 | Q14: 0 | R14: =P14/Q14 | S14: =R14/T14 | T14: 0
A15: Storage Income | B15: =SUMIFS('Data Consolidation'!$D$3:$D$36,'Data Consolidation'!$A$3:$A$36,"Parking Income") | C15: =SUMIFS('Data Consolidation'!$E$3:$E$36,'Data Consolidation'!$A$3:$A$36,"Parking Income") | D15: =SUMIFS('Data Consolidation'!$G$3:$G$36,'Data Consolidation'!$A$3:$A$36,"Parking Income") | E15: =SUMIFS('Data Consolidation'!$H$3:$H$36,'Data Consolidation'!$A$3:$A$36,"Parking Income") | F15: =SUMIFS('Data Consolidation'!$F$3:$F$36,'Data Consolidation'!$A$3:$A$36,"Parking Income") | G15: =I15 | H15: =I15 | I15: =D15 | J15: =I15/$N$7 | M15: Home Rent only NOI | N15: =I47-H47 | O15: 0.12 | P15: =N15/O15
A16: Retail Income | B16: =SUMIFS('Data Consolidation'!$D$3:$D$36,'Data Consolidation'!$A$3:$A$36,"Laundry Income") | C16: =SUMIFS('Data Consolidation'!$E$3:$E$36,'Data Consolidation'!$A$3:$A$36,"Retail") | D16: =SUMIFS('Data Consolidation'!$G$3:$G$36,'Data Consolidation'!$A$3:$A$36,"Retail") | E16: =SUMIFS('Data Consolidation'!$H$3:$H$36,'Data Consolidation'!$A$3:$A$36,"Retail") | F16: =SUMIFS('Data Consolidation'!$F$3:$F$36,'Data Consolidation'!$A$3:$A$36,"Retail") | G16: =I16 | I16: ='Unit Mix Summary'!H7*12*98% | J16: =I16/$N$7 | M16: Total | N16: =SUM(N14:N15) | O16: =N16/P16 | P16: =SUM(P14:P15)
A17: Other Income | B17: =SUMIFS('Data Consolidation'!$D$3:$D$36,'Data Consolidation'!$A$3:$A$36,"Other Income") | C17: =SUMIFS('Data Consolidation'!$E$3:$E$36,'Data Consolidation'!$A$3:$A$36,"Other Income") | D17: =SUMIFS('Data Consolidation'!$G$3:$G$36,'Data Consolidation'!$A$3:$A$36,"Other Income") | E17: =SUMIFS('Data Consolidation'!$H$3:$H$36,'Data Consolidation'!$A$3:$A$36,"Other Income") | F17: =SUMIFS('Data Consolidation'!$F$3:$F$36,'Data Consolidation'!$A$3:$A$36,"Other Income") | G17: =I17 | H17: =I17 | I17: =AVERAGE(C17,D17) | J17: =I17/$N$7
A19: Total Effective Gross Income | B19: =B9+B12+B13+B14+B15+B16+B17 | C19: =C9+C12+C13+C14+C15+C16+C17 | D19: =D9+D12+D13+D14+D15+D16+D17 | E19: =E9+E12+E13+E14+E15+E16+E17 | F19: =F9+F12+F13+F14+F15+F16+F17 | G19: =G9+G12+G13+G14+G15+G16+G17 | H19: =H9+H12+H13+H14+H15+H16+H17 | I19: =I9+I12+I13+I14+I15+I16+I17 | J19: =I19/$N$7 | M19: per month | O19: Tax Analysis Section
A20: YoY % Growth | C20: =(C19-B19)/B19 | D20: =(D19-C19)/C19 | E20: =(E19-D19)/D19 | M20: per unit | O20: Assessed Value
A21: Expenses | B21: =B3 | C21: =C3 | D21: =D3 | E21: Annualization | F21: Broker's Proforma | G21: GGC ProForma | H21: GGC ProForma | I21: GGC ProForma | J21: Per Unit | M21: Notes | O21: Levy Rate
A22: RE Taxes | B22: =SUMIFS('Data Consolidation'!$D$43:$D$102,'Data Consolidation'!$A$43:$A$102,"RE Taxes") | C22: =SUMIFS('Data Consolidation'!$E$43:$E$102,'Data Consolidation'!$A$43:$A$102,"RE Taxes") | D22: =SUMIFS('Data Consolidation'!$G$43:$G$102,'Data Consolidation'!$A$43:$A$102,"RE Taxes") | E22: =SUMIFS('Data Consolidation'!$H$43:$H$102,'Data Consolidation'!$A$43:$A$102,"RE Taxes") | F22: =SUMIFS('Data Consolidation'!$F$43:$F$102,'Data Consolidation'!$A$43:$A$102,"RE Taxes") | G22: =I22 | H22: =I22 | I22: =J22*N7 | J22: 400 | O22: Tax | P22: =P20*P21
A23: Insurance | B23: =SUMIFS('Data Consolidation'!$D$43:$D$102,'Data Consolidation'!$A$43:$A$102,"Insurance") | C23: =SUMIFS('Data Consolidation'!$E$43:$E$102,'Data Consolidation'!$A$43:$A$102,"Insurance") | D23: =SUMIFS('Data Consolidation'!$G$43:$G$102,'Data Consolidation'!$A$43:$A$102,"Insurance") | E23: =SUMIFS('Data Consolidation'!$H$43:$H$102,'Data Consolidation'!$A$43:$A$102,"Insurance") | F23: =SUMIFS('Data Consolidation'!$F$43:$F$102,'Data Consolidation'!$A$43:$A$102,"Insurance") | G23: =I23 | H23: =I23 | I23: =D23*1.05 | J23: =I23/$N$7
A25: Gas/Fuel | B25: =SUMIFS('Data Consolidation'!$D$43:$D$102,'Data Consolidation'!$A$43:$A$102,"Gas/Fuel") | C25: =SUMIFS('Data Consolidation'!$E$43:$E$102,'Data Consolidation'!$A$43:$A$102,"Gas/Fuel") | D25: =SUMIFS('Data Consolidation'!$G$43:$G$102,'Data Consolidation'!$A$43:$A$102,"Gas/Fuel") | E25: =SUMIFS('Data Consolidation'!$H$43:$H$102,'Data Consolidation'!$A$43:$A$102,"Gas/Fuel") | F25: =SUMIFS('Data Consolidation'!$F$43:$F$102,'Data Consolidation'!$A$43:$A$102,"Gas/Fuel") | G25: =I25 | H25: =I25 | I25: =D25*1.03 | J25: =I25/$N$7
A26: Electrcitiy | B26: =SUMIFS('Data Consolidation'!$D$43:$D$102,'Data Consolidation'!$A$43:$A$102,"Electricity") | C26: =SUMIFS('Data Consolidation'!$E$43:$E$102,'Data Consolidation'!$A$43:$A$102,"Electricity") | D26: =SUMIFS('Data Consolidation'!$G$43:$G$102,'Data Consolidation'!$A$43:$A$102,"Electricity") | E26: =SUMIFS('Data Consolidation'!$H$43:$H$102,'Data Consolidation'!$A$43:$A$102,"Electricity") | F26: =SUMIFS('Data Consolidation'!$F$43:$F$102,'Data Consolidation'!$A$43:$A$102,"Electricity") | G26: =I26 | H26: =I26 | I26: =D26*1.03 | J26: =I26/$N$7
A27: Water and Sewer | B27: =SUMIFS('Data Consolidation'!$D$43:$D$102,'Data Consolidation'!$A$43:$A$102,"Water and Sewer") | C27: =SUMIFS('Data Consolidation'!$E$43:$E$102,'Data Consolidation'!$A$43:$A$102,"Water and Sewer") | D27: =SUMIFS('Data Consolidation'!$G$43:$G$102,'Data Consolidation'!$A$43:$A$102,"Water and Sewer") | E27: =SUMIFS('Data Consolidation'!$H$43:$H$102,'Data Consolidation'!$A$43:$A$102,"Water and Sewer") | F27: =SUMIFS('Data Consolidation'!$F$43:$F$102,'Data Consolidation'!$A$43:$A$102,"Water and Sewer") | G27: =I27 | H27: =I27 | I27: =D27*1.03 | J27: =I27/$N$7
A28: Trash Removal | B28: =SUMIFS('Data Consolidation'!$D$43:$D$102,'Data Consolidation'!$A$43:$A$102,"Trash Removal") | C28: =SUMIFS('Data Consolidation'!$E$43:$E$102,'Data Consolidation'!$A$43:$A$102,"Trash Removal") | D28: =SUMIFS('Data Consolidation'!$G$43:$G$102,'Data Consolidation'!$A$43:$A$102,"Trash Removal") | E28: =SUMIFS('Data Consolidation'!$H$43:$H$102,'Data Consolidation'!$A$43:$A$102,"Trash Removal") | F28: =SUMIFS('Data Consolidation'!$F$43:$F$102,'Data Consolidation'!$A$43:$A$102,"Trash Removal") | G28: =I28 | H28: =I28 | I28: =D28*1.03 | J28: =I28/$N$7
A29: Total Utilities | B29: =SUM(B25:B28) | C29: =SUM(C25:C28) | D29: =SUM(D25:D28) | E29: =SUM(E25:E28) | F29: =SUM(F25:F28) | G29: =SUM(G25:G28) | H29: =SUM(H25:H28) | I29: =SUM(I25:I28) | J29: =I29/$N$7 | M29: per unit
A30: Repair and Maintenance | B30: =SUMIFS('Data Consolidation'!$D$43:$D$102,'Data Consolidation'!$A$43:$A$102,"Repair and Maintenance") | C30: =SUMIFS('Data Consolidation'!$E$43:$E$102,'Data Consolidation'!$A$43:$A$102,"Repair and Maintenance") | D30: =SUMIFS('Data Consolidation'!$G$43:$G$102,'Data Consolidation'!$A$43:$A$102,"Repair and Maintenance") | E30: =SUMIFS('Data Consolidation'!$H$43:$H$102,'Data Consolidation'!$A$43:$A$102,"Repair and Maintenance") | F30: =SUMIFS('Data Consolidation'!$F$43:$F$102,'Data Consolidation'!$A$43:$A$102,"Repair and Maintenance") | G30: =I30 | H30: =I30 | I30: =J30*$N$7 | J30: 150
A31: Ground Maintenance | B31: =SUMIFS('Data Consolidation'!$D$43:$D$102,'Data Consolidation'!$A$43:$A$102,"Ground Maintenance") | C31: =SUMIFS('Data Consolidation'!$E$43:$E$102,'Data Consolidation'!$A$43:$A$102,"Ground Maintenance") | D31: =SUMIFS('Data Consolidation'!$G$43:$G$102,'Data Consolidation'!$A$43:$A$102,"Ground Maintenance") | E31: =SUMIFS('Data Consolidation'!$H$43:$H$102,'Data Consolidation'!$A$43:$A$102,"Ground Maintenance") | F31: =SUMIFS('Data Consolidation'!$F$43:$F$102,'Data Consolidation'!$A$43:$A$102,"Ground Maintenance") | G31: =I31 | H31: =I31 | I31: =D31*(100%+3%) | J31: =I31/N7
A32: Recreational Amenities | B32: =SUMIFS('Data Consolidation'!$D$43:$D$102,'Data Consolidation'!$A$43:$A$102,"Recreational Amenities") | C32: =SUMIFS('Data Consolidation'!$E$43:$E$102,'Data Consolidation'!$A$43:$A$102,"Recreational Amenities") | D32: =SUMIFS('Data Consolidation'!$G$43:$G$102,'Data Consolidation'!$A$43:$A$102,"Recreational Amenities") | E32: =SUMIFS('Data Consolidation'!$H$43:$H$102,'Data Consolidation'!$A$43:$A$102,"Recreational Amenities") | F32: =SUMIFS('Data Consolidation'!$F$43:$F$102,'Data Consolidation'!$A$43:$A$102,"Recreational Amenities") | G32: =I32 | H32: =I32 | I32: 0 | J32: =I32/N7
A33: Management Fee | B33: =SUMIFS('Data Consolidation'!$D$43:$D$102,'Data Consolidation'!$A$43:$A$102,"Management Fee") | C33: =SUMIFS('Data Consolidation'!$E$43:$E$102,'Data Consolidation'!$A$43:$A$102,"Management Fee") | D33: =SUMIFS('Data Consolidation'!$G$43:$G$102,'Data Consolidation'!$A$43:$A$102,"Management Fee") | E33: =SUMIFS('Data Consolidation'!$H$43:$H$102,'Data Consolidation'!$A$43:$A$102,"Management Fee") | F33: =SUMIFS('Data Consolidation'!$F$43:$F$102,'Data Consolidation'!$A$43:$A$102,"Management Fee") | G33: =J33*G19 | H33: =J33*H19 | I33: =J33*I19 | J33: 0.05
A34: Management Fee % | B34: =B33/B19 | C34: =C33/C19 | D34: =D33/D19 | E34: =E33/E19 | F34: =F33/F19
A35: Payroll | B35: =SUMIFS('Data Consolidation'!$D$43:$D$102,'Data Consolidation'!$A$43:$A$102,"Payroll") | C35: =SUMIFS('Data Consolidation'!$E$43:$E$102,'Data Consolidation'!$A$43:$A$102,"Payroll") | D35: =SUMIFS('Data Consolidation'!$G$43:$G$102,'Data Consolidation'!$A$43:$A$102,"Payroll") | E35: =SUMIFS('Data Consolidation'!$H$43:$H$102,'Data Consolidation'!$A$43:$A$102,"Payroll") | F35: =SUMIFS('Data Consolidation'!$F$43:$F$102,'Data Consolidation'!$A$43:$A$102,"Payroll") | G35: =I35 | H35: =I35 | I35: =J35*N7 | J35: 600
A36: Employee Allowance | B36: =-SUMIFS('Data Consolidation'!$D$3:$D$36,'Data Consolidation'!$A$3:$A$36,"Employee Allowance (expense)") | C36: =-SUMIFS('Data Consolidation'!$E$3:$E$36,'Data Consolidation'!$A$3:$A$36,"Employee Allowance (expense)") | D36: =-SUMIFS('Data Consolidation'!$G$3:$G$36,'Data Consolidation'!$A$3:$A$36,"Employee Allowance (expense)") | E36: =-SUMIFS('Data Consolidation'!$H$3:$H$36,'Data Consolidation'!$A$3:$A$36,"Employee Allowance (expense)") | F36: =-SUMIFS('Data Consolidation'!$F$3:$F$36,'Data Consolidation'!$A$3:$A$36,"Employee Allowance (expense)") | G36: =I36 | H36: =I36 | I36: 0 | J36: =I36/$N$7
A37: General and Administrative | B37: =SUMIFS('Data Consolidation'!$D$43:$D$102,'Data Consolidation'!$A$43:$A$102,"G&A") | C37: =SUMIFS('Data Consolidation'!$E$43:$E$102,'Data Consolidation'!$A$43:$A$102,"G&A") | D37: =SUMIFS('Data Consolidation'!$G$43:$G$102,'Data Consolidation'!$A$43:$A$102,"G&A") | E37: =SUMIFS('Data Consolidation'!$H$43:$H$102,'Data Consolidation'!$A$43:$A$102,"G&A") | F37: =SUMIFS('Data Consolidation'!$F$43:$F$102,'Data Consolidation'!$A$43:$A$102,"G&A") | G37: =I37 | H37: =I37 | I37: =D37*(100%+3%) | J37: =I37/$N$7
A38: Model Units | B38: =-SUMIFS('Data Consolidation'!$D$3:$D$36,'Data Consolidation'!$A$3:$A$36,"Model Unit (expense)") | C38: =-SUMIFS('Data Consolidation'!$E$3:$E$36,'Data Consolidation'!$A$3:$A$36,"Model Unit (expense)") | D38: =-SUMIFS('Data Consolidation'!$G$3:$G$36,'Data Consolidation'!$A$3:$A$36,"Model Unit (expense)") | E38: =-SUMIFS('Data Consolidation'!$H$3:$H$36,'Data Consolidation'!$A$3:$A$36,"Model Unit (expense)") | F38: =-SUMIFS('Data Consolidation'!$F$3:$F$36,'Data Consolidation'!$A$3:$A$36,"Model Unit (expense)") | G38: =I38 | H38: =I38 | I38: 0 | J38: =I38/$N$7
A39: Professional Fees | B39: =SUMIFS('Data Consolidation'!$D$43:$D$102,'Data Consolidation'!$A$43:$A$102,"Professional Fees") | C39: =SUMIFS('Data Consolidation'!$E$43:$E$102,'Data Consolidation'!$A$43:$A$102,"Professional Fees") | D39: =SUMIFS('Data Consolidation'!$G$43:$G$102,'Data Consolidation'!$A$43:$A$102,"Professional Fees") | E39: =SUMIFS('Data Consolidation'!$H$43:$H$102,'Data Consolidation'!$A$43:$A$102,"Professional Fees") | F39: =SUMIFS('Data Consolidation'!$F$43:$F$102,'Data Consolidation'!$A$43:$A$102,"Professional Fees") | G39: =I39 | H39: =I39 | I39: =D39*1.03 | J39: =I39/$N$7
A40: Advertising | B40: =SUMIFS('Data Consolidation'!$D$43:$D$102,'Data Consolidation'!$A$43:$A$102,"Advertising") | C40: =SUMIFS('Data Consolidation'!$E$43:$E$102,'Data Consolidation'!$A$43:$A$102,"Advertising") | D40: =SUMIFS('Data Consolidation'!$G$43:$G$102,'Data Consolidation'!$A$43:$A$102,"Advertising") | E40: =SUMIFS('Data Consolidation'!$H$43:$H$102,'Data Consolidation'!$A$43:$A$102,"Advertising") | F40: =SUMIFS('Data Consolidation'!$F$43:$F$102,'Data Consolidation'!$A$43:$A$102,"Advertising") | G40: =I40 | H40: =I40 | I40: =D40*1.03 | J40: =I40/$N$7
A41: Home Rent Expense (MH) | B41: =SUMIFS('Data Consolidation'!$D$43:$D$102,'Data Consolidation'!$A$43:$A$102,"Home Rent Expense") | C41: =SUMIFS('Data Consolidation'!$E$43:$E$102,'Data Consolidation'!$A$43:$A$102,"Home Rent Expense") | D41: =SUMIFS('Data Consolidation'!$G$43:$G$102,'Data Consolidation'!$A$43:$A$102,"Home Rent Expense") | E41: =SUMIFS('Data Consolidation'!$H$43:$H$102,'Data Consolidation'!$A$43:$A$102,"Home Rent Expense") | F41: =SUMIFS('Data Consolidation'!$F$43:$F$102,'Data Consolidation'!$A$43:$A$102,"Home Rent Expense") | G41: =I41 | I41: =15%*I13 | J41: =I41/$N$7
A42: Other | B42: =SUMIFS('Data Consolidation'!$D$43:$D$102,'Data Consolidation'!$A$43:$A$102,"Other") | C42: =SUMIFS('Data Consolidation'!$E$43:$E$102,'Data Consolidation'!$A$43:$A$102,"Other") | D42: =SUMIFS('Data Consolidation'!$G$43:$G$102,'Data Consolidation'!$A$43:$A$102,"Other") | E42: =SUMIFS('Data Consolidation'!$H$43:$H$102,'Data Consolidation'!$A$43:$A$102,"Other") | F42: =SUMIFS('Data Consolidation'!$F$43:$F$102,'Data Consolidation'!$A$43:$A$102,"Other") | G42: =I42 | H42: =I42 | I42: 0 | J42: =I42/$N$7
A43: Cap-Ex Reserve | B43: =SUMIFS('Data Consolidation'!$D$43:$D$102,'Data Consolidation'!$A$43:$A$102,"Cap Ex") | C43: =SUMIFS('Data Consolidation'!$E$43:$E$102,'Data Consolidation'!$A$43:$A$102,"Cap Ex") | D43: =SUMIFS('Data Consolidation'!$G$43:$G$102,'Data Consolidation'!$A$43:$A$102,"Cap Ex") | E43: =SUMIFS('Data Consolidation'!$H$43:$H$102,'Data Consolidation'!$A$43:$A$102,"Cap Ex") | F43: =SUMIFS('Data Consolidation'!$F$43:$F$102,'Data Consolidation'!$A$43:$A$102,"Cap Ex") | G43: =I43 | H43: =I43 | I43: =J43*$N$7 | J43: 75
A44: Total Expenses | B44: =B22+B23+B29+B30+B31+B32+B33+B35+B36+B37+B38+B39+B40+B42+B43+B41 | C44: =C22+C23+C29+C30+C31+C32+C33+C35+C36+C37+C38+C39+C40+C42+C43+C41 | D44: =D22+D23+D29+D30+D31+D32+D33+D35+D36+D37+D38+D39+D40+D42+D43+D41 | E44: =E22+E23+E29+E30+E31+E32+E33+E35+E36+E37+E38+E39+E40+E42+E43+E41 | F44: =F22+F23+F29+F30+F31+F32+F33+F35+F36+F37+F38+F39+F40+F42+F43+F41 | G44: =G22+G23+G29+G30+G31+G32+G33+G35+G36+G37+G38+G39+G40+G42+G43+G41 | H44: =H22+H23+H29+H30+H31+H32+H33+H35+H36+H37+H38+H39+H40+H42+H43+H41 | I44: =I22+I23+I29+I30+I31+I32+I33+I35+I36+I37+I38+I39+I40+I42+I43+I41 | J44: =I44/$N$7 | M44: per month
A45: Expense Ratio % | B45: =B44/B19 | C45: =C44/C19 | D45: =D44/D19 | E45: =E44/E19 | F45: =F44/F19 | G45: =G44/G19 | H45: =H44/H19 | I45: =I44/I19 | M45: per unit
A47: Total Net Operating Income | B47: =B19-B44 | C47: =C19-C44 | D47: =D19-D44 | E47: =E19-E44 | F47: =F19-F44 | G47: =G19-G44 | H47: =H19-H44 | I47: =I19-I44
A48: YoY % Growth | C48: =(C47-B47)/B47 | D48: =(D47-C47)/C47 | E48: =(E47-D47)/D47

Sheet GGC Pro Forma
A1: GARY GROUP CAPITAL | I1: First FY Year Post Capex Improvements
D2: Avg Monthly Lot Rent | F2: ='Unit Mix Summary'!C17 | H2: =H8/'Unit Mix Summary'!$E$12/12 | I2: =I8/'Unit Mix Summary'!$E$12/12 | J2: =J8/'Unit Mix Summary'!$E$12/12 | K2: =K8/'Unit Mix Summary'!$E$12/12 | L2: =L8/'Unit Mix Summary'!$E$12/12 | M2: =M8/'Unit Mix Summary'!$E$12/12 | N2: =N8/'Unit Mix Summary'!$E$12/12 | O2: =O8/'Unit Mix Summary'!$E$12/12 | ... Q2: =Q8/'Unit Mix Summary'!$E$12/12
D3: Monthly Lot $ Rent Change | H3: =+H2-F2 | I3: =+I2-H2 | J3: =+J2-I2 | K3: =+K2-J2 | L3: =+L2-K2 | M3: =+M2-L2 | N3: =+N2-M2 | O3: =+O2-N2 | P3: =+P2-O2 | Q3: =+Q2-P2
D4: Monthly Lot % Rent Change | H4: =+H$2/F$2-1 | I4: =+I$2/H$2-1 | J4: =+J$2/I$2-1 | K4: =+K$2/J$2-1 | L4: =+L$2/K$2-1 | M4: =+M$2/L$2-1 | N4: =+N$2/M$2-1 | O4: =+O$2/N$2-1 | P4: =+P$2/O$2-1 | Q4: =+Q$2/P$2-1
D6: T12 | E6: T3 Ann | F6: GGC UW | G6: UW Per Pad | H6: Year 1 | I6: Year 2 | J6: Year 3 | K6: Year 4 | L6: Year 5 | M6: Year 6 | N6: Year 7 | O6: Year 8 | P6: Year 9 | Q6: Year 10
C7: Income | S7: Key Assumptions | T7: Year 1 | U7: Year 2 | V7: Year 3 | W7: Year 4 | X7: Year 5 | Y7: Year 6 | Z7: Year 7 | AA7: Year 8 | AB7: Year 9 | AC7: Year 10
C8: Gross Potential Rent | D8: ='GGC Underwriting'!D4 | E8: ='GGC Underwriting'!E4 | F8: ='GGC Underwriting'!I4 | G8: =F8/'GGC Underwriting'!$N$7 | H8: ='Unit Mix Rent Growth'!F22 | I8: ='Unit Mix Rent Growth'!G22 | J8: ='Unit Mix Rent Growth'!H22 | K8: ='Unit Mix Rent Growth'!I22 | L8: ='Unit Mix Rent Growth'!J22 | M8: ='Unit Mix Rent Growth'!K22 | N8: ='Unit Mix Rent Growth'!L22 | O8: ='Unit Mix Rent Growth'!M22 | ... Q8: ='Unit Mix Rent Growth'!O22 | S8: Net Rental Growth | T8: see unit mix rent growth tab
C9: Less: Vacancy | D9: ='GGC Underwriting'!D5 | E9: ='GGC Underwriting'!E5 | F9: ='GGC Underwriting'!I5 | G9: =F9/'GGC Underwriting'!$N$7 | H9: =-H8*T9 | I9: =-I8*U9 | J9: =-J8*V9 | K9: =-K8*W9 | L9: =-L8*X9 | M9: =-M8*Y9 | N9: =-N8*Z9 | O9: =-O8*AA9 | ... Q9: =-Q8*AC9 | S9: Min. Residential Vacancy | T9: ='Unit Mix Rent Growth'!F25 | U9: ='Unit Mix Rent Growth'!G25 | V9: ='Unit Mix Rent Growth'!H25 | W9: ='Unit Mix Rent Growth'!I25 | X9: ='Unit Mix Rent Growth'!J25 | Y9: ='Unit Mix Rent Growth'!K25 | Z9: ='Unit Mix Rent Growth'!L25 | AA9: ='Unit Mix Rent Growth'!M25 | ... AC9: ='Unit Mix Rent Growth'!O25
C10: Less: Concessions | D10: ='GGC Underwriting'!D6 | E10: ='GGC Underwriting'!E6 | F10: ='GGC Underwriting'!I6 | G10: =F10/'GGC Underwriting'!$N$7 | H10: =F10+(F10*$T$14) | I10: =H10+(H10*$U$14) | J10: =I10+(I10*$V$14) | K10: =J10+(J10*$W$14) | L10: =K10+(K10*$X$14) | M10: =L10+(L10*$Y$14) | N10: =M10+(M10*$Z$14) | O10: =N10+(N10*$Z$14) | P10: =O10+(O10*$Z$14) | Q10: =P10+(P10*$Z$14) | S10: Other Income Growth | T10: 0.03 | U10: 0.03 | V10: 0.03 | W10: 0.03 | X10: 0.03 | Y10: 0.03 | Z10: 0.03 | AA10: 0.03 | AB10: 0.03 | AC10: 0.03
C11: Less: Bad Debt | D11: ='GGC Underwriting'!D7 | E11: ='GGC Underwriting'!E7 | F11: ='GGC Underwriting'!I7 | G11: =F11/'GGC Underwriting'!$N$7 | H11: =F11+(F11*$T$15) | I11: =H11+(H11*$U$15) | J11: =I11+(I11*$V$15) | K11: =J11+(J11*$W$15) | L11: =K11+(K11*$X$15) | M11: =L11+(L11*$Y$15) | N11: =M11+(M11*$Z$15) | O11: =N11+(N11*$Z$15) | P11: =O11+(O11*$Z$15) | Q11: =P11+(P11*$Z$15) | S11: Home Rent Growth | T11: see unit mix rent growth tab
C12: Net Rental Income | D12: =SUM(D8:D11) | E12: =SUM(E8:E11) | F12: =SUM(F8:F11) | G12: =F12/'GGC Underwriting'!$N$7 | H12: =SUM(H8:H11) | I12: =SUM(I8:I11) | J12: =SUM(J8:J11) | K12: =SUM(K8:K11) | L12: =SUM(L8:L11) | M12: =SUM(M8:M11) | N12: =SUM(N8:N11) | O12: =SUM(O8:O11) | ... Q12: =SUM(Q8:Q11) | S12: Lease to Own | T12: ='Unit Mix Rent Growth'!B74 | U12: ='Unit Mix Rent Growth'!C74 | V12: ='Unit Mix Rent Growth'!D74 | W12: ='Unit Mix Rent Growth'!E74 | X12: ='Unit Mix Rent Growth'!F74 | Y12: ='Unit Mix Rent Growth'!G74 | Z12: ='Unit Mix Rent Growth'!H74 | AA12: ='Unit Mix Rent Growth'!I74 | ... AC12: ='Unit Mix Rent Growth'!K74
C13: YoY % Growth | S13: Parking Vacancy | T13: 0.05 | U13: 0.05 | V13: 0.05 | W13: 0.05 | X13: 0.05 | Y13: 0.05 | Z13: 0.05 | AA13: 0.05 | AB13: 0.05 | AC13: 0.05
S14: Concessions | T14: 0 | U14: 0 | V14: 0 | W14: 0 | X14: 0 | Y14: 0 | Z14: 0 | AA14: 0 | AB14: 0 | AC14: 0
C15: Physical Vacancy % | D15: =-D9/D8 | E15: =-E9/E8 | F15: =F9/F8 | H15: =H9/H8 | I15: =I9/I8 | J15: =J9/J8 | K15: =K9/K8 | L15: =L9/L8 | M15: =M9/M8 | N15: =N9/N8 | O15: =O9/O8 | ... Q15: =Q9/Q8 | S15: Bad Debt | T15: 0 | U15: 0 | V15: 0 | W15: 0 | X15: 0 | Y15: 0 | Z15: 0 | AA15: 0 | AB15: 0 | AC15: 0
C16: Ecomomic Vacancy % | D16: =-(D9+D10+D11)/D8 | E16: =-(E9+E10+E11)/E8 | F16: =(F9+F10+F11)/F8 | H16: =(H9+H10+H11)/H8 | I16: =(I9+I10+I11)/I8 | J16: =(J9+J10+J11)/J8 | K16: =(K9+K10+K11)/K8 | L16: =(L9+L10+L11)/L8 | M16: =(M9+M10+M11)/M8 | N16: =(N9+N10+N11)/N8 | O16: =(O9+O10+O11)/O8 | ... Q16: =(Q9+Q10+Q11)/Q8 | S16: Expense Growth | T16: 0.03 | U16: 0.03 | V16: 0.03 | W16: 0.03 | X16: 0.03 | Y16: 0.03 | Z16: 0.03 | AA16: 0.03 | AB16: 0.03 | AC16: 0.03
S17: RE Tax Growth | T17: 0.03 | U17: 0.03 | V17: 0.03 | W17: 0.03 | X17: 0.03 | Y17: 0.03 | Z17: 0.03 | AA17: 0.03 | AB17: 0.03 | AC17: 0.03
S18: Management Fee | T18: 0.03 | U18: 0.03 | V18: 0.03 | W18: 0.03 | X18: 0.03 | Y18: 0.03 | Z18: 0.03 | AA18: 0.03 | AB18: 0.03 | AC18: 0.03
C19: Utility Reimbursement | D19: ='GGC Underwriting'!D12 | E19: ='GGC Underwriting'!E12 | F19: ='GGC Underwriting'!I12 | G19: =F19/'GGC Underwriting'!$N$7 | H19: =75%*H33 | I19: =75%*I33 | J19: =75%*J33 | K19: =75%*K33 | L19: =75%*L33 | M19: =75%*M33 | N19: =75%*N33 | O19: =75%*O33 | ... Q19: =75%*Q33
C20: Home Rent Income | D20: ='GGC Underwriting'!D13 | E20: ='GGC Underwriting'!E13 | F20: ='GGC Underwriting'!I13 | G20: =F20/'GGC Underwriting'!$N$7 | H20: ='Unit Mix Rent Growth'!F41 | I20: ='Unit Mix Rent Growth'!G41 | J20: ='Unit Mix Rent Growth'!H41 | K20: ='Unit Mix Rent Growth'!I41 | L20: ='Unit Mix Rent Growth'!J41 | M20: ='Unit Mix Rent Growth'!K41 | N20: ='Unit Mix Rent Growth'!L41 | O20: ='Unit Mix Rent Growth'!M41 | ... Q20: ='Unit Mix Rent Growth'!O41 | S20: Lot Rent Exit Cap Rate Assumption | X20: 0.065
C21: Long term RV Site | D21: ='GGC Underwriting'!D14 | E21: ='GGC Underwriting'!E14 | F21: ='GGC Underwriting'!I14 | G21: =F21/'GGC Underwriting'!$N$7 | H21: =(F21+(F21*T12)) | I21: =(H21+(H21*U12)) | J21: =(I21+(I21*V12)) | K21: =(J21+(J21*W12)) | L21: =(K21+(K21*X12)) | M21: =(L21+(L21*Y12)) | N21: =(M21+(M21*Z12)) | O21: =(N21+(N21*AD12)) | P21: =(O21+(O21*AE12)) | Q21: =(P21+(P21*AF12)) | S21: Home Rent Exit Cap Rate Assumption | X21: 0.14
C22: Storage Income | D22: ='GGC Underwriting'!D15 | E22: ='GGC Underwriting'!E15 | F22: ='GGC Underwriting'!I15 | G22: =F22/'GGC Underwriting'!$N$7 | H22: =F22+(F22*$T$10) | I22: =H22+(H22*$U$10) | J22: =I22+(I22*$V$10) | K22: =J22+(J22*$W$10) | L22: =K22+(K22*$X$10) | M22: =L22+(L22*$Y$10) | N22: =M22+(M22*$Z$10) | O22: =N22+(N22*$Z$10) | P22: =O22+(O22*$Z$10) | Q22: =P22+(P22*$Z$10)
C23: Laundry Income | D23: ='GGC Underwriting'!D16 | E23: ='GGC Underwriting'!E16 | F23: ='GGC Underwriting'!I16 | G23: =F23/'GGC Underwriting'!$N$7 | H23: =F23+(F23*$T$10) | I23: =H23+(H23*$U$10) | J23: =I23+(I23*$V$10) | K23: =J23+(J23*$W$10) | L23: =K23+(K23*$X$10) | M23: =L23+(L23*$Y$10) | N23: =M23+(M23*$Z$10) | O23: =N23+(N23*$Z$10) | P23: =O23+(O23*$Z$10) | Q23: =P23+(P23*$Z$10)
C24: Other Income | D24: ='GGC Underwriting'!D17 | E24: ='GGC Underwriting'!E17 | F24: ='GGC Underwriting'!I17 | G24: =F24/'GGC Underwriting'!$N$7 | H24: =F24+(F24*$T$10) | I24: =H24+(H24*$U$10) | J24: =I24+(I24*$V$10) | K24: =J24+(J24*$W$10) | L24: =K24+(K24*$X$10) | M24: =L24+(L24*$Y$10) | N24: =M24+(M24*$Z$10) | O24: =N24+(N24*$Z$10) | P24: =O24+(O24*$Z$10) | Q24: =P24+(P24*$Z$10)
C25: Total Effective Gross Income | D25: =D12+D19+D20+D21+D22+D23+D24 | E25: =E12+E19+E20+E21+E22+E23+E24 | F25: =F12+F19+F20+F21+F22+F23+F24 | G25: =F25/'GGC Underwriting'!$N$7 | H25: =H12+H19+H20+H21+H22+H23+H24 | I25: =I12+I19+I20+I21+I22+I23+I24 | J25: =J12+J19+J20+J21+J22+J23+J24 | K25: =K12+K19+K20+K21+K22+K23+K24 | L25: =L12+L19+L20+L21+L22+L23+L24 | M25: =M12+M19+M20+M21+M22+M23+M24 | N25: =N12+N19+N20+N21+N22+N23+N24 | O25: =O12+O19+O20+O21+O22+O23+O24 | ... Q25: =Q12+Q19+Q20+Q21+Q22+Q23+Q24
C26: YoY % Growth
C27: Expenses | G27: UW Per Pad | I27: RE Tax Reassessment
C28: RE Taxes | D28: ='GGC Underwriting'!D22 | E28: ='GGC Underwriting'!E22 | F28: ='GGC Underwriting'!I22 | G28: =F28/'GGC Underwriting'!$N$7 | H28: =D28 | I28: =F28 | J28: =I28+(I28*$V$17) | K28: =J28+(J28*$W$17) | L28: =K28+(K28*$X$17) | M28: =L28+(L28*$Y$17) | N28: =M28+(M28*$Z$17) | O28: =N28+(N28*$Z$17) | P28: =O28+(O28*$Z$17) | Q28: =P28+(P28*$Z$17)
C29: Insurance | D29: ='GGC Underwriting'!D23 | E29: ='GGC Underwriting'!E23 | F29: ='GGC Underwriting'!I23 | G29: =F29/'GGC Underwriting'!$N$7 | H29: =F29+(F29*$T$16) | I29: =H29+(H29*$U$16) | J29: =I29+(I29*$V$16) | K29: =J29+(J29*$W$16) | L29: =K29+(K29*$X$16) | M29: =L29+(L29*$Y$16) | N29: =M29+(M29*$Z$16) | O29: =N29+(N29*$Z$16) | P29: =O29+(O29*$Z$16) | Q29: =P29+(P29*$Z$16)
G30: =F30/'GGC Underwriting'!$N$7
C31: Gas/Fuel | D31: ='GGC Underwriting'!D25 | E31: ='GGC Underwriting'!E25 | F31: ='GGC Underwriting'!I25 | G31: =F31/'GGC Underwriting'!$N$7 | H31: =F31+(F31*$T$16) | I31: =H31+(H31*$U$16) | J31: =I31+(I31*$V$16) | K31: =J31+(J31*$W$16) | L31: =K31+(K31*$X$16) | M31: =L31+(L31*$Y$16) | N31: =M31+(M31*$Z$16) | O31: =N31+(N31*$Z$16) | P31: =O31+(O31*$Z$16) | Q31: =P31+(P31*$Z$16)
C32: Electrcitiy | D32: ='GGC Underwriting'!D26 | E32: ='GGC Underwriting'!E26 | F32: ='GGC Underwriting'!I26 | G32: =F32/'GGC Underwriting'!$N$7 | H32: =F32+(F32*$T$16) | I32: =H32+(H32*$U$16) | J32: =I32+(I32*$V$16) | K32: =J32+(J32*$W$16) | L32: =K32+(K32*$X$16) | M32: =L32+(L32*$Y$16) | N32: =M32+(M32*$Z$16) | O32: =N32+(N32*$Z$16) | P32: =O32+(O32*$Z$16) | Q32: =P32+(P32*$Z$16)
C33: Water and Sewer | D33: ='GGC Underwriting'!D27 | E33: ='GGC Underwriting'!E27 | F33: ='GGC Underwriting'!I27 | G33: =F33/'GGC Underwriting'!$N$7 | H33: =F33+(F33*$T$16) | I33: =H33+(H33*$U$16) | J33: =I33+(I33*$V$16) | K33: =J33+(J33*$W$16) | L33: =K33+(K33*$X$16) | M33: =L33+(L33*$Y$16) | N33: =M33+(M33*$Z$16) | O33: =N33+(N33*$Z$16) | P33: =O33+(O33*$Z$16) | Q33: =P33+(P33*$Z$16)
C34: Trash Removal | D34: ='GGC Underwriting'!D28 | E34: ='GGC Underwriting'!E28 | F34: ='GGC Underwriting'!I28 | G34: =F34/'GGC Underwriting'!$N$7 | H34: =F34+(F34*$T$16) | I34: =H34+(H34*$U$16) | J34: =I34+(I34*$V$16) | K34: =J34+(J34*$W$16) | L34: =K34+(K34*$X$16) | M34: =L34+(L34*$Y$16) | N34: =M34+(M34*$Z$16) | O34: =N34+(N34*$Z$16) | P34: =O34+(O34*$Z$16) | Q34: =P34+(P34*$Z$16)
C35: Total Utilities | D35: =D31+D32+D33+D34 | E35: =E31+E32+E33+E34 | F35: =F31+F32+F33+F34 | G35: =F35/'GGC Underwriting'!$N$7 | H35: =H31+H32+H33+H34 | I35: =I31+I32+I33+I34 | J35: =J31+J32+J33+J34 | K35: =K31+K32+K33+K34 | L35: =L31+L32+L33+L34 | M35: =M31+M32+M33+M34 | N35: =N31+N32+N33+N34 | O35: =O31+O32+O33+O34 | ... Q35: =Q31+Q32+Q33+Q34
C36: Repair and Maintenance | D36: ='GGC Underwriting'!D30 | E36: ='GGC Underwriting'!E30 | F36: ='GGC Underwriting'!I30 | G36: =F36/'GGC Underwriting'!$N$7 | H36: =F36+(F36*$T$16) | I36: =H36+(H36*$U$16) | J36: =I36+(I36*$V$16) | K36: =J36+(J36*$W$16) | L36: =K36+(K36*$X$16) | M36: =L36+(L36*$Y$16) | N36: =M36+(M36*$Z$16) | O36: =N36+(N36*$Z$16) | P36: =O36+(O36*$Z$16) | Q36: =P36+(P36*$Z$16)
C37: Ground Maintenance | D37: ='GGC Underwriting'!D31 | E37: ='GGC Underwriting'!E31 | F37: ='GGC Underwriting'!I31 | G37: =F37/'GGC Underwriting'!$N$7 | H37: =F37+(F37*$T$16) | I37: =H37+(H37*$U$16) | J37: =I37+(I37*$V$16) | K37: =J37+(J37*$W$16) | L37: =K37+(K37*$X$16) | M37: =L37+(L37*$Y$16) | N37: =M37+(M37*$Z$16) | O37: =N37+(N37*$Z$16) | P37: =O37+(O37*$Z$16) | Q37: =P37+(P37*$Z$16)
C38: Recreational Amenities | D38: ='GGC Underwriting'!D32 | E38: ='GGC Underwriting'!E32 | F38: ='GGC Underwriting'!I32 | G38: =F38/'GGC Underwriting'!$N$7 | H38: =F38+(F38*$T$16) | I38: =H38+(H38*$U$16) | J38: =I38+(I38*$V$16) | K38: =J38+(J38*$W$16) | L38: =K38+(K38*$X$16) | M38: =L38+(L38*$Y$16) | N38: =M38+(M38*$Z$16) | O38: =N38+(N38*$Z$16) | P38: =O38+(O38*$Z$16) | Q38: =P38+(P38*$Z$16)
C39: Management Fee | D39: ='GGC Underwriting'!D33 | E39: ='GGC Underwriting'!E33 | F39: ='GGC Underwriting'!I33 | G39: =F39/'GGC Underwriting'!$N$7 | H39: =H40*H25 | I39: =I40*I25 | J39: =J40*J25 | K39: =K40*K25 | L39: =L40*L25 | M39: =M40*M25 | N39: =N40*N25 | O39: =O40*O25 | ... Q39: =Q40*Q25
C40: Management Fee % | D40: =D39/D25 | E40: =E39/E25 | F40: =F39/F25 | G40: =G39/G25 | H40: =F40 | I40: =H40 | J40: =I40 | K40: =J40 | L40: =K40 | M40: =L40 | N40: =M40 | O40: =N40 | P40: =O40 | Q40: =P40
C41: Payroll | D41: ='GGC Underwriting'!D35 | E41: ='GGC Underwriting'!E35 | F41: ='GGC Underwriting'!I35 | G41: =F41/'GGC Underwriting'!$N$7 | H41: =F41+(F41*$T$16) | I41: =H41+(H41*$U$16) | J41: =I41+(I41*$V$16) | K41: =J41+(J41*$W$16) | L41: =K41+(K41*$X$16) | M41: =L41+(L41*$Y$16) | N41: =M41+(M41*$Z$16) | O41: =N41+(N41*$Z$16) | P41: =O41+(O41*$Z$16) | Q41: =P41+(P41*$Z$16)
C42: Employee Allowance | D42: ='GGC Underwriting'!D36 | E42: ='GGC Underwriting'!E36 | F42: ='GGC Underwriting'!I36 | G42: =F42/'GGC Underwriting'!$N$7 | H42: =F42+(F42*$T$16) | I42: =H42+(H42*$U$16) | J42: =I42+(I42*$V$16) | K42: =J42+(J42*$W$16) | L42: =K42+(K42*$X$16) | M42: =L42+(L42*$Y$16) | N42: =M42+(M42*$Z$16) | O42: =N42+(N42*$Z$16) | P42: =O42+(O42*$Z$16) | Q42: =P42+(P42*$Z$16)
C43: General and Administrative | D43: ='GGC Underwriting'!D37 | E43: ='GGC Underwriting'!E37 | F43: ='GGC Underwriting'!I37 | G43: =F43/'GGC Underwriting'!$N$7 | H43: =F43+(F43*$T$16) | I43: =H43+(H43*$U$16) | J43: =I43+(I43*$V$16) | K43: =J43+(J43*$W$16) | L43: =K43+(K43*$X$16) | M43: =L43+(L43*$Y$16) | N43: =M43+(M43*$Z$16) | O43: =N43+(N43*$Z$16) | P43: =O43+(O43*$Z$16) | Q43: =P43+(P43*$Z$16)
C44: Model Units | D44: ='GGC Underwriting'!D38 | E44: ='GGC Underwriting'!E38 | F44: ='GGC Underwriting'!I38 | G44: =F44/'GGC Underwriting'!$N$7 | H44: =F44+(F44*$T$16) | I44: =H44+(H44*$U$16) | J44: =I44+(I44*$V$16) | K44: =J44+(J44*$W$16) | L44: =K44+(K44*$X$16) | M44: =L44+(L44*$Y$16) | N44: =M44+(M44*$Z$16) | O44: =N44+(N44*$Z$16) | P44: =O44+(O44*$Z$16) | Q44: =P44+(P44*$Z$16)
C45: Professional Fees | D45: ='GGC Underwriting'!D39 | E45: ='GGC Underwriting'!E39 | F45: ='GGC Underwriting'!I39 | G45: =F45/'GGC Underwriting'!$N$7 | H45: =F45+(F45*$T$16) | I45: =H45+(H45*$U$16) | J45: =I45+(I45*$V$16) | K45: =J45+(J45*$W$16) | L45: =K45+(K45*$X$16) | M45: =L45+(L45*$Y$16) | N45: =M45+(M45*$Z$16) | O45: =N45+(N45*$Z$16) | P45: =O45+(O45*$Z$16) | Q45: =P45+(P45*$Z$16)
C46: Advertising | D46: ='GGC Underwriting'!D40 | E46: ='GGC Underwriting'!E40 | F46: ='GGC Underwriting'!I40 | G46: =F46/'GGC Underwriting'!$N$7 | H46: =F46+(F46*$T$16) | I46: =H46+(H46*$U$16) | J46: =I46+(I46*$V$16) | K46: =J46+(J46*$W$16) | L46: =K46+(K46*$X$16) | M46: =L46+(L46*$Y$16) | N46: =M46+(M46*$Z$16) | O46: =N46+(N46*$Z$16) | P46: =O46+(O46*$Z$16) | Q46: =P46+(P46*$Z$16)
B47: 0.15 | C47: Home Rent Expense | D47: ='GGC Underwriting'!D41 | E47: ='GGC Underwriting'!E41 | F47: ='GGC Underwriting'!I41 | G47: =F47/'GGC Underwriting'!$N$7 | H47: =$B$47*H20 | I47: =$B$47*SUM(I20:I21) | J47: =$B$47*SUM(J20:J21) | K47: =$B$47*SUM(K20:K21) | L47: =$B$47*SUM(L20:L21) | M47: =$B$47*SUM(M20:M21) | N47: =$B$47*SUM(N20:N21) | O47: =$B$47*SUM(O20:O21) | P47: =$B$47*SUM(P20:P21) | Q47: =$B$47*SUM(Q20:Q21)
C48: Other Expenses | D48: ='GGC Underwriting'!D42 | E48: ='GGC Underwriting'!E42 | F48: ='GGC Underwriting'!I42 | G48: =F48/'GGC Underwriting'!$N$7 | H48: =F48+(F48*$T$16) | I48: =H48+(H48*$U$16) | J48: =I48+(I48*$V$16) | K48: =J48+(J48*$W$16) | L48: =K48+(K48*$X$16) | M48: =L48+(L48*$Y$16) | N48: =M48+(M48*$Z$16) | O48: =N48+(N48*$Z$16) | P48: =O48+(O48*$Z$16) | Q48: =P48+(P48*$Z$16)
C49: Cap-Ex Reserve | D49: ='GGC Underwriting'!D43 | E49: ='GGC Underwriting'!E43 | F49: ='GGC Underwriting'!I43 | G49: =F49/'GGC Underwriting'!$N$7 | H49: =F49+(F49*$T$16) | I49: =H49+(H49*$U$16) | J49: =I49+(I49*$V$16) | K49: =J49+(J49*$W$16) | L49: =K49+(K49*$X$16) | M49: =L49+(L49*$Y$16) | N49: =M49+(M49*$Z$16) | O49: =N49+(N49*$Z$16) | P49: =O49+(O49*$Z$16) | Q49: =P49+(P49*$Z$16)
C50: Total Expenses | D50: =D28+D29+D35+D36+D37+D38+D39+D41+D42+D43+D44+D45+D46+D47+D48+D49 | E50: =E28+E29+E35+E36+E37+E38+E39+E41+E42+E43+E44+E45+E46+E47+E48+E49 | F50: =F28+F29+F35+F36+F37+F38+F39+F41+F42+F43+F44+F45+F46+F47+F48+F49 | G50: =F50/'GGC Underwriting'!$N$7 | H50: =H28+H29+H35+H36+H37+H38+H39+H41+H42+H43+H44+H45+H46+H47+H48+H49 | I50: =I28+I29+I35+I36+I37+I38+I39+I41+I42+I43+I44+I45+I46+I47+I48+I49 | J50: =J28+J29+J35+J36+J37+J38+J39+J41+J42+J43+J44+J45+J46+J47+J48+J49 | K50: =K28+K29+K35+K36+K37+K38+K39+K41+K42+K43+K44+K45+K46+K47+K48+K49 | L50: =L28+L29+L35+L36+L37+L38+L39+L41+L42+L43+L44+L45+L46+L47+L48+L49 | M50: =M28+M29+M35+M36+M37+M38+M39+M41+M42+M43+M44+M45+M46+M47+M48+M49 | N50: =N28+N29+N35+N36+N37+N38+N39+N41+N42+N43+N44+N45+N46+N47+N48+N49 | O50: =O28+O29+O35+O36+O37+O38+O39+O41+O42+O43+O44+O45+O46+O47+O48+O49 | ... Q50: =Q28+Q29+Q35+Q36+Q37+Q38+Q39+Q41+Q42+Q43+Q44+Q45+Q46+Q47+Q48+Q49
C51: Expense Ratio % | D51: =D50/D$25 | E51: =E50/E25 | F51: =F50/F25 | G51: =G50/G25 | H51: =H50/H25 | I51: =I50/I25 | J51: =J50/J25 | K51: =K50/K25 | L51: =L50/L25 | ... Q51: =Q50/Q25
C53: Total Net Operating Income | D53: =D25-D50 | E53: =E25-E50 | F53: =F25-F50 | G53: =F53/'GGC Underwriting'!$N$7 | H53: =H25-H50 | I53: =I25-I50 | J53: =J25-J50 | K53: =K25-K50 | L53: =L25-L50 | M53: =M25-M50 | N53: =N25-N50 | O53: =O25-O50 | ... Q53: =Q25-Q50
C54: NOI Margin | D54: =D53/D$25 | E54: =E53/E$25 | F54: =F53/F$25 | G54: =G53/G$25 | H54: =H53/H$25 | I54: =I53/I$25 | J54: =J53/J$25 | K54: =K53/K$25 | ... Q54: =Q53/Q$25
C56: Lot Rent NOI Only | H56: =H53-H57 | I56: =I53-I57 | J56: =J53-J57 | K56: =K53-K57 | L56: =L53-L57 | M56: =M53-M57 | N56: =N53-N57 | O56: =O53-O57 | ... Q56: =Q53-Q57
C57: Home Rent NOI | H57: =(H20+H21)-H47 | I57: =(I20+I21)-I47 | J57: =(J20+J21)-J47 | K57: =(K20+K21)-K47 | L57: =(L20+L21)-L47 | M57: =(M20+M21)-M47 | N57: =(N20+N21)-N47 | O57: =(O20+O21)-O47 | ... Q57: =(Q20+Q21)-Q47
E58: Exit Summaries
E60: 10 YEAR | F60: Debt Service | H60: =-'Loan Scenario (acquisition)'!M10 | I60: =-'Loan Scenario (acquisition)'!N10 | J60: =-'Loan Scenario (acquisition)'!O10 | K60: =-'Loan Scenario (acquisition)'!P10 | L60: =-'Loan Scenario (acquisition)'!Q10 | M60: =-'Loan Scenario (acquisition)'!R10 | N60: =-'Loan Scenario (acquisition)'!S10 | O60: =-'Loan Scenario (acquisition)'!T10 | ... Q60: =-'Loan Scenario (acquisition)'!V10
F61: Debt Payoff | Q61: =-'Loan Scenario (acquisition)'!J126
F62: Refi Cashout
F63: New Loan | R63: Lot Rent NOI Exit | S63: =$X$20
F64: Total Sale - Community | Q64: =(Q56/S63)+(Q57/S64) | R64: Home Rent NOI Exit | S64: =$X$21
F65: Free Cash Flow | G65: =-'Sources and Uses'!$C$7-'Sources and Uses'!$C$8 | H65: =H53+SUM(H60:H64) | I65: =I53+SUM(I60:I64) | J65: =J53+SUM(J60:J64) | K65: =K53+SUM(K60:K64) | L65: =L53+SUM(L60:L64) | M65: =M53+SUM(M60:M64) | N65: =N53+SUM(N60:N64) | O65: =O53+SUM(O60:O64) | ... Q65: =Q53+SUM(Q60:Q64)
F66: DSCR | H66: =-H$53/H$60 | I66: =-I53/I60 | J66: =-J53/I60 | K66: =-K53/K60 | L66: =-L53/L60 | M66: =-M53/M60 | N66: =-N53/N60 | O66: =-O53/O60 | P66: =-P53/P60 | Q66: =-Q53/Q60
E68: 7 Year | F68: Debt Service | H68: -655388.04 | I68: -773882.18 | J68: -773882.18 | K68: -774628.21 | L68: -773882.18 | M68: -773882.18 | N68: -773882.18
F69: Debt Payoff | N69: -9833889.3
F70: Refi Cashout
F71: New Loan
F72: total Sale - Community | N72: =N53/X20 | R72: Lot Rent Exit cap rate: | S72: =+$X$20
F73: Free Cash Flow | H73: =H53+SUM(H68:H72) | I73: =I53+SUM(I68:I72) | J73: =J53+SUM(J68:J72) | K73: =K53+SUM(K68:K72) | L73: =L53+SUM(L68:L72) | M73: =M53+SUM(M68:M72) | N73: =N53+SUM(N68:N72)
F74: DSCR | H74: =-H$53/H$68 | I74: =-I$53/I$68 | J74: =-J$53/J$68 | K74: =-K$53/K$68 | L74: =-L$53/L$68 | M74: =-M$53/M$68 | N74: =-N$53/N$68
E79: 5 YEAR | F79: Debt Service | H79: =-'Loan Scenario (acquisition)'!M10 | I79: =-'Loan Scenario (acquisition)'!N10 | J79: =-'Loan Scenario (acquisition)'!O10 | K79: =-'Loan Scenario (acquisition)'!P10 | L79: =-'Loan Scenario (acquisition)'!Q10
F80: Debt Payoff | L80: =-'Loan Scenario (acquisition)'!J66
F81: Refi Cashout
F82: New Loan | M82: Lot Rent NOI Exit | N82: =$X$20
F83: Total Sale - Community | L83: =(L56/N82)+(L57/N83) | M83: Home Rent NOI Exit | N83: =$X$21
F84: Free Cash Flow | G84: =-'Sources and Uses'!$C$7-'Sources and Uses'!$C$8 | H84: =H53+SUM(H79:H83) | I84: =I53+SUM(I79:I83) | J84: =J53+SUM(J79:J83) | K84: =K53+SUM(K79:K83) | L84: =L53+SUM(L79:L83)
F85: DSCR | H85: =-H53/H79 | I85: =-I53/I79 | J85: =-J53/J79 | K85: =-K53/K79 | L85: =-L53/L79
D90: S2-Secondary seller note
E91: 10 YEAR | F91: Debt Service | H91: =-'Loan Scenario (acquisition)'!M10 | I91: =-'Loan Scenario (acquisition)'!N10 | J91: =-'Loan Scenario (acquisition)'!O10 | K91: =-'Loan Scenario (acquisition)'!P10 | L91: =-'Loan Scenario (acquisition)'!Q10 | M91: =-6.75%*$L$94 | N91: =-6.75%*$L$94 | O91: =-6.75%*$L$94 | P91: =-6.75%*$L$94 | Q91: =-6.75%*$L$94
F92: Debt Payoff | L92: =-'Loan Scenario (acquisition)'!J66-'Sources and Uses'!$I$6 | Q92: =-L94
F93: Seller note | H93: =-5%*'Sources and Uses'!$I$6 | I93: =-5%*'Sources and Uses'!$I$6 | J93: =-5%*'Sources and Uses'!$I$6 | K93: =-5%*'Sources and Uses'!$I$6 | L93: =-5%*'Sources and Uses'!$I$6
F94: Refi Cashout | L94: =L56/7%/1.25
F95: New Loan | R95: Lot Rent NOI Exit | S95: =$X$20
F96: Total Sale - Community | Q96: =(Q56/S95)+(Q57/S96) | R96: Home Rent NOI Exit | S96: =$X$21
F97: Free Cash Flow | G97: =-'Sources and Uses'!I7-'Sources and Uses'!I8 | H97: =H53+SUM(H91:H96) | I97: =I53+SUM(I91:I96) | J97: =J53+SUM(J91:J96) | K97: =K53+SUM(K91:K96) | L97: =L53+SUM(L91:L96) | M97: =M53+SUM(M91:M96) | N97: =N53+SUM(N91:N96) | O97: =O53+SUM(O91:O96) | ... Q97: =Q53+SUM(Q91:Q96)
F98: DSCR | H98: =-H53/(H91+H93) | I98: =-I53/(I91+I93) | J98: =-J53/(J91+J93) | K98: =-K53/(K91+K93) | L98: =-L53/(L91+L93) | M98: =-M53/(M91+M93) | N98: =-N53/(N91+N93) | O98: =-O53/(O91+O93) | ... Q98: =-Q53/(Q91+Q93)
F99: Coc Return | H99: =H97/-$G$97 | I99: =I97/-$G$97 | J99: =J97/-$G$97 | K99: =K97/-$G$97 | L99: =L97/-$G$97 | M99: =M97/-$G$97 | N99: =N97/-$G$97 | O99: =O97/-$G$97 | ... Q99: =Q97/-$G$97
F100: Avg cOC Y1-Y4 | G100: =AVERAGE(H99:K99)
F101: IRR | G101: =IRR(G97:Q97)
F102: MOIC | G102: =SUM(H97:Q97)/-G97

Sheet GGC Pro Forma (Conversion)
A1: GARY GROUP CAPITAL | I1: First FY Year Post Capex Improvements
D2: Avg Monthly Lot Rent | F2: ='Unit Mix Summary'!C17 | H2: =H8/'Unit Mix Summary'!$E$12/12 | I2: =I8/'Unit Mix Summary'!$E$12/12 | J2: =J8/'Unit Mix Summary'!$E$12/12 | K2: =K8/'Unit Mix Summary'!$E$12/12 | L2: =L8/'Unit Mix Summary'!$E$12/12 | M2: =M8/'Unit Mix Summary'!$E$12/12 | N2: =N8/'Unit Mix Summary'!$E$12/12 | O2: =O8/'Unit Mix Summary'!$E$12/12 | ... Q2: =Q8/'Unit Mix Summary'!$E$12/12
D3: Monthly Lot $ Rent Change | H3: =+H2-F2 | I3: =+I2-H2 | J3: =+J2-I2 | K3: =+K2-J2 | L3: =+L2-K2 | M3: =+M2-L2 | N3: =+N2-M2 | O3: =+O2-N2 | P3: =+P2-O2 | Q3: =+Q2-P2
D4: Monthly Lot % Rent Change | H4: =+H$2/F$2-1 | I4: =+I$2/H$2-1 | J4: =+J$2/I$2-1 | K4: =+K$2/J$2-1 | L4: =+L$2/K$2-1 | M4: =+M$2/L$2-1 | N4: =+N$2/M$2-1 | O4: =+O$2/N$2-1 | P4: =+P$2/O$2-1 | Q4: =+Q$2/P$2-1
D6: T12 | E6: T3 Ann | F6: GGC UW | G6: UW Per Pad | H6: Year 1 | I6: Year 2 | J6: Year 3 | K6: Year 4 | L6: Year 5 | M6: Year 6 | N6: Year 7 | O6: Year 8 | P6: Year 9 | Q6: Year 10
C7: Income | S7: Key Assumptions | T7: Year 1 | U7: Year 2 | V7: Year 3 | W7: Year 4 | X7: Year 5 | Y7: Year 6 | Z7: Year 7 | AA7: Year 8 | AB7: Year 9 | AC7: Year 10
C8: Gross Potential Rent | D8: ='GGC Underwriting'!D4 | E8: ='GGC Underwriting'!E4 | F8: ='GGC Underwriting'!I4 | G8: =F8/'GGC Underwriting'!$N$7 | H8: ='Unit Mix Rent Growth'!F22 | I8: ='Unit Mix Rent Growth'!G22 | J8: ='Unit Mix Rent Growth'!H22 | K8: ='Unit Mix Rent Growth'!I22 | L8: ='Unit Mix Rent Growth'!J22 | M8: ='Unit Mix Rent Growth'!K22 | N8: ='Unit Mix Rent Growth'!L22 | O8: ='Unit Mix Rent Growth'!M22 | ... Q8: ='Unit Mix Rent Growth'!O22 | S8: Net Rental Growth | T8: see unit mix rent growth tab
C9: Less: Vacancy | D9: ='GGC Underwriting'!D5 | E9: ='GGC Underwriting'!E5 | F9: ='GGC Underwriting'!I5 | G9: =F9/'GGC Underwriting'!$N$7 | H9: =-H8*T9 | I9: =-I8*U9 | J9: =-J8*V9 | K9: =-K8*W9 | L9: =-L8*X9 | M9: =-M8*Y9 | N9: =-N8*Z9 | O9: =-O8*AA9 | ... Q9: =-Q8*AC9 | S9: Min. Residential Vacancy | T9: ='Unit Mix Rent Growth'!F60 | U9: ='Unit Mix Rent Growth'!G60 | V9: ='Unit Mix Rent Growth'!H60 | W9: ='Unit Mix Rent Growth'!I60 | X9: ='Unit Mix Rent Growth'!J60 | Y9: ='Unit Mix Rent Growth'!K60 | Z9: ='Unit Mix Rent Growth'!L60 | AA9: ='Unit Mix Rent Growth'!M60 | ... AC9: ='Unit Mix Rent Growth'!O60
C10: Less: Concessions | D10: ='GGC Underwriting'!D6 | E10: ='GGC Underwriting'!E6 | F10: ='GGC Underwriting'!I6 | G10: =F10/'GGC Underwriting'!$N$7 | H10: =F10+(F10*$T$14) | I10: =H10+(H10*$U$14) | J10: =I10+(I10*$V$14) | K10: =J10+(J10*$W$14) | L10: =K10+(K10*$X$14) | M10: =L10+(L10*$Y$14) | N10: =M10+(M10*$Z$14) | O10: =N10+(N10*$Z$14) | P10: =O10+(O10*$Z$14) | Q10: =P10+(P10*$Z$14) | S10: Other Income Growth | T10: 0.03 | U10: 0.03 | V10: 0.03 | W10: 0.03 | X10: 0.03 | Y10: 0.03 | Z10: 0.03 | AA10: 0.03 | AB10: 0.03 | AC10: 0.03
C11: Less: Bad Debt | D11: ='GGC Underwriting'!D7 | E11: ='GGC Underwriting'!E7 | F11: ='GGC Underwriting'!I7 | G11: =F11/'GGC Underwriting'!$N$7 | H11: =F11+(F11*$T$15) | I11: =H11+(H11*$U$15) | J11: =I11+(I11*$V$15) | K11: =J11+(J11*$W$15) | L11: =K11+(K11*$X$15) | M11: =L11+(L11*$Y$15) | N11: =M11+(M11*$Z$15) | O11: =N11+(N11*$Z$15) | P11: =O11+(O11*$Z$15) | Q11: =P11+(P11*$Z$15) | S11: Home Rent Growth | T11: see unit mix rent growth tab
C12: Net Rental Income | D12: =SUM(D8:D11) | E12: =SUM(E8:E11) | F12: =SUM(F8:F11) | G12: =F12/'GGC Underwriting'!$N$7 | H12: =SUM(H8:H11) | I12: =SUM(I8:I11) | J12: =SUM(J8:J11) | K12: =SUM(K8:K11) | L12: =SUM(L8:L11) | M12: =SUM(M8:M11) | N12: =SUM(N8:N11) | O12: =SUM(O8:O11) | ... Q12: =SUM(Q8:Q11) | S12: Lease to Own | T12: ='Unit Mix Rent Growth'!B74 | U12: ='Unit Mix Rent Growth'!C74 | V12: ='Unit Mix Rent Growth'!D74 | W12: ='Unit Mix Rent Growth'!E74 | X12: ='Unit Mix Rent Growth'!F74 | Y12: ='Unit Mix Rent Growth'!G74 | Z12: ='Unit Mix Rent Growth'!H74 | AA12: ='Unit Mix Rent Growth'!I74 | ... AC12: ='Unit Mix Rent Growth'!K74
C13: YoY % Growth | S13: Parking Vacancy | T13: 0.05 | U13: 0.05 | V13: 0.05 | W13: 0.05 | X13: 0.05 | Y13: 0.05 | Z13: 0.05 | AA13: 0.05 | AB13: 0.05 | AC13: 0.05
S14: Concessions | T14: 0 | U14: 0 | V14: 0 | W14: 0 | X14: 0 | Y14: 0 | Z14: 0 | AA14: 0 | AB14: 0 | AC14: 0
C15: Physical Vacancy % | D15: =-D9/D8 | E15: =-E9/E8 | F15: =F9/F8 | H15: =H9/H8 | I15: =I9/I8 | J15: =J9/J8 | K15: =K9/K8 | L15: =L9/L8 | M15: =M9/M8 | N15: =N9/N8 | O15: =O9/O8 | ... Q15: =Q9/Q8 | S15: Bad Debt | T15: 0 | U15: 0 | V15: 0 | W15: 0 | X15: 0 | Y15: 0 | Z15: 0 | AA15: 0 | AB15: 0 | AC15: 0
C16: Ecomomic Vacancy % | D16: =-(D9+D10+D11)/D8 | E16: =-(E9+E10+E11)/E8 | F16: =(F9+F10+F11)/F8 | H16: =(H9+H10+H11)/H8 | I16: =(I9+I10+I11)/I8 | J16: =(J9+J10+J11)/J8 | K16: =(K9+K10+K11)/K8 | L16: =(L9+L10+L11)/L8 | M16: =(M9+M10+M11)/M8 | N16: =(N9+N10+N11)/N8 | O16: =(O9+O10+O11)/O8 | ... Q16: =(Q9+Q10+Q11)/Q8 | S16: Expense Growth | T16: 0.03 | U16: 0.03 | V16: 0.03 | W16: 0.03 | X16: 0.03 | Y16: 0.03 | Z16: 0.03 | AA16: 0.03 | AB16: 0.03 | AC16: 0.03
S17: RE Tax Growth | T17: 0.03 | U17: 0.03 | V17: 0.03 | W17: 0.03 | X17: 0.03 | Y17: 0.03 | Z17: 0.03 | AA17: 0.03 | AB17: 0.03 | AC17: 0.03
S18: Management Fee | T18: 0.03 | U18: 0.03 | V18: 0.03 | W18: 0.03 | X18: 0.03 | Y18: 0.03 | Z18: 0.03 | AA18: 0.03 | AB18: 0.03 | AC18: 0.03
C19: Utility Reimbursement | D19: ='GGC Underwriting'!D12 | E19: ='GGC Underwriting'!E12 | F19: ='GGC Underwriting'!I12 | G19: =F19/'GGC Underwriting'!$N$7 | H19: =75%*H33 | I19: =75%*I33 | J19: =75%*J33 | K19: =75%*K33 | L19: =75%*L33 | M19: =75%*M33 | N19: =75%*N33 | O19: =75%*O33 | ... Q19: =75%*Q33
C20: Home Rent Income | D20: ='GGC Underwriting'!D13 | E20: ='GGC Underwriting'!E13 | F20: ='GGC Underwriting'!I13 | G20: =F20/'GGC Underwriting'!$N$7 | H20: ='Unit Mix Rent Growth'!F53 | I20: ='Unit Mix Rent Growth'!G53 | J20: ='Unit Mix Rent Growth'!H53 | K20: ='Unit Mix Rent Growth'!I53 | L20: ='Unit Mix Rent Growth'!J53 | M20: ='Unit Mix Rent Growth'!K53 | N20: ='Unit Mix Rent Growth'!L53 | O20: ='Unit Mix Rent Growth'!M53 | ... Q20: ='Unit Mix Rent Growth'!O53 | S20: Lot Rent Exit Cap Rate Assumption | X20: 0
C21: Lease to Own | D21: ='GGC Underwriting'!D14 | E21: ='GGC Underwriting'!E14 | F21: ='GGC Underwriting'!I14 | G21: =F21/'GGC Underwriting'!$N$7 | H21: =(F21+(F21*T12)) | I21: =(H21+(H21*U12)) | J21: =(I21+(I21*V12)) | K21: =(J21+(J21*W12)) | L21: =(K21+(K21*X12)) | M21: =(L21+(L21*Y12)) | N21: =(M21+(M21*Z12)) | O21: =(N21+(N21*AD12)) | P21: =(O21+(O21*AE12)) | Q21: =(P21+(P21*AF12)) | S21: Home Rent Exit Cap Rate Assumption | X21: 0
C22: Storage Income | D22: ='GGC Underwriting'!D15 | E22: ='GGC Underwriting'!E15 | F22: ='GGC Underwriting'!I15 | G22: =F22/'GGC Underwriting'!$N$7 | H22: =F22+(F22*$T$10) | I22: =H22+(H22*$U$10) | J22: =I22+(I22*$V$10) | K22: =J22+(J22*$W$10) | L22: =K22+(K22*$X$10) | M22: =L22+(L22*$Y$10) | N22: =M22+(M22*$Z$10) | O22: =N22+(N22*$Z$10) | P22: =O22+(O22*$Z$10) | Q22: =P22+(P22*$Z$10)
C23: Laundry Income | D23: ='GGC Underwriting'!D16 | E23: ='GGC Underwriting'!E16 | F23: ='GGC Underwriting'!I16 | G23: =F23/'GGC Underwriting'!$N$7 | H23: =F23+(F23*$T$10) | I23: =H23+(H23*$U$10) | J23: =I23+(I23*$V$10) | K23: =J23+(J23*$W$10) | L23: =K23+(K23*$X$10) | M23: =L23+(L23*$Y$10) | N23: =M23+(M23*$Z$10) | O23: =N23+(N23*$Z$10) | P23: =O23+(O23*$Z$10) | Q23: =P23+(P23*$Z$10)
C24: Other Income | D24: ='GGC Underwriting'!D17 | E24: ='GGC Underwriting'!E17 | F24: ='GGC Underwriting'!I17 | G24: =F24/'GGC Underwriting'!$N$7 | H24: =F24+(F24*$T$10) | I24: =H24+(H24*$U$10) | J24: =I24+(I24*$V$10) | K24: =J24+(J24*$W$10) | L24: =K24+(K24*$X$10) | M24: =L24+(L24*$Y$10) | N24: =M24+(M24*$Z$10) | O24: =N24+(N24*$Z$10) | P24: =O24+(O24*$Z$10) | Q24: =P24+(P24*$Z$10)
C25: Total Effective Gross Income | D25: =D12+D19+D20+D21+D22+D23+D24 | E25: =E12+E19+E20+E21+E22+E23+E24 | F25: =F12+F19+F20+F21+F22+F23+F24 | G25: =F25/'GGC Underwriting'!$N$7 | H25: =H12+H19+H20+H21+H22+H23+H24 | I25: =I12+I19+I20+I21+I22+I23+I24 | J25: =J12+J19+J20+J21+J22+J23+J24 | K25: =K12+K19+K20+K21+K22+K23+K24 | L25: =L12+L19+L20+L21+L22+L23+L24 | M25: =M12+M19+M20+M21+M22+M23+M24 | N25: =N12+N19+N20+N21+N22+N23+N24 | O25: =O12+O19+O20+O21+O22+O23+O24 | ... Q25: =Q12+Q19+Q20+Q21+Q22+Q23+Q24
C26: YoY % Growth
C27: Expenses | G27: UW Per Pad | I27: RE Tax Reassessment
C28: RE Taxes | D28: ='GGC Underwriting'!D22 | E28: ='GGC Underwriting'!E22 | F28: ='GGC Underwriting'!I22 | G28: =F28/'GGC Underwriting'!$N$7 | H28: =D28 | I28: =F28 | J28: =I28+(I28*$V$17) | K28: =J28+(J28*$W$17) | L28: =K28+(K28*$X$17) | M28: =L28+(L28*$Y$17) | N28: =M28+(M28*$Z$17) | O28: =N28+(N28*$Z$17) | P28: =O28+(O28*$Z$17) | Q28: =P28+(P28*$Z$17)
C29: Insurance | D29: ='GGC Underwriting'!D23 | E29: ='GGC Underwriting'!E23 | F29: ='GGC Underwriting'!I23 | G29: =F29/'GGC Underwriting'!$N$7 | H29: =F29+(F29*$T$16) | I29: =H29+(H29*$U$16) | J29: =I29+(I29*$V$16) | K29: =J29+(J29*$W$16) | L29: =K29+(K29*$X$16) | M29: =L29+(L29*$Y$16) | N29: =M29+(M29*$Z$16) | O29: =N29+(N29*$Z$16) | P29: =O29+(O29*$Z$16) | Q29: =P29+(P29*$Z$16)
G30: =F30/'GGC Underwriting'!$N$7
C31: Gas/Fuel | D31: ='GGC Underwriting'!D25 | E31: ='GGC Underwriting'!E25 | F31: ='GGC Underwriting'!I25 | G31: =F31/'GGC Underwriting'!$N$7 | H31: =F31+(F31*$T$16) | I31: =H31+(H31*$U$16) | J31: =I31+(I31*$V$16) | K31: =J31+(J31*$W$16) | L31: =K31+(K31*$X$16) | M31: =L31+(L31*$Y$16) | N31: =M31+(M31*$Z$16) | O31: =N31+(N31*$Z$16) | P31: =O31+(O31*$Z$16) | Q31: =P31+(P31*$Z$16)
C32: Electrcitiy | D32: ='GGC Underwriting'!D26 | E32: ='GGC Underwriting'!E26 | F32: ='GGC Underwriting'!I26 | G32: =F32/'GGC Underwriting'!$N$7 | H32: =F32+(F32*$T$16) | I32: =H32+(H32*$U$16) | J32: =I32+(I32*$V$16) | K32: =J32+(J32*$W$16) | L32: =K32+(K32*$X$16) | M32: =L32+(L32*$Y$16) | N32: =M32+(M32*$Z$16) | O32: =N32+(N32*$Z$16) | P32: =O32+(O32*$Z$16) | Q32: =P32+(P32*$Z$16)
C33: Water and Sewer | D33: ='GGC Underwriting'!D27 | E33: ='GGC Underwriting'!E27 | F33: ='GGC Underwriting'!I27 | G33: =F33/'GGC Underwriting'!$N$7 | H33: =F33+(F33*$T$16) | I33: =H33+(H33*$U$16) | J33: =I33+(I33*$V$16) | K33: =J33+(J33*$W$16) | L33: =K33+(K33*$X$16) | M33: =L33+(L33*$Y$16) | N33: =M33+(M33*$Z$16) | O33: =N33+(N33*$Z$16) | P33: =O33+(O33*$Z$16) | Q33: =P33+(P33*$Z$16)
C34: Trash Removal | D34: ='GGC Underwriting'!D28 | E34: ='GGC Underwriting'!E28 | F34: ='GGC Underwriting'!I28 | G34: =F34/'GGC Underwriting'!$N$7 | H34: =F34+(F34*$T$16) | I34: =H34+(H34*$U$16) | J34: =I34+(I34*$V$16) | K34: =J34+(J34*$W$16) | L34: =K34+(K34*$X$16) | M34: =L34+(L34*$Y$16) | N34: =M34+(M34*$Z$16) | O34: =N34+(N34*$Z$16) | P34: =O34+(O34*$Z$16) | Q34: =P34+(P34*$Z$16)
C35: Total Utilities | D35: =D31+D32+D33+D34 | E35: =E31+E32+E33+E34 | F35: =F31+F32+F33+F34 | G35: =F35/'GGC Underwriting'!$N$7 | H35: =H31+H32+H33+H34 | I35: =I31+I32+I33+I34 | J35: =J31+J32+J33+J34 | K35: =K31+K32+K33+K34 | L35: =L31+L32+L33+L34 | M35: =M31+M32+M33+M34 | N35: =N31+N32+N33+N34 | O35: =O31+O32+O33+O34 | ... Q35: =Q31+Q32+Q33+Q34
C36: Repair and Maintenance | D36: ='GGC Underwriting'!D30 | E36: ='GGC Underwriting'!E30 | F36: ='GGC Underwriting'!I30 | G36: =F36/'GGC Underwriting'!$N$7 | H36: =F36+(F36*$T$16) | I36: =H36+(H36*$U$16) | J36: =I36+(I36*$V$16) | K36: =J36+(J36*$W$16) | L36: =K36+(K36*$X$16) | M36: =L36+(L36*$Y$16) | N36: =M36+(M36*$Z$16) | O36: =N36+(N36*$Z$16) | P36: =O36+(O36*$Z$16) | Q36: =P36+(P36*$Z$16)
C37: Ground Maintenance | D37: ='GGC Underwriting'!D31 | E37: ='GGC Underwriting'!E31 | F37: ='GGC Underwriting'!I31 | G37: =F37/'GGC Underwriting'!$N$7 | H37: =F37+(F37*$T$16) | I37: =H37+(H37*$U$16) | J37: =I37+(I37*$V$16) | K37: =J37+(J37*$W$16) | L37: =K37+(K37*$X$16) | M37: =L37+(L37*$Y$16) | N37: =M37+(M37*$Z$16) | O37: =N37+(N37*$Z$16) | P37: =O37+(O37*$Z$16) | Q37: =P37+(P37*$Z$16)
C38: Recreational Amenities | D38: ='GGC Underwriting'!D32 | E38: ='GGC Underwriting'!E32 | F38: ='GGC Underwriting'!I32 | G38: =F38/'GGC Underwriting'!$N$7 | H38: =F38+(F38*$T$16) | I38: =H38+(H38*$U$16) | J38: =I38+(I38*$V$16) | K38: =J38+(J38*$W$16) | L38: =K38+(K38*$X$16) | M38: =L38+(L38*$Y$16) | N38: =M38+(M38*$Z$16) | O38: =N38+(N38*$Z$16) | P38: =O38+(O38*$Z$16) | Q38: =P38+(P38*$Z$16)
C39: Management Fee | D39: ='GGC Underwriting'!D33 | E39: ='GGC Underwriting'!E33 | F39: ='GGC Underwriting'!I33 | G39: =F39/'GGC Underwriting'!$N$7 | H39: =H40*H25 | I39: =I40*I25 | J39: =J40*J25 | K39: =K40*K25 | L39: =L40*L25 | M39: =M40*M25 | N39: =N40*N25 | O39: =O40*O25 | ... Q39: =Q40*Q25
C40: Management Fee % | D40: =D39/D25 | E40: =E39/E25 | F40: =F39/F25 | G40: =G39/G25 | H40: =F40 | I40: =H40 | J40: =I40 | K40: =J40 | L40: =K40 | M40: =L40 | N40: =M40 | O40: =N40 | P40: =O40 | Q40: =P40
C41: Payroll | D41: ='GGC Underwriting'!D35 | E41: ='GGC Underwriting'!E35 | F41: ='GGC Underwriting'!I35 | G41: =F41/'GGC Underwriting'!$N$7 | H41: =F41+(F41*$T$16) | I41: =H41+(H41*$U$16) | J41: =I41+(I41*$V$16) | K41: =J41+(J41*$W$16) | L41: =K41+(K41*$X$16) | M41: =L41+(L41*$Y$16) | N41: =M41+(M41*$Z$16) | O41: =N41+(N41*$Z$16) | P41: =O41+(O41*$Z$16) | Q41: =P41+(P41*$Z$16)
C42: Employee Allowance | D42: ='GGC Underwriting'!D36 | E42: ='GGC Underwriting'!E36 | F42: ='GGC Underwriting'!I36 | G42: =F42/'GGC Underwriting'!$N$7 | H42: =F42+(F42*$T$16) | I42: =H42+(H42*$U$16) | J42: =I42+(I42*$V$16) | K42: =J42+(J42*$W$16) | L42: =K42+(K42*$X$16) | M42: =L42+(L42*$Y$16) | N42: =M42+(M42*$Z$16) | O42: =N42+(N42*$Z$16) | P42: =O42+(O42*$Z$16) | Q42: =P42+(P42*$Z$16)
C43: General and Administrative | D43: ='GGC Underwriting'!D37 | E43: ='GGC Underwriting'!E37 | F43: ='GGC Underwriting'!I37 | G43: =F43/'GGC Underwriting'!$N$7 | H43: =F43+(F43*$T$16) | I43: =H43+(H43*$U$16) | J43: =I43+(I43*$V$16) | K43: =J43+(J43*$W$16) | L43: =K43+(K43*$X$16) | M43: =L43+(L43*$Y$16) | N43: =M43+(M43*$Z$16) | O43: =N43+(N43*$Z$16) | P43: =O43+(O43*$Z$16) | Q43: =P43+(P43*$Z$16)
C44: Model Units | D44: ='GGC Underwriting'!D38 | E44: ='GGC Underwriting'!E38 | F44: ='GGC Underwriting'!I38 | G44: =F44/'GGC Underwriting'!$N$7 | H44: =F44+(F44*$T$16) | I44: =H44+(H44*$U$16) | J44: =I44+(I44*$V$16) | K44: =J44+(J44*$W$16) | L44: =K44+(K44*$X$16) | M44: =L44+(L44*$Y$16) | N44: =M44+(M44*$Z$16) | O44: =N44+(N44*$Z$16) | P44: =O44+(O44*$Z$16) | Q44: =P44+(P44*$Z$16)
C45: Professional Fees | D45: ='GGC Underwriting'!D39 | E45: ='GGC Underwriting'!E39 | F45: ='GGC Underwriting'!I39 | G45: =F45/'GGC Underwriting'!$N$7 | H45: =F45+(F45*$T$16) | I45: =H45+(H45*$U$16) | J45: =I45+(I45*$V$16) | K45: =J45+(J45*$W$16) | L45: =K45+(K45*$X$16) | M45: =L45+(L45*$Y$16) | N45: =M45+(M45*$Z$16) | O45: =N45+(N45*$Z$16) | P45: =O45+(O45*$Z$16) | Q45: =P45+(P45*$Z$16)
C46: Advertising | D46: ='GGC Underwriting'!D40 | E46: ='GGC Underwriting'!E40 | F46: ='GGC Underwriting'!I40 | G46: =F46/'GGC Underwriting'!$N$7 | H46: =F46+(F46*$T$16) | I46: =H46+(H46*$U$16) | J46: =I46+(I46*$V$16) | K46: =J46+(J46*$W$16) | L46: =K46+(K46*$X$16) | M46: =L46+(L46*$Y$16) | N46: =M46+(M46*$Z$16) | O46: =N46+(N46*$Z$16) | P46: =O46+(O46*$Z$16) | Q46: =P46+(P46*$Z$16)
C47: Home Rent Expense | D47: ='GGC Underwriting'!D41 | E47: ='GGC Underwriting'!E41 | F47: ='GGC Underwriting'!I41 | G47: =F47/'GGC Underwriting'!$N$7 | H47: =$B$47*SUM(H20:H21) | I47: =$B$47*SUM(I20:I21) | J47: =$B$47*SUM(J20:J21) | K47: =$B$47*SUM(K20:K21) | L47: =$B$47*SUM(L20:L21) | M47: =$B$47*SUM(M20:M21) | N47: =$B$47*SUM(N20:N21) | O47: =$B$47*SUM(O20:O21) | ... Q47: =$B$47*SUM(Q20:Q21)
C48: Other Expenses | D48: ='GGC Underwriting'!D42 | E48: ='GGC Underwriting'!E42 | F48: ='GGC Underwriting'!I42 | G48: =F48/'GGC Underwriting'!$N$7 | H48: =F48+(F48*$T$16) | I48: =H48+(H48*$U$16) | J48: =I48+(I48*$V$16) | K48: =J48+(J48*$W$16) | L48: =K48+(K48*$X$16) | M48: =L48+(L48*$Y$16) | N48: =M48+(M48*$Z$16) | O48: =N48+(N48*$Z$16) | P48: =O48+(O48*$Z$16) | Q48: =P48+(P48*$Z$16)
C49: Cap-Ex Reserve | D49: ='GGC Underwriting'!D43 | E49: ='GGC Underwriting'!E43 | F49: ='GGC Underwriting'!I43 | G49: =F49/'GGC Underwriting'!$N$7 | H49: =F49+(F49*$T$16) | I49: =H49+(H49*$U$16) | J49: =I49+(I49*$V$16) | K49: =J49+(J49*$W$16) | L49: =K49+(K49*$X$16) | M49: =L49+(L49*$Y$16) | N49: =M49+(M49*$Z$16) | O49: =N49+(N49*$Z$16) | P49: =O49+(O49*$Z$16) | Q49: =P49+(P49*$Z$16)
C50: Total Expenses | D50: =D28+D29+D35+D36+D37+D38+D39+D41+D42+D43+D44+D45+D46+D47+D48+D49 | E50: =E28+E29+E35+E36+E37+E38+E39+E41+E42+E43+E44+E45+E46+E47+E48+E49 | F50: =F28+F29+F35+F36+F37+F38+F39+F41+F42+F43+F44+F45+F46+F47+F48+F49 | G50: =F50/'GGC Underwriting'!$N$7 | H50: =H28+H29+H35+H36+H37+H38+H39+H41+H42+H43+H44+H45+H46+H47+H48+H49 | I50: =I28+I29+I35+I36+I37+I38+I39+I41+I42+I43+I44+I45+I46+I47+I48+I49 | J50: =J28+J29+J35+J36+J37+J38+J39+J41+J42+J43+J44+J45+J46+J47+J48+J49 | K50: =K28+K29+K35+K36+K37+K38+K39+K41+K42+K43+K44+K45+K46+K47+K48+K49 | L50: =L28+L29+L35+L36+L37+L38+L39+L41+L42+L43+L44+L45+L46+L47+L48+L49 | M50: =M28+M29+M35+M36+M37+M38+M39+M41+M42+M43+M44+M45+M46+M47+M48+M49 | N50: =N28+N29+N35+N36+N37+N38+N39+N41+N42+N43+N44+N45+N46+N47+N48+N49 | O50: =O28+O29+O35+O36+O37+O38+O39+O41+O42+O43+O44+O45+O46+O47+O48+O49 | ... Q50: =Q28+Q29+Q35+Q36+Q37+Q38+Q39+Q41+Q42+Q43+Q44+Q45+Q46+Q47+Q48+Q49
C51: Expense Ratio % | D51: =D50/D$25 | E51: =E50/E25 | F51: =F50/F25 | G51: =G50/G25 | H51: =H50/H25 | I51: =I50/I25 | J51: =J50/J25 | K51: =K50/K25 | L51: =L50/L25 | ... Q51: =Q50/Q25
C53: Total Net Operating Income | D53: =D25-D50 | E53: =E25-E50 | F53: =F25-F50 | G53: =F53/'GGC Underwriting'!$N$7 | H53: =H25-H50 | I53: =I25-I50 | J53: =J25-J50 | K53: =K25-K50 | L53: =L25-L50 | M53: =M25-M50 | N53: =N25-N50 | O53: =O25-O50 | ... Q53: =Q25-Q50
C54: NOI Margin | D54: =D53/D$25 | E54: =E53/E$25 | F54: =F53/F$25 | G54: =G53/G$25 | H54: =H53/H$25 | I54: =I53/I$25 | J54: =J53/J$25 | K54: =K53/K$25 | ... Q54: =Q53/Q$25
C56: Lot Rent NOI Only | H56: =H53-H57 | I56: =I53-I57 | J56: =J53-J57 | K56: =K53-K57 | L56: =L53-L57 | M56: =M53-M57 | N56: =N53-N57 | O56: =O53-O57 | ... Q56: =Q53-Q57
C57: Home Rent NOI | H57: =(H20+H21)-H47 | I57: =(I20+I21)-I47 | J57: =(J20+J21)-J47 | K57: =(K20+K21)-K47 | L57: =(L20+L21)-L47 | M57: =(M20+M21)-M47 | N57: =(N20+N21)-N47 | O57: =(O20+O21)-O47 | ... Q57: =(Q20+Q21)-Q47
E58: Exit Summaries
F60: Debt Service | H60: =-'Loan Scenario (acquisition)'!M10 | I60: =-'Loan Scenario (acquisition)'!N10 | J60: =-'Loan Scenario (acquisition)'!O10 | K60: =-'Loan Scenario (acquisition)'!P10 | L60: =-'Loan Scenario (acquisition)'!Q10 | M60: =-'Loan Scenario (acquisition)'!R10 | N60: =-'Loan Scenario (acquisition)'!S10 | O60: =-'Loan Scenario (acquisition)'!T10 | ... Q60: =-'Loan Scenario (acquisition)'!V10
F61: Debt Payoff | Q61: =-'Loan Scenario (acquisition)'!J126
F62: Sale Proceeds Net | H62: ='Unit Mix Rent Growth'!E68 | I62: ='Unit Mix Rent Growth'!F68 | J62: ='Unit Mix Rent Growth'!G68 | K62: ='Unit Mix Rent Growth'!H68 | L62: ='Unit Mix Rent Growth'!I68
F63: Refi Cashout
F64: New Loan | R64: Lot Rent NOI Exit | S64: 0.06
F65: Total Sale - Community | Q65: =(Q56/S64)+(Q57/S65) | R65: Home Rent NOI Exit | S65: =$X$21
F66: Free Cash Flow | G66: =-'Sources and Uses'!$C$7-'Sources and Uses'!$C$8 | H66: =H53+SUM(H60:H65) | I66: =I53+SUM(I60:I65) | J66: =J53+SUM(J60:J65) | K66: =K53+SUM(K60:K65) | L66: =L53+SUM(L60:L65) | M66: =M53+SUM(M60:M65) | N66: =N53+SUM(N60:N65) | O66: =O53+SUM(O60:O65) | ... Q66: =Q53+SUM(Q60:Q65)
F67: DSCR | H67: =-H$53/H$60 | I67: =-I53/I60 | J67: =-J53/I60 | K67: =-K53/K60 | L67: =-L53/L60 | M67: =-M53/M60 | N67: =-N53/N60 | O67: =-O53/O60 | P67: =-P53/P60 | Q67: =-Q53/Q60
F68: Coc Return | H68: =H66/-$G$66 | I68: =I66/-$G$66 | J68: =J66/-$G$66 | K68: =K66/-$G$66 | L68: =L66/-$G$66 | M68: =M66/-$G$66 | N68: =N66/-$G$66 | O68: =O66/-$G$66 | ... Q68: =Q66/-$G$66
E69: 7 Year | F69: Avg cOC Y1-Y4 | G69: =AVERAGE(H68:K68)
F70: IRR | G70: =IRR(G66:Q66)
F71: MOIC | G71: =SUM(H66:Q66)/-G66
F72: New Loan
F73: total Sale - Community | N73: =N53/X20 | R73: Lot Rent Exit cap rate: | S73: =+$X$20
F74: Free Cash Flow | H74: =H53+SUM(H69:H73) | I74: =I53+SUM(I69:I73) | J74: =J53+SUM(J69:J73) | K74: =K53+SUM(K69:K73) | L74: =L53+SUM(L69:L73) | M74: =M53+SUM(M69:M73) | N74: =N53+SUM(N69:N73)
F75: DSCR | H75: =-H$53/H$69 | I75: =-I$53/I$69 | J75: =-J$53/J$69 | K75: =-K$53/K$69 | L75: =-L$53/L$69 | M75: =-M$53/M$69 | N75: =-N$53/N$69
F78: Avg cOC Y1-Y4 | G78: =AVERAGE(H68:P68)
F79: IRR | G79: =IRR(G66:Q66)
E80: 5 YEAR | F80: MOIC | G80: =SUM(H75:Q75)/-G75 | H80: =-'Loan Scenario (acquisition)'!M10 | I80: =-'Loan Scenario (acquisition)'!N10 | J80: =-'Loan Scenario (acquisition)'!O10 | K80: =-'Loan Scenario (acquisition)'!P10 | L80: =-'Loan Scenario (acquisition)'!Q10
F81: Debt Payoff | L81: =-'Loan Scenario (acquisition)'!J66
F82: Refi Cashout
F83: New Loan | M83: Lot Rent NOI Exit | N83: 0.06
F84: Total Sale - Community | L84: =(L56/N83)+(L57/N84) | M84: Home Rent NOI Exit | N84: =$X$21
F85: Free Cash Flow | G85: =-'Sources and Uses'!$C$7-'Sources and Uses'!$C$8 | H85: =H53+SUM(H80:H84) | I85: =I53+SUM(I80:I84) | J85: =J53+SUM(J80:J84) | K85: =K53+SUM(K80:K84) | L85: =L53+SUM(L80:L84)
F86: DSCR | H86: =-H53/H80 | I86: =-I53/I80 | J86: =-J53/J80 | K86: =-K53/K80 | L86: =-L53/L80
F87: MOIC | G87: =SUM(H66:Q66)/-G66
F92: Debt Service | H92: =-'Loan Scenario (acquisition)'!M10 | I92: =-'Loan Scenario (acquisition)'!N10 | J92: =-'Loan Scenario (acquisition)'!O10 | K92: =-'Loan Scenario (acquisition)'!P10 | L92: =-'Loan Scenario (acquisition)'!Q10 | M92: =-6.75%*$L$96 | N92: =-6.75%*$L$96 | O92: =-6.75%*$L$96 | P92: =-6.75%*$L$96 | Q92: =-6.75%*$L$96
F93: Debt Payoff | L93: =-'Loan Scenario (acquisition)'!J66 | Q93: =-L96
F94: Seller finance service | H94: =-5%*'Sources and Uses'!O5 | I94: =-5%*'Sources and Uses'!O6 | J94: =-5%*'Sources and Uses'!O7 | K94: =-5%*'Sources and Uses'!O8 | L94: =-5%*'Sources and Uses'!O9
F95: Seller finance payoff | L95: =-'Sources and Uses'!O9
F96: Refi Cashout | L96: =L56/7.78%/1.25
R97: Lot Rent NOI Exit | S97: 0.06
F98: Total Sale - Community | Q98: =(Q56/S97)+(Q57/S98) | R98: Home Rent NOI Exit | S98: =$X$21
F99: Free Cash Flow | G99: =-'Sources and Uses'!I7-'Sources and Uses'!I8 | H99: =H53+SUM(H92:H98) | I99: =I53+SUM(I92:I98) | J99: =J53+SUM(J92:J98) | K99: =K53+SUM(K92:K98) | L99: =L53+SUM(L92:L98) | M99: =M53+SUM(M92:M98) | N99: =N53+SUM(N92:N98) | O99: =O53+SUM(O92:O98) | ... Q99: =Q53+SUM(Q92:Q98)
F100: DSCR | H100: =-H53/(H92+H94) | I100: =-I53/(I92+I94) | J100: =-J53/(J92+J94) | K100: =-K53/(K92+K94) | L100: =-L53/(L92+L94) | M100: =-M53/(M92+M94) | N100: =-N53/(N92+N94) | O100: =-O53/(O92+O94) | ... Q100: =-Q53/(Q92+Q94)
F101: Coc Return | H101: =H99/-$G$99 | I101: =I99/-$G$99 | J101: =J99/-$G$99 | K101: =K99/-$G$99 | L101: =L99/-$G$99 | M101: =M99/-$G$99 | N101: =N99/-$G$99 | O101: =O99/-$G$99 | ... Q101: =Q99/-$G$99
F102: Avg cOC Y1-Y4 | G102: =AVERAGE(H101:K101)
F103: IRR | G103: =IRR(G99:Q99)
F104: MOIC | G104: =SUM(H99:Q99)/-G99
F108: Debt Service | H108: =-'Loan Scenario (acquisition)'!M10 | I108: =-'Loan Scenario (acquisition)'!N10 | J108: =-'Loan Scenario (acquisition)'!O10 | K108: =-'Loan Scenario (acquisition)'!P10 | L108: =-'Loan Scenario (acquisition)'!Q10 | M108: =M92 | N108: =N92 | O108: =O92 | P108: =P92 | Q108: =Q92
F109: Debt Payoff | L109: =-'Loan Scenario (acquisition)'!J66 | Q109: =-L112
F110: Seller finance service I/O | H110: =-5%*'Sources and Uses'!I6 | I110: =H110 | J110: =I110 | K110: =J110 | L110: =K110
F111: Seller finance payoff-balloon pmt | L111: =-'Sources and Uses'!I6
F112: Refi Cashout | L112: =L96
F113: Sales Proceeds | H113: ='Unit Mix Rent Growth'!E68 | I113: ='Unit Mix Rent Growth'!F68 | J113: ='Unit Mix Rent Growth'!G68 | K113: ='Unit Mix Rent Growth'!H68 | L113: ='Unit Mix Rent Growth'!I68 | R113: Lot Rent NOI Exit | S113: 0.06
...

Sheet Investor Return
M1: Summary/Output
C3: Investor Return Summary
C4: 10 Year Return Summary | M4: Send LOI? | N4: No
C5: Deal Level | D5: Exit Cap Rate 6% in-going | M5: Reason if No
C6: IRR | F6: ='Waterfall (10-yr-S1)'!D30
C7: Equity Multiple | F7: ='Waterfall (10-yr-S1)'!D31
C8: Cash on Cash Avg Y1-Y9 | F8: =AVERAGE('Waterfall (10-yr-S1)'!G31:O31)
C17: 5 Year Return Summary
C18: Deal Level | D18: Exit Cap Rate 6.5% in-going
C19: IRR | F19: ='Waterfall (5-yr-S1)'!D30
C20: Equity Multiple | F20: ='Waterfall (5-yr-S1)'!D31
C21: Cash on Cash Avg Y1-Y4 | F21: =AVERAGE('Waterfall (5-yr-S1)'!G31:J31)
C25: 10 Year Return Summary
C26: Deal Level | D26: Exit Cap Rate 6% in-going
C27: IRR | F27: =AVERAGE('Waterfall (10-yr-S1)'!G31:O31)
C28: Equity Multiple | F28: ='Waterfall (10-yr-S1)'!D31
C29: Cash on Cash Avg Y1-Y4 | F29: =AVERAGE('Waterfall (10-yr-S1)'!G31:J31)
C33: Summary
B34: 1 | C34: Expansion land -can fit in 25 additional units for value add-MH zoned
B35: 2 | C35: IRR 16% w/seller note + refi
B36: 3 | C36: pay down seller note w/ sales proceeds
B37: 4 | C37: go market lot rent $700 by Y3-nearby comps support
B38: 5 | C38: closer proximity to Brookhaven (15 miles)
B39: 6 | C39: majority POH-LTO doesn't mature until hold period--no signiciant decline in LTO income
B40: 7 | C40: opportunity to recapture w/s
B41: 8 | C41: mix of SW/DW | D41: DW market lot rent is higher $775

Sheet Waterfall (10-yr-S1)
B2: PARTNERSHIP LEVEL RETURNS - EQUITY WATERFALL (IRR & EQUITY MULTIPLE HURDLES)
B4: Promote Hurdle Method | D4: IRR | E4: GP Catch Up?
B5: # of Tiers | D5: 3-Tier
A6: =AND(E6="Yes", H15<Equity_Share_GP) | B6: Return of Capital | D6: =IF(H15<Equity_Share_GP,"LP 1st","Pari Passu") | E6: Yes
B8: Equity Contributions | C8: % | D8: Amount
B9: General Partner (GP) | C9: ='Sources and Uses'!E8 | D9: =Equity_Share_GP*Total_Equity | K9: Error Check: | L9: =IF(ROUND(L11,0)=ROUND(L10,0),"OK","Error")
B10: Limited Partner (LP) | C10: =1-C9 | D10: =Total_Equity*Equity_Share_LP | K10: Profit Dist.: | L10: =(D29+D41)/1000000
B11: Total Equity | D11: =-SUMIF(F51:M51,"<0") | K11: Net BTCF: | L11: =SUM(F47:M47)/1000000
B13: Hurdle Rate Method Used: | C13: =IF(D4="IRR","IRR",IF(D4="Equity Multiple","Equity Multiple",IF(D4<>"IRR + EMx","",IF(D71<D179,"IRR","Equity Multiple")))) | F13: Promote Structure Incentive Breakdown | H13: Distribution as %
B14: =IF(D4="Equity Multiple","Partnership Distribution Assumptions (Equity Multiple Hurdles)",IF(D4="IRR","Partnership Distribution Assumptions (IRR Hurdles)","Partnership Distribution Assumptions (Max of IRR or Emx Hurdles)")) | H14: GP % | I14: LP % | J14: Notes
B15: Tier 1 (Pref + Return of Capital) | C15: Equity Multiple | D15: IRR | E15: =IF($D$4="Equity Multiple",C16,D16) | F15: GP Promote | H15: =Equity_Share_GP | I15: =1-H15 | J15: =IF(I15=Equity_Share_LP,"Pref prorata to LP/GP, then Pro rata return of capital",IF(CU?,"Return of capital and Pref NOT pro rata + GP Catch Up","Return of capital and Pref NOT pro rata"))
B16: Tier 2 (Promote) | C16: 1 | D16: 0.08 | E16: =IF($D$4="Equity Multiple",IF(B277<3,"",C17),IF(B277<3,"",D17)) | F16: 0.25 | H16: =1-(Equity_Share_LP*(1-F16)) | I16: =1-H16 | J16: =IF(Equity_Share_GP<>H15,TEXT(I15,"0.0%")&"/"&TEXT(H15,"0.0%")&" to "&(IF(D4="IRR",TEXT(E15,"0.0%"),TEXT(E15,"0.0X")))&", then "&TEXT(I16,"0.0%")&"/"&TEXT(H16,"0.0%")&" to "&(IF(D4="IRR",TEXT(E16,"0.0%"),TEXT(E16,"0.0X"))),"Prorata to LP/GP to "&(IF(D4="IRR",TEXT(E15,"0.0%"),TEXT(E15,"0.0X")))&", then "&TEXT(I16,"0.0%")&"/"&TEXT(H16,"0.0%")&" to "&(IF(D4="IRR",TEXT(E16,"0.0%"),TEXT(E16,"0.0X"))))
B17: =IF(B277<3,"NOT USED","Tier 3 (Promote)") | C17: 1.5 | D17: 0.12 | E17: =IF($D$4="Equity Multiple",IF(B277<4,"",C18),IF(B277<4,"",D18)) | F17: 0.4 | H17: =1-(Equity_Share_LP*(1-F17)) | I17: =1-H17 | J17: =TEXT(I16,"0.0%")&"/"&TEXT(H16,"0.0%")&" to "&(IF(D4="IRR",TEXT(E16,"0.0%"),TEXT(E16,"0.0X")))&", then "&TEXT(I17,"0.0%")&"/"&TEXT(H17,"0.0%")&" to "&(IF(D4="IRR",TEXT(E17,"0.0%"),TEXT(E17,"0.0X")))
B18: =IF(B277<4,"NOT USED","Tier 4 (Promote)") | C18: 2 | D18: 0.15 | E18: =IF($D$4="Equity Multiple",IF(B277<5,"",C19),IF(B277<5,"",D19)) | F18: 0.4 | H18: =1-(Equity_Share_LP*(1-F18)) | I18: =1-H18 | J18: =TEXT(I17,"0.0%")&"/"&TEXT(H17,"0.0%")&" to "&(IF(D4="IRR",TEXT(E17,"0.0%"),TEXT(E17,"0.0X")))&", then "&TEXT(I18,"0.0%")&"/"&TEXT(H18,"0.0%")&" thereafter"
B19: =IF(B277<5,"NOT USED","Tier 5 (Promote)") | C19: 2.5 | D19: 0.18 | F19: 0.5 | H19: =1-(Equity_Share_LP*(1-F19)) | I19: =1-H19 | J19: =TEXT(I18,"0.0%")&"/"&TEXT(H18,"0.0%")&" to "&(IF(D6="IRR",TEXT(E18,"0.0%"),TEXT(E18,"0.0X")))&", then "&TEXT(I19,"0.0%")&"/"&TEXT(H19,"0.0%")&" thereafter"
B21: Summary of Partnership-Level Returns | D21: Analysis Period | E21: =MAX(F21:M21) | F21: 0 | G21: =IF(G47="","",F21+1) | H21: =IF(H47="","",G21+1) | I21: =IF(I47="","",H21+1) | J21: =IF(J47="","",I21+1) | K21: =IF(K47="","",J21+1) | L21: =IF(L47="","",K21+1) | M21: =IF(M47="","",L21+1) | N21: =IF(N47="","",M21+1) | ... P21: =IF(P47="","",O21+1)
B22: Limited Partner (LP) Returns
C23: Check
B24: Preferred Return | C24: =IF(ROUND(D24,0)=ROUND(SUM(F24:P24),0),"OK","ERROR") | D24: =(C13="IRR")*(SUM(F97:P97)-D25)+(C13="Equity Multiple")*(SUM(F205:P205)-D25) | F24: =IF(F21="","",MIN($D24-SUM($E24:E24),F27)) | G24: =IF(G21="","",MIN($D24-SUM($E24:F24),G27)) | H24: =IF(H21="","",MIN($D24-SUM($E24:G24),H27)) | I24: =IF(I21="","",MIN($D24-SUM($E24:H24),I27)) | J24: =IF(J21="","",MIN($D24-SUM($E24:I24),J27)) | K24: =IF(K21="","",MIN($D24-SUM($E24:J24),K27)) | L24: =IF(L21="","",MIN($D24-SUM($E24:K24),L27)) | M24: =IF(M21="","",MIN($D24-SUM($E24:L24),M27)) | ... P24: =IF(P21="","",MIN($D24-SUM($E24:O24),P27))
B25: Return of Capital | C25: =IF(ROUND(D25,0)=ROUND(SUM(F25:P25),0),"OK","ERROR") | D25: =MIN(D28,D27) | F25: =IF(F21="","",MIN($D25-SUM($E25:E25),F27-F24)) | G25: =IF(G21="","",MIN($D25-SUM($E25:F25),G27-G24)) | H25: =IF(H21="","",MIN($D25-SUM($E25:G25),H27-H24)) | I25: =IF(I21="","",MIN($D25-SUM($E25:H25),I27-I24)) | J25: =IF(J21="","",MIN($D25-SUM($E25:I25),J27-J24)) | K25: =IF(K21="","",MIN($D25-SUM($E25:J25),K27-K24)) | L25: =IF(L21="","",MIN($D25-SUM($E25:K25),L27-L24)) | M25: =IF(M21="","",MIN($D25-SUM($E25:L25),M27-M24)) | ... P25: =IF(P21="","",MIN($D25-SUM($E25:O25),P27-P24))
B26: Excess Cash Flow | C26: =IF(ROUND(D26,0)=ROUND(SUM(F26:P26),0),"OK","ERROR") | D26: =D27-D25-D24 | F26: =IF(F21="","",F27-F25-F24) | G26: =IF(G21="","",G27-G25-G24) | H26: =IF(H21="","",H27-H25-H24) | I26: =IF(I21="","",I27-I25-I24) | J26: =IF(J21="","",J27-J25-J24) | K26: =IF(K21="","",K27-K25-K24) | L26: =IF(L21="","",L27-L25-L24) | M26: =IF(M21="","",M27-M25-M24) | ... P26: =IF(P21="","",P27-P25-P24)
B27: Total LP Distributions | D27: =SUM(F27:P27) | F27: =IF(F$21="","",($C$13="IRR")*F68+($C$13="Equity Multiple")*F176) | G27: =IF(G$21="","",($C$13="IRR")*G68+($C$13="Equity Multiple")*G176) | H27: =IF(H$21="","",($C$13="IRR")*H68+($C$13="Equity Multiple")*H176) | I27: =IF(I$21="","",($C$13="IRR")*I68+($C$13="Equity Multiple")*I176) | J27: =IF(J$21="","",($C$13="IRR")*J68+($C$13="Equity Multiple")*J176) | K27: =IF(K$21="","",($C$13="IRR")*K68+($C$13="Equity Multiple")*K176) | L27: =IF(L$21="","",($C$13="IRR")*L68+($C$13="Equity Multiple")*L176) | M27: =IF(M$21="","",($C$13="IRR")*M68+($C$13="Equity Multiple")*M176) | ... P27: =IF(P$21="","",($C$13="IRR")*P68+($C$13="Equity Multiple")*P176)
B28: Total LP Contributions | D28: =SUM(F28:P28) | F28: =F96 | G28: =G96 | H28: =H96 | I28: =I96 | J28: =J96 | K28: =K96 | L28: =L96 | M28: =M96 | ... P28: =P96
B29: Total LP Profit | D29: =D27-D28
B30: LP IRR | D30: =IRR(F30:P30) | F30: =IF(F21="","",(-F28)+F27) | G30: =IF(G21="","",(-G28)+G27) | H30: =IF(H21="","",(-H28)+H27) | I30: =IF(I21="","",(-I28)+I27) | J30: =IF(J21="","",(-J28)+J27) | K30: =IF(K21="","",(-K28)+K27) | L30: =IF(L21="","",(-L28)+L27) | M30: =IF(M21="","",(-M28)+M27) | ... P30: =IF(P21="","",(-P28)+P27)
B31: LP Equity Multiple | D31: =D27/D28 | G31: =IF($D$4="IRR", G30/G93,G30/G201) | H31: =IF($D$4="IRR", H30/H93,H30/H201) | I31: =IF($D$4="IRR", I30/I93,I30/I201) | J31: =IF($D$4="IRR", J30/J93,J30/J201) | K31: =IF($D$4="IRR", K30/K93,K30/K201) | L31: =IF($D$4="IRR", L30/L93,L30/L201) | M31: =IF($D$4="IRR", M30/M93,M30/M201) | N31: =IF($D$4="IRR", N30/N93,N30/N201) | ... P31: =IF($D$4="IRR", P30/P93,P30/P201)
B33: GP Returns
B34: Preferred Return | C34: =IF(ROUND(D34,0)=ROUND(SUM(F34:P34),0),"OK","ERROR") | D34: =(C13="IRR")*(SUM(F105:P105)-D35)+(C13="Equity Multiple")*(SUM(F213:P213)-D35) | F34: =IF(F21="","",MIN($D34-SUM($E34:E34),F38)) | G34: =IF(G21="","",MIN($D34-SUM($E34:F34),G38)) | H34: =IF(H21="","",MIN($D34-SUM($E34:G34),H38)) | I34: =IF(I21="","",MIN($D34-SUM($E34:H34),I38)) | J34: =IF(J21="","",MIN($D34-SUM($E34:I34),J38)) | K34: =IF(K21="","",MIN($D34-SUM($E34:J34),K38)) | L34: =IF(L21="","",MIN($D34-SUM($E34:K34),L38)) | M34: =IF(M21="","",MIN($D34-SUM($E34:L34),M38)) | ... P34: =IF(P21="","",MIN($D34-SUM($E34:O34),P38))
B35: Return of Capital | C35: =IF(ROUND(D35,0)=ROUND(SUM(F35:P35),0),"OK","ERROR") | D35: =MIN(D38,D40) | F35: =IF(F21="","",MIN($D35-SUM($E35:E35),F38-F34)) | G35: =IF(G21="","",MIN($D35-SUM($E35:F35),G38-G34)) | H35: =IF(H21="","",MIN($D35-SUM($E35:G35),H38-H34)) | I35: =IF(I21="","",MIN($D35-SUM($E35:H35),I38-I34)) | J35: =IF(J21="","",MIN($D35-SUM($E35:I35),J38-J34)) | K35: =IF(K21="","",MIN($D35-SUM($E35:J35),K38-K34)) | L35: =IF(L21="","",MIN($D35-SUM($E35:K35),L38-L34)) | M35: =IF(M21="","",MIN($D35-SUM($E35:L35),M38-M34)) | ... P35: =IF(P21="","",MIN($D35-SUM($E35:O35),P38-P34))
B36: Promote | C36: =IF(ROUND(D36,0)=ROUND(SUM(F36:P36),0),"OK","ERROR") | D36: =D38-D35-D37-D34 | F36: =IF(F21="","",F38-F37-F35-F34) | G36: =IF(G21="","",G38-G37-G35-G34) | H36: =IF(H21="","",H38-H37-H35-H34) | I36: =IF(I21="","",I38-I37-I35-I34) | J36: =IF(J21="","",J38-J37-J35-J34) | K36: =IF(K21="","",K38-K37-K35-K34) | L36: =IF(L21="","",L38-L37-L35-L34) | M36: =IF(M21="","",M38-M37-M35-M34) | ... P36: =IF(P21="","",P38-P37-P35-P34)
B37: Excess Cash Flow | C37: =IF(ROUND(D37,0)=ROUND(SUM(F37:P37),0),"OK","ERROR") | D37: =D26/Equity_Share_LP*Equity_Share_GP | F37: =IF(F21="","",F26/Equity_Share_LP*Equity_Share_GP) | G37: =IF(G21="","",G26/Equity_Share_LP*Equity_Share_GP) | H37: =IF(H21="","",H26/Equity_Share_LP*Equity_Share_GP) | I37: =IF(I21="","",I26/Equity_Share_LP*Equity_Share_GP) | J37: =IF(J21="","",J26/Equity_Share_LP*Equity_Share_GP) | K37: =IF(K21="","",K26/Equity_Share_LP*Equity_Share_GP) | L37: =IF(L21="","",L26/Equity_Share_LP*Equity_Share_GP) | M37: =IF(M21="","",M26/Equity_Share_LP*Equity_Share_GP) | ... P37: =IF(P21="","",P26/Equity_Share_LP*Equity_Share_GP)
B38: Total GP Distributions | D38: =SUM(F38:P38) | F38: =IF(F$21="","",($C$13="IRR")*F75+($C$13="Equity Multiple")*F183) | G38: =IF(G$21="","",($C$13="IRR")*G75+($C$13="Equity Multiple")*G183) | H38: =IF(H$21="","",($C$13="IRR")*H75+($C$13="Equity Multiple")*H183) | I38: =IF(I$21="","",($C$13="IRR")*I75+($C$13="Equity Multiple")*I183) | J38: =IF(J$21="","",($C$13="IRR")*J75+($C$13="Equity Multiple")*J183) | K38: =IF(K$21="","",($C$13="IRR")*K75+($C$13="Equity Multiple")*K183) | L38: =IF(L$21="","",($C$13="IRR")*L75+($C$13="Equity Multiple")*L183) | M38: =IF(M$21="","",($C$13="IRR")*M75+($C$13="Equity Multiple")*M183) | ... P38: =IF(P$21="","",($C$13="IRR")*P75+($C$13="Equity Multiple")*P183)
B39: Total GP Fees | D39: =SUM(F39:P39) | F39: =IF(F21="","",SUM(F48:F49)) | G39: =IF(G21="","",SUM(G48:G49)) | H39: =IF(H21="","",SUM(H48:H49)) | I39: =IF(I21="","",SUM(I48:I49)) | J39: =IF(J21="","",SUM(J48:J49)) | K39: =IF(K21="","",SUM(K48:K49)) | L39: =IF(L21="","",SUM(L48:L49)) | M39: =IF(M21="","",SUM(M48:M49)) | ... P39: =IF(P21="","",SUM(P48:P49))
B40: Total GP Contributions | D40: =SUM(F40:P40) | F40: =F104 | G40: =G104 | H40: =H104 | I40: =I104 | J40: =J104 | K40: =K104 | L40: =L104 | M40: =M104 | ... P40: =P104
B41: Total GP Profit (Including Fees) | D41: =+D38+D39-D40
B42: GP IRR | D42: =IFERROR(IRR(F42:P42),"NA") | F42: =IF(F21="","",(-F40)+F38+F39) | G42: =IF(G21="","",(-G40)+G38+G39) | H42: =IF(H21="","",(-H40)+H38+H39) | I42: =IF(I21="","",(-I40)+I38+I39) | J42: =IF(J21="","",(-J40)+J38+J39) | K42: =IF(K21="","",(-K40)+K38+K39) | L42: =IF(L21="","",(-L40)+L38+L39) | M42: =IF(M21="","",(-M40)+M38+M39) | ... P42: =IF(P21="","",(-P40)+P38+P39)
B43: GP Equity Multiple | D43: =IFERROR(D38/D40,"NA")
B45: Property-Level Cash and GP Fees | F45: Year 0 | G45: =G$21 | H45: =H$21 | I45: =I$21 | J45: =J$21 | K45: =K$21 | L45: =L$21 | M45: =M$21 | N45: =N$21 | ... P45: =P$21
E46: Year Ending | F46: 45657 | G46: =IF(G45="","",EOMONTH(F46,12)) | H46: =IF(H45="","",EOMONTH(G46,12)) | I46: =IF(I45="","",EOMONTH(H46,12)) | J46: =IF(J45="","",EOMONTH(I46,12)) | K46: =IF(K45="","",EOMONTH(J46,12)) | L46: =IF(L45="","",EOMONTH(K46,12)) | M46: =IF(M45="","",EOMONTH(L46,12)) | N46: =IF(N45="","",EOMONTH(M46,12)) | ... P46: =IF(P45="","",EOMONTH(O46,12))
B47: Net Property-Level Cash Flow | F47: =-'Sources and Uses'!C7-'Sources and Uses'!C8+'Sources and Uses'!C15 | G47: ='GGC Pro Forma'!H65 | H47: ='GGC Pro Forma'!I65 | I47: ='GGC Pro Forma'!J65 | J47: ='GGC Pro Forma'!K65 | K47: ='GGC Pro Forma'!L65 | L47: ='GGC Pro Forma'!M65 | M47: ='GGC Pro Forma'!N65 | N47: ='GGC Pro Forma'!O65 | ... P47: ='GGC Pro Forma'!Q65
B48: Asset Management Fees | F48: 0 | G48: =2%*'GGC Pro Forma'!H25 | H48: =2%*'GGC Pro Forma'!I25 | I48: =2%*'GGC Pro Forma'!J25 | J48: =2%*'GGC Pro Forma'!K25 | K48: =2%*'GGC Pro Forma'!L25 | L48: =2%*'GGC Pro Forma'!M25 | M48: =2%*'GGC Pro Forma'!N25 | N48: =2%*'GGC Pro Forma'!O25 | ... P48: =2%*'GGC Pro Forma'!Q25
B49: Acquisition/Disposition Fees | F49: ='Sources and Uses'!C15 | G49: 0 | H49: 0 | I49: 0 | J49: 0 | K49: 0 | L49: 0 | M49: 0 | N49: 0 | O49: 0 | P49: 0
B51: Adjusted Net Property-Level Cash Flow | F51: =IF(F45="","",F47-F48-F49) | G51: =IF(G45="","",G47-G48-G49) | H51: =IF(H45="","",H47-H48-H49) | I51: =IF(I45="","",I47-I48-I49) | J51: =IF(J45="","",J47-J48-J49) | K51: =IF(K45="","",K47-K48-K49) | L51: =IF(L45="","",L47-L48-L49) | M51: =IF(M45="","",M47-M48-M49) | ... P51: =IF(P45="","",P47-P48-P49)
B52: Levered IRR | F52: =IRR(F51:P51)
B53: Equity Multiple | F53: =SUMIF(F51:P51,">0")/-SUMIF(F51:P51,"<0")
B56: PARTNERSHIP LEVEL RETURNS - IRR EQUITY WATERFALL
D57: =$D$4
F58: Promote Structure Incentive Breakdown | H58: Distribution as %
B59: =IF(D57="Equity Multiple","Partnership Distribution Assumptions (Equity Multiple Hurdles)","Partnership Distribution Assumptions (IRR Hurdles)") | H59: GP % | I59: LP % | J59: Notes
B60: =B15 | E60: =D61 | F60: GP Promote | H60: =H15 | I60: =1-H60 | J60: =IF(I60=Equity_Share_LP,"Pref prorata to LP/GP, then Pro rata return of capital",IF(CU?,"Return of capital and Pref NOT pro rata + GP Catch Up","Return of capital and Pref NOT pro rata"))
B61: =B16 | D61: =D16 | E61: =IF($B$277<3,9.99,D62) | F61: =F16 | H61: =H16 | I61: =1-H61 | J61: =IF(Equity_Share_GP<>H60,TEXT(I60,"0.0%")&"/"&TEXT(H60,"0.0%")&" to "&(IF(D57="IRR",TEXT(E60,"0.0%"),TEXT(E60,"0.0X")))&", then "&TEXT(I61,"0.0%")&"/"&TEXT(H61,"0.0%")&" to "&(IF(D57="IRR",TEXT(E61,"0.0%"),TEXT(E61,"0.0X"))),"Prorata to LP/GP to "&(IF(D57="IRR",TEXT(E60,"0.0%"),TEXT(E60,"0.0X")))&", then "&TEXT(I61,"0.0%")&"/"&TEXT(H61,"0.0%")&" to "&(IF(D57="IRR",TEXT(E61,"0.0%"),TEXT(E61,"0.0X"))))
B62: =B17 | D62: =D17 | E62: =IF($B$277<4,9.99,D63) | F62: =F17 | H62: =H17 | I62: =1-H62 | J62: =TEXT(I61,"0.0%")&"/"&TEXT(H61,"0.0%")&" to "&(IF(D57="IRR",TEXT(E61,"0.0%"),TEXT(E61,"0.0X")))&", then "&TEXT(I62,"0.0%")&"/"&TEXT(H62,"0.0%")&" to "&(IF(D57="IRR",TEXT(E62,"0.0%"),TEXT(E62,"0.0X")))
B63: =B18 | D63: =D18 | E63: =IF($B$277<5,9.99,D64) | F63: =F18 | H63: =H18 | I63: =1-H63 | J63: =TEXT(I62,"0.0%")&"/"&TEXT(H62,"0.0%")&" to "&(IF(D58="IRR",TEXT(E62,"0.0%"),TEXT(E62,"0.0X")))&", then "&TEXT(I63,"0.0%")&"/"&TEXT(H63,"0.0%")&" to "&(IF(D58="IRR",TEXT(E63,"0.0%"),TEXT(E63,"0.0X")))
B64: =B19 | D64: =D19 | F64: =F19 | H64: =H19 | I64: =1-H64 | J64: =TEXT(I63,"0.0%")&"/"&TEXT(H63,"0.0%")&" to "&(IF(D59="IRR",TEXT(E63,"0.0%"),TEXT(E63,"0.0X")))&", then "&TEXT(I64,"0.0%")&"/"&TEXT(H64,"0.0%")&" to "&(IF(D59="IRR",TEXT(E64,"0.0%"),TEXT(E64,"0.0X")))
B66: Summary of Partnership-Level Returns | F66: 0 | G66: =IF(G84="","",F66+1) | H66: =IF(H84="","",G66+1) | I66: =IF(I84="","",H66+1) | J66: =IF(J84="","",I66+1) | K66: =IF(K84="","",J66+1) | L66: =IF(L84="","",K66+1) | M66: =IF(M84="","",L66+1) | N66: =IF(N84="","",M66+1) | ... P66: =IF(P84="","",O66+1)
B67: Limited Partner (LP) Returns
B68: Total LP Distributions | D68: =SUM(F68:P68) | F68: =IF(F66="","",F100+F122+F137+F152+F159) | G68: =IF(G66="","",G100+G122+G137+G152+G159) | H68: =IF(H66="","",H100+H122+H137+H152+H159) | I68: =IF(I66="","",I100+I122+I137+I152+I159) | J68: =IF(J66="","",J100+J122+J137+J152+J159) | K68: =IF(K66="","",K100+K122+K137+K152+K159) | L68: =IF(L66="","",L100+L122+L137+L152+L159) | M68: =IF(M66="","",M100+M122+M137+M152+M159) | ... P68: =IF(P66="","",P100+P122+P137+P152+P159)
B69: Total LP Contributions | D69: =SUM(F69:P69) | F69: =F96 | G69: =G96 | H69: =H96 | I69: =I96 | J69: =J96 | K69: =K96 | L69: =L96 | M69: =M96 | ... P69: =P96
B70: Total LP Profit | D70: =D68-D69
B71: LP IRR | D71: =IRR(F71:P71) | F71: =IF(F66="","",(-F69)+F68) | G71: =IF(G66="","",(-G69)+G68) | H71: =IF(H66="","",(-H69)+H68) | I71: =IF(I66="","",(-I69)+I68) | J71: =IF(J66="","",(-J69)+J68) | K71: =IF(K66="","",(-K69)+K68) | L71: =IF(L66="","",(-L69)+L68) | M71: =IF(M66="","",(-M69)+M68) | ... P71: =IF(P66="","",(-P69)+P68)
B72: LP Equity Multiple | D72: =D68/D69
B74: GP Returns
B75: Total GP Distributions | D75: =SUM(F75:P75) | F75: =IF(F66="","",F105+F123+F138+F153+F160) | G75: =IF(G66="","",G105+G123+G138+G153+G160) | H75: =IF(H66="","",H105+H123+H138+H153+H160) | I75: =IF(I66="","",I105+I123+I138+I153+I160) | J75: =IF(J66="","",J105+J123+J138+J153+J160) | K75: =IF(K66="","",K105+K123+K138+K153+K160) | L75: =IF(L66="","",L105+L123+L138+L153+L160) | M75: =IF(M66="","",M105+M123+M138+M153+M160) | ... P75: =IF(P66="","",P105+P123+P138+P153+P160)
B76: Total GP Fees | D76: =SUM(F76:P76) | F76: =IF(F66="","",SUM(F85:F86)) | G76: =IF(G66="","",SUM(G85:G86)) | H76: =IF(H66="","",SUM(H85:H86)) | I76: =IF(I66="","",SUM(I85:I86)) | J76: =IF(J66="","",SUM(J85:J86)) | K76: =IF(K66="","",SUM(K85:K86)) | L76: =IF(L66="","",SUM(L85:L86)) | M76: =IF(M66="","",SUM(M85:M86)) | ... P76: =IF(P66="","",SUM(P85:P86))
B77: Total GP Contributions | D77: =SUM(F77:P77) | F77: =IF(F66="","",-(MIN(F87,0)+F96)) | G77: =IF(G66="","",-(MIN(G87,0)+G96)) | H77: =IF(H66="","",-(MIN(H87,0)+H96)) | I77: =IF(I66="","",-(MIN(I87,0)+I96)) | J77: =IF(J66="","",-(MIN(J87,0)+J96)) | K77: =IF(K66="","",-(MIN(K87,0)+K96)) | L77: =IF(L66="","",-(MIN(L87,0)+L96)) | M77: =IF(M66="","",-(MIN(M87,0)+M96)) | ... P77: =IF(P66="","",-(MIN(P87,0)+P96))
B78: Total GP Profit | D78: =+D75+D76-D77
B79: GP IRR | D79: =IFERROR(IRR(F79:P79),"NA") | F79: =IF(F66="","",(-F77)+F75+F76) | G79: =IF(G66="","",(-G77)+G75+G76) | H79: =IF(H66="","",(-H77)+H75+H76) | I79: =IF(I66="","",(-I77)+I75+I76) | J79: =IF(J66="","",(-J77)+J75+J76) | K79: =IF(K66="","",(-K77)+K75+K76) | L79: =IF(L66="","",(-L77)+L75+L76) | M79: =IF(M66="","",(-M77)+M75+M76) | ... P79: =IF(P66="","",(-P77)+P75+P76)
B80: GP Equity Multiple | D80: =IFERROR(D75/D77,"NA")
B82: Property-Level Cash and GP Fees | F82: Year 0 | G82: =G$21 | H82: =H$21 | I82: =I$21 | J82: =J$21 | K82: =K$21 | L82: =L$21 | M82: =M$21 | N82: =N$21 | ... P82: =P$21
E83: Year Ending | F83: =IF(F46="","",F46) | G83: =IF(G46="","",G46) | H83: =IF(H46="","",H46) | I83: =IF(I46="","",I46) | J83: =IF(J46="","",J46) | K83: =IF(K46="","",K46) | L83: =IF(L46="","",L46) | M83: =IF(M46="","",M46) | ... P83: =IF(P46="","",P46)
B84: Net Property-Level Cash Flow | F84: =IF(F47="","",F47) | G84: =IF(G47="","",G47) | H84: =IF(H47="","",H47) | I84: =IF(I47="","",I47) | J84: =IF(J47="","",J47) | K84: =IF(K47="","",K47) | L84: =IF(L47="","",L47) | M84: =IF(M47="","",M47) | ... P84: =IF(P47="","",P47)
B85: =IF(B48="","",B48) | F85: =IF(F48="","",F48) | G85: =IF(G48="","",G48) | H85: =IF(H48="","",H48) | I85: =IF(I48="","",I48) | J85: =IF(J48="","",J48) | K85: =IF(K48="","",K48) | L85: =IF(L48="","",L48) | M85: =IF(M48="","",M48) | ... P85: =IF(P48="","",P48)
B86: =IF(B49="","",B49) | F86: =IF(F49="","",F49) | G86: =IF(G49="","",G49) | H86: =IF(H49="","",H49) | I86: =IF(I49="","",I49) | J86: =IF(J49="","",J49) | K86: =IF(K49="","",K49) | L86: =IF(L49="","",L49) | M86: =IF(M49="","",M49) | ... P86: =IF(P49="","",P49)
B87: Adjusted Net Property-Level Cash Flow | F87: =IF(F82="","",F84-F85-F86) | G87: =IF(G82="","",G84-G85-G86) | H87: =IF(H82="","",H84-H85-H86) | I87: =IF(I82="","",I84-I85-I86) | J87: =IF(J82="","",J84-J85-J86) | K87: =IF(K82="","",K84-K85-K86) | L87: =IF(L82="","",L84-L85-L86) | M87: =IF(M82="","",M84-M85-M86) | ... P87: =IF(P82="","",P84-P85-P86)
B88: Levered IRR | F88: =IRR(F87:M87)
B89: Equity Multiple | F89: =SUMIF(F87:M87,">0")/-SUMIF(F87:M87,"<0")
B91: Tier 1 - Preferred Return + Return of Capital
B92: Return Threshold - Up to: | C92: =E60 | F92: Year 0 | G92: =G$21 | H92: =H$21 | I92: =I$21 | J92: =J$21 | K92: =K$21 | L92: =L$21 | M92: =M$21 | N92: =N$21 | ... P92: =P$21
B93: Beginning Balance (LP Capital Account) | F93: =IF(F92="","",E98) | G93: =IF(G92="","",F98) | H93: =IF(H92="","",G98) | I93: =IF(I92="","",H98) | J93: =IF(J92="","",I98) | K93: =IF(K92="","",J98) | L93: =IF(L92="","",K98) | M93: =IF(M92="","",L98) | ... P93: =IF(P92="","",O98)
B94: LP Return of Capital | F94: =IF(ROUND(SUM(G94:M94),0)=ROUND(SUM(F96:M96),0),"All Capital Returned","Capital Not Returned") | G94: =IF(G92="","",G100-G95) | H94: =IF(H92="","",H100-H95) | I94: =IF(I92="","",I100-I95) | J94: =IF(J92="","",J100-J95) | K94: =IF(K92="","",K100-K95) | L94: =IF(L92="","",L100-L95) | M94: =IF(M92="","",M100-M95) | N94: =IF(N92="","",N100-N95) | ... P94: =IF(P92="","",P100-P95)
B95: Req'd Return by LP to hit Hurdle 1 | F95: =IF(F92="","",IF($D$57="Equity Multiple",E96*$C92-E96,F93*Preferred_Return)) | G95: =IF(G92="","",IF($D$57="Equity Multiple",F96*$C92-F96,G93*Preferred_Return)) | H95: =IF(H92="","",IF($D$57="Equity Multiple",G96*$C92-G96,H93*Preferred_Return)) | I95: =IF(I92="","",IF($D$57="Equity Multiple",H96*$C92-H96,I93*Preferred_Return)) | J95: =IF(J92="","",IF($D$57="Equity Multiple",I96*$C92-I96,J93*Preferred_Return)) | K95: =IF(K92="","",IF($D$57="Equity Multiple",J96*$C92-J96,K93*Preferred_Return)) | L95: =IF(L92="","",IF($D$57="Equity Multiple",K96*$C92-K96,L93*Preferred_Return)) | M95: =IF(M92="","",IF($D$57="Equity Multiple",L96*$C92-L96,M93*Preferred_Return)) | ... P95: =IF(P92="","",IF($D$57="Equity Multiple",O96*$C92-O96,P93*Preferred_Return))
B96: Contributions from LP | F96: =IF(F92="","",-MIN(0,F87*Equity_Share_LP)) | G96: =IF(G92="","",-MIN(0,G87*Equity_Share_LP)) | H96: =IF(H92="","",-MIN(0,H87*Equity_Share_LP)) | I96: =IF(I92="","",-MIN(0,I87*Equity_Share_LP)) | J96: =IF(J92="","",-MIN(0,J87*Equity_Share_LP)) | K96: =IF(K92="","",-MIN(0,K87*Equity_Share_LP)) | L96: =IF(L92="","",-MIN(0,L87*Equity_Share_LP)) | M96: =IF(M92="","",-MIN(0,M87*Equity_Share_LP)) | ... P96: =IF(P92="","",-MIN(0,P87*Equity_Share_LP))
B97: Distributions to LP (Hurdle 1) | F97: =IF(F92="","",MIN(F93+F95,MAX(F87,0)*$I$15)) | G97: =IF(G92="","",MIN(G93+G95,MAX(G87,0)*$I$15)) | H97: =IF(H92="","",MIN(H93+H95,MAX(H87,0)*$I$15)) | I97: =IF(I92="","",MIN(I93+I95,MAX(I87,0)*$I$15)) | J97: =IF(J92="","",MIN(J93+J95,MAX(J87,0)*$I$15)) | K97: =IF(K92="","",MIN(K93+K95,MAX(K87,0)*$I$15)) | L97: =IF(L92="","",MIN(L93+L95,MAX(L87,0)*$I$15)) | M97: =IF(M92="","",MIN(M93+M95,MAX(M87,0)*$I$15)) | ... P97: =IF(P92="","",MIN(P93+P95,MAX(P87,0)*$I$15))
B98: Ending Balance (LP Capital Account) | F98: =IF(F92="","",F93+F95+F96-F97) | G98: =IF(G92="","",G93+G95+G96-G97) | H98: =IF(H92="","",H93+H95+H96-H97) | I98: =IF(I92="","",I93+I95+I96-I97) | J98: =IF(J92="","",J93+J95+J96-J97) | K98: =IF(K92="","",K93+K95+K96-K97) | L98: =IF(L92="","",L93+L95+L96-L97) | M98: =IF(M92="","",M93+M95+M96-M97) | ... P98: =IF(P92="","",P93+P95+P96-P97)
B99: =IF(D57="Equity Multiple", "LP EMx Check","LP IRR Check") | E99: =IF($D$57="IRR",IRR(F99:P99),SUMIF(F99:P99,">0")/-SUMIF(F99:P99,"<0")) | F99: =IF(F92="","",-F96+F97) | G99: =IF(G92="","",-G96+G97) | H99: =IF(H92="","",-H96+H97) | I99: =IF(I92="","",-I96+I97) | J99: =IF(J92="","",-J96+J97) | K99: =IF(K92="","",-K96+K97) | L99: =IF(L92="","",-L96+L97) | M99: =IF(M92="","",-M96+M97) | ... P99: =IF(P92="","",-P96+P97)
B100: Distribution to LP | F100: =IF(F92="","",MIN(F93+F95,MAX(F87,0)*$I$15)) | G100: =IF(G92="","",MIN(G93+G95,MAX(G87,0)*$I$15)) | H100: =IF(H92="","",MIN(H93+H95,MAX(H87,0)*$I$15)) | I100: =IF(I92="","",MIN(I93+I95,MAX(I87,0)*$I$15)) | J100: =IF(J92="","",MIN(J93+J95,MAX(J87,0)*$I$15)) | K100: =IF(K92="","",MIN(K93+K95,MAX(K87,0)*$I$15)) | L100: =IF(L92="","",MIN(L93+L95,MAX(L87,0)*$I$15)) | M100: =IF(M92="","",MIN(M93+M95,MAX(M87,0)*$I$15)) | ... P100: =IF(P92="","",MIN(P93+P95,MAX(P87,0)*$I$15))
B102: Beginning Balance (GP Capital Account) | F102: =IF(F92="","",E106) | G102: =IF(G92="","",F106) | H102: =IF(H92="","",G106) | I102: =IF(I92="","",H106) | J102: =IF(J92="","",I106) | K102: =IF(K92="","",J106) | L102: =IF(L92="","",K106) | M102: =IF(M92="","",L106) | ... P102: =IF(P92="","",O106)
B103: Req'd Return by GP (Pref) | F103: =IF(F92="","",IF($D$57="Equity Multiple",E104*$C92-E104,F102*Preferred_Return)) | G103: =IF(G102="","",IF($D$57="Equity Multiple",F104*$C92-F104,G102*Preferred_Return)) | H103: =IF(H102="","",IF($D$57="Equity Multiple",G104*$C92-G104,H102*Preferred_Return)) | I103: =IF(I102="","",IF($D$57="Equity Multiple",H104*$C92-H104,I102*Preferred_Return)) | J103: =IF(J102="","",IF($D$57="Equity Multiple",I104*$C92-I104,J102*Preferred_Return)) | K103: =IF(K102="","",IF($D$57="Equity Multiple",J104*$C92-J104,K102*Preferred_Return)) | L103: =IF(L102="","",IF($D$57="Equity Multiple",K104*$C92-K104,L102*Preferred_Return)) | M103: =IF(M102="","",IF($D$57="Equity Multiple",L104*$C92-L104,M102*Preferred_Return)) | N103: =IF(N102="","",IF($D$57="Equity Multiple",M104*$C92-M104,N102*Preferred_Return)) | ... P103: =IF(P102="","",IF($D$57="Equity Multiple",O104*$C92-O104,P102*Preferred_Return))
B104: Contributions from GP | F104: =IF(F92="","",-MIN(0,F87*Equity_Share_GP)) | G104: =IF(G92="","",-MIN(0,G87*Equity_Share_GP)) | H104: =IF(H92="","",-MIN(0,H87*Equity_Share_GP)) | I104: =IF(I92="","",-MIN(0,I87*Equity_Share_GP)) | J104: =IF(J92="","",-MIN(0,J87*Equity_Share_GP)) | K104: =IF(K92="","",-MIN(0,K87*Equity_Share_GP)) | L104: =IF(L92="","",-MIN(0,L87*Equity_Share_GP)) | M104: =IF(M92="","",-MIN(0,M87*Equity_Share_GP)) | ... P104: =IF(P92="","",-MIN(0,P87*Equity_Share_GP))
B105: Distribution to GP | F105: =IF(F92="","",IF(CU?,MAX(MIN(F87-F100,F102+F103+F104),0),F97/$I$15*$H$15)) | G105: =IF(G92="","",IF(CU?,MAX(MIN(G87-G100,G102+G103+G104),0),G97/$I$15*$H$15)) | H105: =IF(H92="","",IF(CU?,MAX(MIN(H87-H100,H102+H103+H104),0),H97/$I$15*$H$15)) | I105: =IF(I92="","",IF(CU?,MAX(MIN(I87-I100,I102+I103+I104),0),I97/$I$15*$H$15)) | J105: =IF(J92="","",IF(CU?,MAX(MIN(J87-J100,J102+J103+J104),0),J97/$I$15*$H$15)) | K105: =IF(K92="","",IF(CU?,MAX(MIN(K87-K100,K102+K103+K104),0),K97/$I$15*$H$15)) | L105: =IF(L92="","",IF(CU?,MAX(MIN(L87-L100,L102+L103+L104),0),L97/$I$15*$H$15)) | M105: =IF(M92="","",IF(CU?,MAX(MIN(M87-M100,M102+M103+M104),0),M97/$I$15*$H$15)) | ... P105: =IF(P92="","",IF(CU?,MAX(MIN(P87-P100,P102+P103+P104),0),P97/$I$15*$H$15))
B106: Ending Balance (GP Capital Account) | F106: =IF(F92="","",F102+F103+F104-F105) | G106: =IF(G92="","",G102+G103+G104-G105) | H106: =IF(H92="","",H102+H103+H104-H105) | I106: =IF(I92="","",I102+I103+I104-I105) | J106: =IF(J92="","",J102+J103+J104-J105) | K106: =IF(K92="","",K102+K103+K104-K105) | L106: =IF(L92="","",L102+L103+L104-L105) | M106: =IF(M92="","",M102+M103+M104-M105) | ... P106: =IF(P92="","",P102+P103+P104-P105)
B107: =IF(D57="Equity Multiple", "GP EMx Check","GP IRR Check") | E107: =IF($D$57="IRR",IFERROR(IRR(F107:P107),"NA"),SUMIF(F107:P107,">0")/-SUMIF(F107:P107,"<0")) | F107: =IF(F92="","",-F104+F105) | G107: =IF(G92="","",-G104+G105) | H107: =IF(H92="","",-H104+H105) | I107: =IF(I92="","",-I104+I105) | J107: =IF(J92="","",-J104+J105) | K107: =IF(K92="","",-K104+K105) | L107: =IF(L92="","",-L104+L105) | M107: =IF(M92="","",-M104+M105) | ... P107: =IF(P92="","",-P104+P105)
B109: ="Total Distributions ("&B91&")" | F109: =IF(F92="","",F105+F100) | G109: =IF(G92="","",G105+G100) | H109: =IF(H92="","",H105+H100) | I109: =IF(I92="","",I105+I100) | J109: =IF(J92="","",J105+J100) | K109: =IF(K92="","",K105+K100) | L109: =IF(L92="","",L105+L100) | M109: =IF(M92="","",M105+M100) | ... P109: =IF(P92="","",P105+P100)
B110: Cash Flow Remaining | F110: =IF(F92="","",MAX(F87-F109,0)) | G110: =IF(G92="","",MAX(G87-G109,0)) | H110: =IF(H92="","",MAX(H87-H109,0)) | I110: =IF(I92="","",MAX(I87-I109,0)) | J110: =IF(J92="","",MAX(J87-J109,0)) | K110: =IF(K92="","",MAX(K87-K109,0)) | L110: =IF(L92="","",MAX(L87-L109,0)) | M110: =IF(M92="","",MAX(M87-M109,0)) | ... P110: =IF(P92="","",MAX(P87-P109,0))
B112: Tier 2 | F112: Year 0 | G112: =G$21 | H112: =H$21 | I112: =I$21 | J112: =J$21 | K112: =K$21 | L112: =L$21 | M112: =M$21 | N112: =N$21 | ... P112: =P$21
B113: Return Threshold - Up to: | C113: =E61
B114: Beginning Balance (LP Capital Account) | F114: =IF(F112="","",E119) | G114: =IF(G112="","",F119) | H114: =IF(H112="","",G119) | I114: =IF(I112="","",H119) | J114: =IF(J112="","",I119) | K114: =IF(K112="","",J119) | L114: =IF(L112="","",K119) | M114: =IF(M112="","",L119) | ... P114: =IF(P112="","",O119)
B115: Req'd Return by LP to hit Hurdle 2 | F115: =IF(F112="","",IF($D$57="Equity Multiple",E116*$C113-E116,F114*$C113)) | G115: =IF(G112="","",IF($D$57="Equity Multiple",F116*$C113-F116,G114*$C113)) | H115: =IF(H112="","",IF($D$57="Equity Multiple",G116*$C113-G116,H114*$C113)) | I115: =IF(I112="","",IF($D$57="Equity Multiple",H116*$C113-H116,I114*$C113)) | J115: =IF(J112="","",IF($D$57="Equity Multiple",I116*$C113-I116,J114*$C113)) | K115: =IF(K112="","",IF($D$57="Equity Multiple",J116*$C113-J116,K114*$C113)) | L115: =IF(L112="","",IF($D$57="Equity Multiple",K116*$C113-K116,L114*$C113)) | M115: =IF(M112="","",IF($D$57="Equity Multiple",L116*$C113-L116,M114*$C113)) | ... P115: =IF(P112="","",IF($D$57="Equity Multiple",O116*$C113-O116,P114*$C113))
B116: Contributions from LP | F116: =IF(F112="","",-MIN(0,F$51*Equity_Share_LP)) | G116: =IF(G112="","",-MIN(0,G$51*Equity_Share_LP)) | H116: =IF(H112="","",-MIN(0,H$51*Equity_Share_LP)) | I116: =IF(I112="","",-MIN(0,I$51*Equity_Share_LP)) | J116: =IF(J112="","",-MIN(0,J$51*Equity_Share_LP)) | K116: =IF(K112="","",-MIN(0,K$51*Equity_Share_LP)) | L116: =IF(L112="","",-MIN(0,L$51*Equity_Share_LP)) | M116: =IF(M112="","",-MIN(0,M$51*Equity_Share_LP)) | ... P116: =IF(P112="","",-MIN(0,P$51*Equity_Share_LP))
B117: Prior Distributions | F117: =F100 | G117: =G100 | H117: =H100 | I117: =I100 | J117: =J100 | K117: =K100 | L117: =L100 | M117: =M100 | ... P117: =P100
...

Sheet Waterfall (5-yr-S1)
B2: PARTNERSHIP LEVEL RETURNS - EQUITY WATERFALL (IRR & EQUITY MULTIPLE HURDLES)
B4: Promote Hurdle Method | D4: IRR | E4: GP Catch Up?
B5: # of Tiers | D5: 3-Tier
A6: =AND(E6="Yes", H15<Equity_Share_GP) | B6: Return of Capital | D6: =IF(H15<Equity_Share_GP,"LP 1st","Pari Passu") | E6: Yes
B8: Equity Contributions | C8: % | D8: Amount
B9: General Partner (GP) | C9: ='Sources and Uses'!E8 | D9: =Equity_Share_GP*Total_Equity | K9: Error Check:
B10: Limited Partner (LP) | C10: =1-C9 | D10: =Total_Equity*Equity_Share_LP | K10: Profit Dist.:
B11: Total Equity | D11: =-SUMIF(F51:K51,"<0") | K11: Net BTCF:
B13: Hurdle Rate Method Used: | C13: =IF(D4="IRR","IRR",IF(D4="Equity Multiple","Equity Multiple",IF(D4<>"IRR + EMx","",IF(D71<D179,"IRR","Equity Multiple")))) | F13: Promote Structure Incentive Breakdown | H13: Distribution as %
B14: =IF(D4="Equity Multiple","Partnership Distribution Assumptions (Equity Multiple Hurdles)",IF(D4="IRR","Partnership Distribution Assumptions (IRR Hurdles)","Partnership Distribution Assumptions (Max of IRR or Emx Hurdles)")) | H14: GP % | I14: LP % | J14: Notes
B15: Tier 1 (Pref + Return of Capital) | C15: Equity Multiple | D15: IRR | E15: =IF($D$4="Equity Multiple",C16,D16) | F15: GP Promote | H15: =Equity_Share_GP | I15: =1-H15 | J15: =IF(I15=Equity_Share_LP,"Pref prorata to LP/GP, then Pro rata return of capital",IF(CU?,"Return of capital and Pref NOT pro rata + GP Catch Up","Return of capital and Pref NOT pro rata"))
B16: Tier 2 (Promote) | C16: 1 | D16: 0.08 | E16: =IF($D$4="Equity Multiple",IF(B277<3,"",C17),IF(B277<3,"",D17)) | F16: 0.25 | H16: =1-(Equity_Share_LP*(1-F16)) | I16: =1-H16 | J16: =IF(Equity_Share_GP<>H15,TEXT(I15,"0.0%")&"/"&TEXT(H15,"0.0%")&" to "&(IF(D4="IRR",TEXT(E15,"0.0%"),TEXT(E15,"0.0X")))&", then "&TEXT(I16,"0.0%")&"/"&TEXT(H16,"0.0%")&" to "&(IF(D4="IRR",TEXT(E16,"0.0%"),TEXT(E16,"0.0X"))),"Prorata to LP/GP to "&(IF(D4="IRR",TEXT(E15,"0.0%"),TEXT(E15,"0.0X")))&", then "&TEXT(I16,"0.0%")&"/"&TEXT(H16,"0.0%")&" to "&(IF(D4="IRR",TEXT(E16,"0.0%"),TEXT(E16,"0.0X"))))
B17: =IF(B277<3,"NOT USED","Tier 3 (Promote)") | C17: 1.5 | D17: 0.12 | E17: =IF($D$4="Equity Multiple",IF(B277<4,"",C18),IF(B277<4,"",D18)) | F17: 0.4 | H17: =1-(Equity_Share_LP*(1-F17)) | I17: =1-H17 | J17: =TEXT(I16,"0.0%")&"/"&TEXT(H16,"0.0%")&" to "&(IF(D4="IRR",TEXT(E16,"0.0%"),TEXT(E16,"0.0X")))&", then "&TEXT(I17,"0.0%")&"/"&TEXT(H17,"0.0%")&" to "&(IF(D4="IRR",TEXT(E17,"0.0%"),TEXT(E17,"0.0X")))
B18: =IF(B277<4,"NOT USED","Tier 4 (Promote)") | C18: 2 | D18: 0.15 | E18: =IF($D$4="Equity Multiple",IF(B277<5,"",C19),IF(B277<5,"",D19)) | F18: 0.4 | H18: =1-(Equity_Share_LP*(1-F18)) | I18: =1-H18 | J18: =TEXT(I17,"0.0%")&"/"&TEXT(H17,"0.0%")&" to "&(IF(D4="IRR",TEXT(E17,"0.0%"),TEXT(E17,"0.0X")))&", then "&TEXT(I18,"0.0%")&"/"&TEXT(H18,"0.0%")&" thereafter"
B19: =IF(B277<5,"NOT USED","Tier 5 (Promote)") | C19: 2.5 | D19: 0.18 | F19: 0.5 | H19: =1-(Equity_Share_LP*(1-F19)) | I19: =1-H19 | J19: =TEXT(I18,"0.0%")&"/"&TEXT(H18,"0.0%")&" to "&(IF(D6="IRR",TEXT(E18,"0.0%"),TEXT(E18,"0.0X")))&", then "&TEXT(I19,"0.0%")&"/"&TEXT(H19,"0.0%")&" thereafter"
B21: Summary of Partnership-Level Returns | D21: Analysis Period | E21: =MAX(F21:K21) | F21: 0 | G21: =IF(G47="","",F21+1) | H21: =IF(H47="","",G21+1) | I21: =IF(I47="","",H21+1) | J21: =IF(J47="","",I21+1) | K21: =IF(K47="","",J21+1)
B22: Limited Partner (LP) Returns
C23: Check
B24: Preferred Return | C24: =IF(ROUND(D24,0)=ROUND(SUM(F24:K24),0),"OK","ERROR") | D24: =(C13="IRR")*(SUM(F97:K97)-D25)+(C13="Equity Multiple")*(SUM(F205:K205)-D25) | F24: =IF(F21="","",MIN($D24-SUM($E24:E24),F27)) | G24: =IF(G21="","",MIN($D24-SUM($E24:F24),G27)) | H24: =IF(H21="","",MIN($D24-SUM($E24:G24),H27)) | I24: =IF(I21="","",MIN($D24-SUM($E24:H24),I27)) | J24: =IF(J21="","",MIN($D24-SUM($E24:I24),J27)) | K24: =IF(K21="","",MIN($D24-SUM($E24:J24),K27))
B25: Return of Capital | C25: =IF(ROUND(D25,0)=ROUND(SUM(F25:K25),0),"OK","ERROR") | D25: =MIN(D28,D27) | F25: =IF(F21="","",MIN($D25-SUM($E25:E25),F27-F24)) | G25: =IF(G21="","",MIN($D25-SUM($E25:F25),G27-G24)) | H25: =IF(H21="","",MIN($D25-SUM($E25:G25),H27-H24)) | I25: =IF(I21="","",MIN($D25-SUM($E25:H25),I27-I24)) | J25: =IF(J21="","",MIN($D25-SUM($E25:I25),J27-J24)) | K25: =IF(K21="","",MIN($D25-SUM($E25:J25),K27-K24))
B26: Excess Cash Flow | C26: =IF(ROUND(D26,0)=ROUND(SUM(F26:K26),0),"OK","ERROR") | D26: =D27-D25-D24 | F26: =IF(F21="","",F27-F25-F24) | G26: =IF(G21="","",G27-G25-G24) | H26: =IF(H21="","",H27-H25-H24) | I26: =IF(I21="","",I27-I25-I24) | J26: =IF(J21="","",J27-J25-J24) | K26: =IF(K21="","",K27-K25-K24)
B27: Total LP Distributions | D27: =SUM(F27:K27) | F27: =IF(F$21="","",($C$13="IRR")*F68+($C$13="Equity Multiple")*F176) | G27: =IF(G$21="","",($C$13="IRR")*G68+($C$13="Equity Multiple")*G176) | H27: =IF(H$21="","",($C$13="IRR")*H68+($C$13="Equity Multiple")*H176) | I27: =IF(I$21="","",($C$13="IRR")*I68+($C$13="Equity Multiple")*I176) | J27: =IF(J$21="","",($C$13="IRR")*J68+($C$13="Equity Multiple")*J176) | K27: =IF(K$21="","",($C$13="IRR")*K68+($C$13="Equity Multiple")*K176)
B28: Total LP Contributions | D28: =SUM(F28:K28) | F28: =F96 | G28: =G96 | H28: =H96 | I28: =I96 | J28: =J96 | K28: =K96
B29: Total LP Profit | D29: =D27-D28
B30: LP IRR | D30: =IRR(F30:K30) | F30: =IF(F21="","",(-F28)+F27) | G30: =IF(G21="","",(-G28)+G27) | H30: =IF(H21="","",(-H28)+H27) | I30: =IF(I21="","",(-I28)+I27) | J30: =IF(J21="","",(-J28)+J27) | K30: =IF(K21="","",(-K28)+K27)
B31: LP Equity Multiple | D31: =D27/D28 | G31: =IF($D$4="IRR", G30/G93,G30/G201) | H31: =IF($D$4="IRR", H30/H93,H30/H201) | I31: =IF($D$4="IRR", I30/I93,I30/I201) | J31: =IF($D$4="IRR", J30/J93,J30/J201) | K31: =IF($D$4="IRR", K30/K93,K30/K201)
B33: GP Returns
B34: Preferred Return | C34: =IF(ROUND(D34,0)=ROUND(SUM(F34:K34),0),"OK","ERROR") | D34: =(C13="IRR")*(SUM(F105:K105)-D35)+(C13="Equity Multiple")*(SUM(F213:K213)-D35) | F34: =IF(F21="","",MIN($D34-SUM($E34:E34),F38)) | G34: =IF(G21="","",MIN($D34-SUM($E34:F34),G38)) | H34: =IF(H21="","",MIN($D34-SUM($E34:G34),H38)) | I34: =IF(I21="","",MIN($D34-SUM($E34:H34),I38)) | J34: =IF(J21="","",MIN($D34-SUM($E34:I34),J38)) | K34: =IF(K21="","",MIN($D34-SUM($E34:J34),K38))
B35: Return of Capital | C35: =IF(ROUND(D35,0)=ROUND(SUM(F35:K35),0),"OK","ERROR") | D35: =MIN(D38,D40) | F35: =IF(F21="","",MIN($D35-SUM($E35:E35),F38-F34)) | G35: =IF(G21="","",MIN($D35-SUM($E35:F35),G38-G34)) | H35: =IF(H21="","",MIN($D35-SUM($E35:G35),H38-H34)) | I35: =IF(I21="","",MIN($D35-SUM($E35:H35),I38-I34)) | J35: =IF(J21="","",MIN($D35-SUM($E35:I35),J38-J34)) | K35: =IF(K21="","",MIN($D35-SUM($E35:J35),K38-K34))
B36: Promote | C36: =IF(ROUND(D36,0)=ROUND(SUM(F36:K36),0),"OK","ERROR") | D36: =D38-D35-D37-D34 | F36: =IF(F21="","",F38-F37-F35-F34) | G36: =IF(G21="","",G38-G37-G35-G34) | H36: =IF(H21="","",H38-H37-H35-H34) | I36: =IF(I21="","",I38-I37-I35-I34) | J36: =IF(J21="","",J38-J37-J35-J34) | K36: =IF(K21="","",K38-K37-K35-K34)
B37: Excess Cash Flow | C37: =IF(ROUND(D37,0)=ROUND(SUM(F37:K37),0),"OK","ERROR") | D37: =D26/Equity_Share_LP*Equity_Share_GP | F37: =IF(F21="","",F26/Equity_Share_LP*Equity_Share_GP) | G37: =IF(G21="","",G26/Equity_Share_LP*Equity_Share_GP) | H37: =IF(H21="","",H26/Equity_Share_LP*Equity_Share_GP) | I37: =IF(I21="","",I26/Equity_Share_LP*Equity_Share_GP) | J37: =IF(J21="","",J26/Equity_Share_LP*Equity_Share_GP) | K37: =IF(K21="","",K26/Equity_Share_LP*Equity_Share_GP)
B38: Total GP Distributions | D38: =SUM(F38:K38) | F38: =IF(F$21="","",($C$13="IRR")*F75+($C$13="Equity Multiple")*F183) | G38: =IF(G$21="","",($C$13="IRR")*G75+($C$13="Equity Multiple")*G183) | H38: =IF(H$21="","",($C$13="IRR")*H75+($C$13="Equity Multiple")*H183) | I38: =IF(I$21="","",($C$13="IRR")*I75+($C$13="Equity Multiple")*I183) | J38: =IF(J$21="","",($C$13="IRR")*J75+($C$13="Equity Multiple")*J183) | K38: =IF(K$21="","",($C$13="IRR")*K75+($C$13="Equity Multiple")*K183)
B39: Total GP Fees | D39: =SUM(F39:K39) | F39: =IF(F21="","",SUM(F48:F49)) | G39: =IF(G21="","",SUM(G48:G49)) | H39: =IF(H21="","",SUM(H48:H49)) | I39: =IF(I21="","",SUM(I48:I49)) | J39: =IF(J21="","",SUM(J48:J49)) | K39: =IF(K21="","",SUM(K48:K49))
B40: Total GP Contributions | D40: =SUM(F40:K40) | F40: =F104 | G40: =G104 | H40: =H104 | I40: =I104 | J40: =J104 | K40: =K104
B41: Total GP Profit (Including Fees) | D41: =+D38+D39-D40
B42: GP IRR | D42: =IFERROR(IRR(F42:K42),"NA") | F42: =IF(F21="","",(-F40)+F38+F39) | G42: =IF(G21="","",(-G40)+G38+G39) | H42: =IF(H21="","",(-H40)+H38+H39) | I42: =IF(I21="","",(-I40)+I38+I39) | J42: =IF(J21="","",(-J40)+J38+J39) | K42: =IF(K21="","",(-K40)+K38+K39)
B43: GP Equity Multiple | D43: =IFERROR(D38/D40,"NA")
B45: Property-Level Cash and GP Fees | F45: Year 0 | G45: =G$21 | H45: =H$21 | I45: =I$21 | J45: =J$21 | K45: =K$21
E46: Year Ending | F46: 45657 | G46: =IF(G45="","",EOMONTH(F46,12)) | H46: =IF(H45="","",EOMONTH(G46,12)) | I46: =IF(I45="","",EOMONTH(H46,12)) | J46: =IF(J45="","",EOMONTH(I46,12)) | K46: =IF(K45="","",EOMONTH(J46,12))
B47: Net Property-Level Cash Flow | F47: =-'Sources and Uses'!C7-'Sources and Uses'!C8+'Sources and Uses'!C15 | G47: ='GGC Pro Forma'!H84 | H47: ='GGC Pro Forma'!I84 | I47: ='GGC Pro Forma'!J84 | J47: ='GGC Pro Forma'!K84 | K47: ='GGC Pro Forma'!L84
B48: Asset Management Fees | F48: 0 | G48: =2%*'GGC Pro Forma'!H25 | H48: =2%*'GGC Pro Forma'!I25 | I48: =2%*'GGC Pro Forma'!J25 | J48: =2%*'GGC Pro Forma'!K25 | K48: =2%*'GGC Pro Forma'!L25
B49: Acquisition/Disposition Fees | F49: ='Sources and Uses'!C15 | G49: 0 | H49: 0 | I49: 0 | J49: 0 | K49: 0
B51: Adjusted Net Property-Level Cash Flow | F51: =IF(F45="","",F47-F48-F49) | G51: =IF(G45="","",G47-G48-G49) | H51: =IF(H45="","",H47-H48-H49) | I51: =IF(I45="","",I47-I48-I49) | J51: =IF(J45="","",J47-J48-J49) | K51: =IF(K45="","",K47-K48-K49)
B52: Levered IRR | F52: =IRR(F51:K51)
B53: Equity Multiple | F53: =SUMIF(F51:K51,">0")/-SUMIF(F51:K51,"<0")
B56: PARTNERSHIP LEVEL RETURNS - IRR EQUITY WATERFALL
D57: =$D$4
F58: Promote Structure Incentive Breakdown | H58: Distribution as %
B59: =IF(D57="Equity Multiple","Partnership Distribution Assumptions (Equity Multiple Hurdles)","Partnership Distribution Assumptions (IRR Hurdles)") | H59: GP % | I59: LP % | J59: Notes
B60: =B15 | E60: =D61 | F60: GP Promote | H60: =H15 | I60: =1-H60 | J60: =IF(I60=Equity_Share_LP,"Pref prorata to LP/GP, then Pro rata return of capital",IF(CU?,"Return of capital and Pref NOT pro rata + GP Catch Up","Return of capital and Pref NOT pro rata"))
B61: =B16 | D61: =D16 | E61: =IF($B$277<3,9.99,D62) | F61: =F16 | H61: =H16 | I61: =1-H61 | J61: =IF(Equity_Share_GP<>H60,TEXT(I60,"0.0%")&"/"&TEXT(H60,"0.0%")&" to "&(IF(D57="IRR",TEXT(E60,"0.0%"),TEXT(E60,"0.0X")))&", then "&TEXT(I61,"0.0%")&"/"&TEXT(H61,"0.0%")&" to "&(IF(D57="IRR",TEXT(E61,"0.0%"),TEXT(E61,"0.0X"))),"Prorata to LP/GP to "&(IF(D57="IRR",TEXT(E60,"0.0%"),TEXT(E60,"0.0X")))&", then "&TEXT(I61,"0.0%")&"/"&TEXT(H61,"0.0%")&" to "&(IF(D57="IRR",TEXT(E61,"0.0%"),TEXT(E61,"0.0X"))))
B62: =B17 | D62: =D17 | E62: =IF($B$277<4,9.99,D63) | F62: =F17 | H62: =H17 | I62: =1-H62 | J62: =TEXT(I61,"0.0%")&"/"&TEXT(H61,"0.0%")&" to "&(IF(D57="IRR",TEXT(E61,"0.0%"),TEXT(E61,"0.0X")))&", then "&TEXT(I62,"0.0%")&"/"&TEXT(H62,"0.0%")&" to "&(IF(D57="IRR",TEXT(E62,"0.0%"),TEXT(E62,"0.0X")))
B63: =B18 | D63: =D18 | E63: =IF($B$277<5,9.99,D64) | F63: =F18 | H63: =H18 | I63: =1-H63 | J63: =TEXT(I62,"0.0%")&"/"&TEXT(H62,"0.0%")&" to "&(IF(D58="IRR",TEXT(E62,"0.0%"),TEXT(E62,"0.0X")))&", then "&TEXT(I63,"0.0%")&"/"&TEXT(H63,"0.0%")&" to "&(IF(D58="IRR",TEXT(E63,"0.0%"),TEXT(E63,"0.0X")))
B64: =B19 | D64: =D19 | F64: =F19 | H64: =H19 | I64: =1-H64 | J64: =TEXT(I63,"0.0%")&"/"&TEXT(H63,"0.0%")&" to "&(IF(D59="IRR",TEXT(E63,"0.0%"),TEXT(E63,"0.0X")))&", then "&TEXT(I64,"0.0%")&"/"&TEXT(H64,"0.0%")&" to "&(IF(D59="IRR",TEXT(E64,"0.0%"),TEXT(E64,"0.0X")))
B66: Summary of Partnership-Level Returns | F66: 0 | G66: =IF(G84="","",F66+1) | H66: =IF(H84="","",G66+1) | I66: =IF(I84="","",H66+1) | J66: =IF(J84="","",I66+1) | K66: =IF(K84="","",J66+1)
B67: Limited Partner (LP) Returns
B68: Total LP Distributions | D68: =SUM(F68:K68) | F68: =IF(F66="","",F100+F122+F137+F152+F159) | G68: =IF(G66="","",G100+G122+G137+G152+G159) | H68: =IF(H66="","",H100+H122+H137+H152+H159) | I68: =IF(I66="","",I100+I122+I137+I152+I159) | J68: =IF(J66="","",J100+J122+J137+J152+J159) | K68: =IF(K66="","",K100+K122+K137+K152+K159)
B69: Total LP Contributions | D69: =SUM(F69:K69) | F69: =F96 | G69: =G96 | H69: =H96 | I69: =I96 | J69: =J96 | K69: =K96
B70: Total LP Profit | D70: =D68-D69
B71: LP IRR | D71: =IRR(F71:K71) | F71: =IF(F66="","",(-F69)+F68) | G71: =IF(G66="","",(-G69)+G68) | H71: =IF(H66="","",(-H69)+H68) | I71: =IF(I66="","",(-I69)+I68) | J71: =IF(J66="","",(-J69)+J68) | K71: =IF(K66="","",(-K69)+K68)
B72: LP Equity Multiple | D72: =D68/D69
B74: GP Returns
B75: Total GP Distributions | D75: =SUM(F75:K75) | F75: =IF(F66="","",F105+F123+F138+F153+F160) | G75: =IF(G66="","",G105+G123+G138+G153+G160) | H75: =IF(H66="","",H105+H123+H138+H153+H160) | I75: =IF(I66="","",I105+I123+I138+I153+I160) | J75: =IF(J66="","",J105+J123+J138+J153+J160) | K75: =IF(K66="","",K105+K123+K138+K153+K160)
B76: Total GP Fees | D76: =SUM(F76:K76) | F76: =IF(F66="","",SUM(F85:F86)) | G76: =IF(G66="","",SUM(G85:G86)) | H76: =IF(H66="","",SUM(H85:H86)) | I76: =IF(I66="","",SUM(I85:I86)) | J76: =IF(J66="","",SUM(J85:J86)) | K76: =IF(K66="","",SUM(K85:K86))
B77: Total GP Contributions | D77: =SUM(F77:K77) | F77: =IF(F66="","",-(MIN(F87,0)+F96)) | G77: =IF(G66="","",-(MIN(G87,0)+G96)) | H77: =IF(H66="","",-(MIN(H87,0)+H96)) | I77: =IF(I66="","",-(MIN(I87,0)+I96)) | J77: =IF(J66="","",-(MIN(J87,0)+J96)) | K77: =IF(K66="","",-(MIN(K87,0)+K96))
B78: Total GP Profit | D78: =+D75+D76-D77
B79: GP IRR | D79: =IFERROR(IRR(F79:K79),"NA") | F79: =IF(F66="","",(-F77)+F75+F76) | G79: =IF(G66="","",(-G77)+G75+G76) | H79: =IF(H66="","",(-H77)+H75+H76) | I79: =IF(I66="","",(-I77)+I75+I76) | J79: =IF(J66="","",(-J77)+J75+J76) | K79: =IF(K66="","",(-K77)+K75+K76)
B80: GP Equity Multiple | D80: =IFERROR(D75/D77,"NA")
B82: Property-Level Cash and GP Fees | F82: Year 0 | G82: =G$21 | H82: =H$21 | I82: =I$21 | J82: =J$21 | K82: =K$21
E83: Year Ending | F83: =IF(F46="","",F46) | G83: =IF(G46="","",G46) | H83: =IF(H46="","",H46) | I83: =IF(I46="","",I46) | J83: =IF(J46="","",J46) | K83: =IF(K46="","",K46)
B84: Net Property-Level Cash Flow | F84: =IF(F47="","",F47) | G84: =IF(G47="","",G47) | H84: =IF(H47="","",H47) | I84: =IF(I47="","",I47) | J84: =IF(J47="","",J47) | K84: =IF(K47="","",K47)
B85: =IF(B48="","",B48) | F85: =IF(F48="","",F48) | G85: =IF(G48="","",G48) | H85: =IF(H48="","",H48) | I85: =IF(I48="","",I48) | J85: =IF(J48="","",J48) | K85: =IF(K48="","",K48)
B86: =IF(B49="","",B49) | F86: =IF(F49="","",F49) | G86: =IF(G49="","",G49) | H86: =IF(H49="","",H49) | I86: =IF(I49="","",I49) | J86: =IF(J49="","",J49) | K86: =IF(K49="","",K49)
B87: Adjusted Net Property-Level Cash Flow | F87: =IF(F82="","",F84-F85-F86) | G87: =IF(G82="","",G84-G85-G86) | H87: =IF(H82="","",H84-H85-H86) | I87: =IF(I82="","",I84-I85-I86) | J87: =IF(J82="","",J84-J85-J86) | K87: =IF(K82="","",K84-K85-K86)
B88: Levered IRR | F88: =IRR(F87:K87)
B89: Equity Multiple | F89: =SUMIF(F87:K87,">0")/-SUMIF(F87:K87,"<0")
B91: Tier 1 - Preferred Return + Return of Capital
B92: Return Threshold - Up to: | C92: =E60 | F92: Year 0 | G92: =G$21 | H92: =H$21 | I92: =I$21 | J92: =J$21 | K92: =K$21
B93: Beginning Balance (LP Capital Account) | F93: =IF(F92="","",E98) | G93: =IF(G92="","",F98) | H93: =IF(H92="","",G98) | I93: =IF(I92="","",H98) | J93: =IF(J92="","",I98) | K93: =IF(K92="","",J98)
B94: LP Return of Capital | F94: =IF(ROUND(SUM(G94:K94),0)=ROUND(SUM(F96:K96),0),"All Capital Returned","Capital Not Returned") | G94: =IF(G92="","",G100-G95) | H94: =IF(H92="","",H100-H95) | I94: =IF(I92="","",I100-I95) | J94: =IF(J92="","",J100-J95) | K94: =IF(K92="","",K100-K95)
B95: Req'd Return by LP to hit Hurdle 1 | F95: =IF(F92="","",IF($D$57="Equity Multiple",E96*$C92-E96,F93*Preferred_Return)) | G95: =IF(G92="","",IF($D$57="Equity Multiple",F96*$C92-F96,G93*Preferred_Return)) | H95: =IF(H92="","",IF($D$57="Equity Multiple",G96*$C92-G96,H93*Preferred_Return)) | I95: =IF(I92="","",IF($D$57="Equity Multiple",H96*$C92-H96,I93*Preferred_Return)) | J95: =IF(J92="","",IF($D$57="Equity Multiple",I96*$C92-I96,J93*Preferred_Return)) | K95: =IF(K92="","",IF($D$57="Equity Multiple",J96*$C92-J96,K93*Preferred_Return))
B96: Contributions from LP | F96: =IF(F92="","",-MIN(0,F87*Equity_Share_LP)) | G96: =IF(G92="","",-MIN(0,G87*Equity_Share_LP)) | H96: =IF(H92="","",-MIN(0,H87*Equity_Share_LP)) | I96: =IF(I92="","",-MIN(0,I87*Equity_Share_LP)) | J96: =IF(J92="","",-MIN(0,J87*Equity_Share_LP)) | K96: =IF(K92="","",-MIN(0,K87*Equity_Share_LP))
B97: Distributions to LP (Hurdle 1) | F97: =IF(F92="","",MIN(F93+F95,MAX(F87,0)*$I$15)) | G97: =IF(G92="","",MIN(G93+G95,MAX(G87,0)*$I$15)) | H97: =IF(H92="","",MIN(H93+H95,MAX(H87,0)*$I$15)) | I97: =IF(I92="","",MIN(I93+I95,MAX(I87,0)*$I$15)) | J97: =IF(J92="","",MIN(J93+J95,MAX(J87,0)*$I$15)) | K97: =IF(K92="","",MIN(K93+K95,MAX(K87,0)*$I$15))
B98: Ending Balance (LP Capital Account) | F98: =IF(F92="","",F93+F95+F96-F97) | G98: =IF(G92="","",G93+G95+G96-G97) | H98: =IF(H92="","",H93+H95+H96-H97) | I98: =IF(I92="","",I93+I95+I96-I97) | J98: =IF(J92="","",J93+J95+J96-J97) | K98: =IF(K92="","",K93+K95+K96-K97)
B99: =IF(D57="Equity Multiple", "LP EMx Check","LP IRR Check") | E99: =IF($D$57="IRR",IRR(F99:K99),SUMIF(F99:K99,">0")/-SUMIF(F99:K99,"<0")) | F99: =IF(F92="","",-F96+F97) | G99: =IF(G92="","",-G96+G97) | H99: =IF(H92="","",-H96+H97) | I99: =IF(I92="","",-I96+I97) | J99: =IF(J92="","",-J96+J97) | K99: =IF(K92="","",-K96+K97)
B100: Distribution to LP | F100: =IF(F92="","",MIN(F93+F95,MAX(F87,0)*$I$15)) | G100: =IF(G92="","",MIN(G93+G95,MAX(G87,0)*$I$15)) | H100: =IF(H92="","",MIN(H93+H95,MAX(H87,0)*$I$15)) | I100: =IF(I92="","",MIN(I93+I95,MAX(I87,0)*$I$15)) | J100: =IF(J92="","",MIN(J93+J95,MAX(J87,0)*$I$15)) | K100: =IF(K92="","",MIN(K93+K95,MAX(K87,0)*$I$15))
B102: Beginning Balance (GP Capital Account) | F102: =IF(F92="","",E106) | G102: =IF(G92="","",F106) | H102: =IF(H92="","",G106) | I102: =IF(I92="","",H106) | J102: =IF(J92="","",I106) | K102: =IF(K92="","",J106)
B103: Req'd Return by GP (Pref) | F103: =IF(F92="","",IF($D$57="Equity Multiple",E104*$C92-E104,F102*Preferred_Return)) | G103: =IF(G102="","",IF($D$57="Equity Multiple",F104*$C92-F104,G102*Preferred_Return)) | H103: =IF(H102="","",IF($D$57="Equity Multiple",G104*$C92-G104,H102*Preferred_Return)) | I103: =IF(I102="","",IF($D$57="Equity Multiple",H104*$C92-H104,I102*Preferred_Return)) | J103: =IF(J102="","",IF($D$57="Equity Multiple",I104*$C92-I104,J102*Preferred_Return)) | K103: =IF(K102="","",IF($D$57="Equity Multiple",J104*$C92-J104,K102*Preferred_Return))
B104: Contributions from GP | F104: =IF(F92="","",-MIN(0,F87*Equity_Share_GP)) | G104: =IF(G92="","",-MIN(0,G87*Equity_Share_GP)) | H104: =IF(H92="","",-MIN(0,H87*Equity_Share_GP)) | I104: =IF(I92="","",-MIN(0,I87*Equity_Share_GP)) | J104: =IF(J92="","",-MIN(0,J87*Equity_Share_GP)) | K104: =IF(K92="","",-MIN(0,K87*Equity_Share_GP))
B105: Distribution to GP | F105: =IF(F92="","",IF(CU?,MAX(MIN(F87-F100,F102+F103+F104),0),F97/$I$15*$H$15)) | G105: =IF(G92="","",IF(CU?,MAX(MIN(G87-G100,G102+G103+G104),0),G97/$I$15*$H$15)) | H105: =IF(H92="","",IF(CU?,MAX(MIN(H87-H100,H102+H103+H104),0),H97/$I$15*$H$15)) | I105: =IF(I92="","",IF(CU?,MAX(MIN(I87-I100,I102+I103+I104),0),I97/$I$15*$H$15)) | J105: =IF(J92="","",IF(CU?,MAX(MIN(J87-J100,J102+J103+J104),0),J97/$I$15*$H$15)) | K105: =IF(K92="","",IF(CU?,MAX(MIN(K87-K100,K102+K103+K104),0),K97/$I$15*$H$15))
B106: Ending Balance (GP Capital Account) | F106: =IF(F92="","",F102+F103+F104-F105) | G106: =IF(G92="","",G102+G103+G104-G105) | H106: =IF(H92="","",H102+H103+H104-H105) | I106: =IF(I92="","",I102+I103+I104-I105) | J106: =IF(J92="","",J102+J103+J104-J105) | K106: =IF(K92="","",K102+K103+K104-K105)
B107: =IF(D57="Equity Multiple", "GP EMx Check","GP IRR Check") | E107: =IF($D$57="IRR",IFERROR(IRR(F107:K107),"NA"),SUMIF(F107:K107,">0")/-SUMIF(F107:K107,"<0")) | F107: =IF(F92="","",-F104+F105) | G107: =IF(G92="","",-G104+G105) | H107: =IF(H92="","",-H104+H105) | I107: =IF(I92="","",-I104+I105) | J107: =IF(J92="","",-J104+J105) | K107: =IF(K92="","",-K104+K105)
B109: ="Total Distributions ("&B91&")" | F109: =IF(F92="","",F105+F100) | G109: =IF(G92="","",G105+G100) | H109: =IF(H92="","",H105+H100) | I109: =IF(I92="","",I105+I100) | J109: =IF(J92="","",J105+J100) | K109: =IF(K92="","",K105+K100)
B110: Cash Flow Remaining | F110: =IF(F92="","",MAX(F87-F109,0)) | G110: =IF(G92="","",MAX(G87-G109,0)) | H110: =IF(H92="","",MAX(H87-H109,0)) | I110: =IF(I92="","",MAX(I87-I109,0)) | J110: =IF(J92="","",MAX(J87-J109,0)) | K110: =IF(K92="","",MAX(K87-K109,0))
B112: Tier 2 | F112: Year 0 | G112: =G$21 | H112: =H$21 | I112: =I$21 | J112: =J$21 | K112: =K$21
B113: Return Threshold - Up to: | C113: =E61
B114: Beginning Balance (LP Capital Account) | F114: =IF(F112="","",E119) | G114: =IF(G112="","",F119) | H114: =IF(H112="","",G119) | I114: =IF(I112="","",H119) | J114: =IF(J112="","",I119) | K114: =IF(K112="","",J119)
B115: Req'd Return by LP to hit Hurdle 2 | F115: =IF(F112="","",IF($D$57="Equity Multiple",E116*$C113-E116,F114*$C113)) | G115: =IF(G112="","",IF($D$57="Equity Multiple",F116*$C113-F116,G114*$C113)) | H115: =IF(H112="","",IF($D$57="Equity Multiple",G116*$C113-G116,H114*$C113)) | I115: =IF(I112="","",IF($D$57="Equity Multiple",H116*$C113-H116,I114*$C113)) | J115: =IF(J112="","",IF($D$57="Equity Multiple",I116*$C113-I116,J114*$C113)) | K115: =IF(K112="","",IF($D$57="Equity Multiple",J116*$C113-J116,K114*$C113))
B116: Contributions from LP | F116: =IF(F112="","",-MIN(0,F$51*Equity_Share_LP)) | G116: =IF(G112="","",-MIN(0,G$51*Equity_Share_LP)) | H116: =IF(H112="","",-MIN(0,H$51*Equity_Share_LP)) | I116: =IF(I112="","",-MIN(0,I$51*Equity_Share_LP)) | J116: =IF(J112="","",-MIN(0,J$51*Equity_Share_LP)) | K116: =IF(K112="","",-MIN(0,K$51*Equity_Share_LP))
B117: Prior Distributions | F117: =F100 | G117: =G100 | H117: =H100 | I117: =I100 | J117: =J100 | K117: =K100
...

Sheet Sources and Uses
A1: GARY GROUP CAPITAL
H3: S2
B4: Sources of Funds | D4: / Unit | H4: Sources of Funds | J4: / Unit
B5: Senior Loan | C5: ='Loan Scenario (acquisition)'!C31 | D5: =C5/'GGC Underwriting'!$N$7 | H5: Senior Loan | I5: ='Loan Scenario (acquisition)'!C31 | J5: =I5/'GGC Underwriting'!$N$7
B6: Mezz Debt | C6: 0 | D6: =C6/'GGC Underwriting'!$N$7 | H6: Seller note | I6: 0 | J6: =I6/'GGC Underwriting'!$N$7
B7: LP - Equity | C7: =C18-C5-C6-C8 | D7: =C7/'GGC Underwriting'!$N$7 | H7: LP - Equity | I7: =I18-I5-I6-I8 | J7: =I7/'GGC Underwriting'!$N$7
B8: GP | C8: =C15 | D8: =C8/'GGC Underwriting'!$N$7 | E8: =C8/(C7+C8) | H8: GP | I8: =I15 | J8: =I8/'GGC Underwriting'!$N$7 | K8: =I8/(I7+I8)
B9: Total | C9: =C5+C6+C7+C8 | D9: =C9/'GGC Underwriting'!$N$7 | H9: Total | I9: =I5+I6+I7+I8 | J9: =I9/'GGC Underwriting'!$N$7
B12: Uses of Funds of Funds | D12: / Unit | H12: Uses of Funds of Funds | J12: / Unit
B13: Purchase Price | C13: ='GGC Underwriting'!P4 | D13: =C13/'GGC Underwriting'!$N$7 | H13: Purchase Price | I13: ='GGC Underwriting'!P4 | J13: =I13/'GGC Underwriting'!$N$7
B14: Closing Costs | C14: =C13*1.5% | D14: =C14/'GGC Underwriting'!$N$7 | H14: Closing Costs | I14: =I13*1.5% | J14: =I14/'GGC Underwriting'!$N$7
B15: Acquistion Fee (2%) | C15: =C13*2% | D15: =C15/'GGC Underwriting'!$N$7 | H15: Acquistion Fee (2%) | I15: =I13*2% | J15: =I15/'GGC Underwriting'!$N$7
B16: Equity Broker Fee (3%) | C16: =3%*C20 | D16: =C16/'GGC Underwriting'!$N$7 | H16: Equity Broker Fee (3%) | I16: =3%*I20 | J16: =I16/'GGC Underwriting'!$N$7
B17: Capex Budget | C17: =C24 | D17: =C17/'GGC Underwriting'!$N$7 | H17: Capex Budget | I17: =I24 | J17: =I17/'GGC Underwriting'!$N$7 | K17: Working Capital
B18: Total | C18: =SUM(C13:C17) | D18: =C18/'GGC Underwriting'!$N$7 | H18: Total | I18: =SUM(I13:I17) | J18: =I18/'GGC Underwriting'!$N$7
B21: Water / Septic / Utilities | C21: 0 | I21: 0
B22: Add Homes / In-fill | C22: 0 | I22: 0
B23: Working Capital | C23: 200000 | I23: 200000
B24: Capex Budget Total | C24: =SUM(C21:C23) | I24: =SUM(I21:I23)
L93: =-'Loan Scenario (acquisition)'!J66-

Sheet Loan Scenario (acquisition)
A1: GARY GROUP CAPITAL
B3: Loan Sizing | F3: Loan Amortization Schedule
C4: = INPUT VALUE
B6: Lender | F6: Payment # | G6: Payment Amt | H6: Interest | I6: Principal | J6: Remaining Balance | M6: Yr 1 | N6: Yr 2 | O6: Yr 3 | P6: Yr 4 | Q6: Yr 5 | R6: Yr 6 | S6: Yr 7 | T6: Yr 8 | U6: Yr 9 | V6: Yr 10 | W6: Total
B7: Fixed or Floating | C7: Fixed | F7: 1 | G7: =$C$39 | H7: =(C31*C16)/12 | I7: 0 | J7: =C31-I7 | L7: Principle | M7: =SUM(I7:I18) | N7: =SUM(I19:I30) | O7: =SUM(I31:I42) | P7: =SUM(I43:I54) | Q7: =SUM(I55:I66) | R7: =SUM(I67:I78) | S7: =SUM(I79:I90) | T7: =SUM(I91:I102) | U7: =SUM(I103:I114) | V7: =SUM(I115:I126) | W7: =SUM(M7:V7)
B8: Term (months) | C8: 120 | F8: 2 | G8: =$C$39 | H8: =(J7*$C$16)/12 | I8: 0 | J8: =J7-I8 | L8: Interest | M8: =SUM(H7:H18) | N8: =SUM(H19:H30) | O8: =SUM(H31:H42) | P8: =SUM(H42:H53) | Q8: =SUM(H55:H66) | R8: =SUM(H67:H78) | S8: =SUM(H79:H90) | T8: =SUM(H81:H92) | U8: =SUM(H91:H102) | V8: =SUM(H115:H126) | W8: =SUM(M8:V8)
B9: IO Period (months) | C9: 24 | F9: 3 | G9: =$C$39 | H9: =(J8*$C$16)/12 | I9: 0 | J9: =J8-I9 | L9: Payoff | V9: 0 | W9: =SUM(M9:V9)
B10: Amortization (months) | C10: =30*12 | F10: 4 | G10: =$C$39 | H10: =(J9*$C$16)/12 | I10: 0 | J10: =J9-I10 | L10: Total | M10: =M7+M8+M9 | N10: =N7+N8+N9 | O10: =O7+O8+O9 | P10: =P7+P8+P9 | Q10: =Q7+Q8+Q9 | R10: =R7+R8+R9 | S10: =S7+S8+S9 | T10: =T7+T8+T9 | ... V10: =V7+V8+V9 | W10: =SUM(M10:V10)
B11: Prepayment Structure | C11: Yield Maintenance | F11: 5 | G11: =$C$39 | H11: =(J10*$C$16)/12 | I11: 0 | J11: =J10-I11
F12: 6 | G12: =$C$39 | H12: =(J11*$C$16)/12 | I12: 0 | J12: =J11-I12
B13: Interest Rate Stack | F13: 7 | G13: =$C$39 | H13: =(J12*$C$16)/12 | I13: 0 | J13: =J12-I13
B14: US Treasury or SOFR | C14: 0.0405 | F14: 8 | G14: =$C$39 | H14: =(J13*$C$16)/12 | I14: 0 | J14: =J13-I14
B15: Spread | C15: 0.0185 | F15: 9 | G15: =$C$39 | H15: =(J14*$C$16)/12 | I15: 0 | J15: =J14-I15
B16: Total Interest Rate | C16: =C14+C15 | F16: 10 | G16: =$C$39 | H16: =(J15*$C$16)/12 | I16: 0 | J16: =J15-I16
B17: Mortgage Costant | C17: =IFERROR(PMT(C16/12,C$10,(-1))*12," ") | F17: 11 | G17: =$C$39 | H17: =(J16*$C$16)/12 | I17: 0 | J17: =J16-I17
F18: 12 | G18: =$C$39 | H18: =(J17*$C$16)/12 | I18: 0 | J18: =J17-I18
B19: Purchase Price | C19: ='Sources and Uses'!C13 | F19: 13 | G19: =$C$39 | H19: =(J18*$C$16)/12 | I19: 0 | J19: =J18-I19
B20: Closing Costs | C20: 0 | F20: 14 | G20: =$C$39 | H20: =(J19*$C$16)/12 | I20: 0 | J20: =J19-I20
B21: Capital Expenditure | C21: ='Sources and Uses'!C17 | F21: 15 | G21: =$C$39 | H21: =(J20*$C$16)/12 | I21: 0 | J21: =J20-I21
B22: Total Cost Basis | C22: =C19+C20+C21 | F22: 16 | G22: =$C$39 | H22: =(J21*$C$16)/12 | I22: 0 | J22: =J21-I22
F23: 17 | G23: =$C$39 | H23: =(J22*$C$16)/12 | I23: 0 | J23: =J22-I23
B24: Max Loan to Value | C24: 0.7 | F24: 18 | G24: =$C$39 | H24: =(J23*$C$16)/12 | I24: 0 | J24: =J23-I24
B25: Min DSCR | C25: 1.25 | F25: 19 | G25: =$C$39 | H25: =(J24*$C$16)/12 | I25: 0 | J25: =J24-I25
F26: 20 | G26: =$C$39 | H26: =(J25*$C$16)/12 | I26: 0 | J26: =J25-I26
A27: Lot Rents | B27: Net Operating Income | C27: ='GGC Underwriting'!I47 | F27: 21 | G27: =$C$39 | H27: =(J26*$C$16)/12 | I27: 0 | J27: =J26-I27
F28: 22 | G28: =$C$39 | H28: =(J27*$C$16)/12 | I28: 0 | J28: =J27-I28
B29: LTV Loan Amount | C29: =C24*(C19+C20) | F29: 23 | G29: =$C$39 | H29: =(J28*$C$16)/12 | I29: 0 | J29: =J28-I29
B30: DSCR Loan Amount | C30: =C27/C25/C17 | F30: 24 | G30: =$C$39 | H30: =(J29*$C$16)/12 | I30: 0 | J30: =J29-I30
B31: Max Loan Amount | C31: =MIN(C29,C30) | F31: 25 | G31: =$C$39 | H31: =(J30*$C$16)/12 | I31: =G31-H31 | J31: =J30-I31
F32: 26 | G32: =$C$39 | H32: =(J31*$C$16)/12 | I32: =G32-H32 | J32: =J31-I32
B33: Actual Loan to Value | C33: =C31/(C19+C20) | F33: 27 | G33: =$C$39 | H33: =(J32*$C$16)/12 | I33: =G33-H33 | J33: =J32-I33
B34: Actual Loan to Cost | C34: =-C31/C22 | F34: 28 | G34: =$C$39 | H34: =(J33*$C$16)/12 | I34: =G34-H34 | J34: =J33-I34
B35: Actual DSCR | C35: =C27/(C31*C17) | F35: 29 | G35: =$C$39 | H35: =(J34*$C$16)/12 | I35: =G35-H35 | J35: =J34-I35
B36: Actual Debt Yield | C36: =C27/C31 | F36: 30 | G36: =$C$39 | H36: =(J35*$C$16)/12 | I36: =G36-H36 | J36: =J35-I36
F37: 31 | G37: =$C$39 | H37: =(J36*$C$16)/12 | I37: =G37-H37 | J37: =J36-I37
B38: Annual Debt Service | C38: =C31*C17 | F38: 32 | G38: =$C$39 | H38: =(J37*$C$16)/12 | I38: =G38-H38 | J38: =J37-I38
B39: Monthly Debt Service | C39: =C38/12 | F39: 33 | G39: =$C$39 | H39: =(J38*$C$16)/12 | I39: =G39-H39 | J39: =J38-I39
F40: 34 | G40: =$C$39 | H40: =(J39*$C$16)/12 | I40: =G40-H40 | J40: =J39-I40
F41: 35 | G41: =$C$39 | H41: =(J40*$C$16)/12 | I41: =G41-H41 | J41: =J40-I41
F42: 36 | G42: =$C$39 | H42: =(J41*$C$16)/12 | I42: =G42-H42 | J42: =J41-I42
F43: 37 | G43: =$C$39 | H43: =(J42*$C$16)/12 | I43: =G43-H43 | J43: =J42-I43
F44: 38 | G44: =$C$39 | H44: =(J43*$C$16)/12 | I44: =G44-H44 | J44: =J43-I44
